Workbook

Sheet Dashboard
A1: INDIA CPI INFLATION — INTERVIEW DASHBOARD
A4: CPI case study covering category contribution, inflation trends, COVID impact, food dynamics and imported-oil relationships.
A6: Q1 — Top Contribution | C6: Q2 — Highest Full-Year YoY | E6: Q3 — Food 12M Change | G6: Q4 — Headline Pre → Post | J6: Q5 — Strongest Correlation
A7: ='Q1 Contribution'!B21 -> Pan, Tobacco & Intoxicants | C7: ='Q2 Calculation'!B23 -> 2022 | E7: ="May-22 → May-23" -> May-22 → May-23 | G7: =TEXT('Q4 Calculation'!Q4,"0.00%")&" → "&TEXT('Q4 Calculation'!R4,"0.00%") -> 4.76% → 5.80% | J7: ='Q5 Calculation'!B73 -> Oils and fats
A8: ='Q1 Contribution'!D21 -> 0.10162387 | C8: ='Q2 Calculation'!D23 -> 0.066219355 | E8: ='Q3 Calculation'!B36 -> 0.030112316 | G8: ='Q4 Calculation'!S4 -> 0.010482467 | J8: ='Q5 Calculation'!B74 -> 0.40446503
A11: Q1 Analysis | C11: Q2 Calculation | E11: Q3 Calculation | G11: Q4 Calculation | I11: Q5 Calculation | K11: Project Guide
A13: Q1 — CPI Contribution | G13: Q2 — Annual Inflation Trend
M15: Q1 — CPI Basket
M16: The basket is broadly distributed across categories.
M17: Pan, Tobacco & Intoxicants has the
M18: highest calculated contribution, while Transport & Communication has the lowest..
M19: calculated contribution, while Transport & Communication has the lowest.
A31: Q3 — Food Inflation | G31: Q4 — COVID Impact
A38: Q2 — Inflation Trend | D38: Full-year YoY inflation peaked at 6.62% in 2022, reflecting global commodity shocks, food and energy pressures, supply constraints and pass-through into core prices.
A40: Q3 — Food | D40: Food prices remained volatile, with a 3.01% increase in the Food Index from May 2022 to May 2023. Spices showed the largest individual index increase.
A42: Q4 — COVID-19 | D42: Average headline inflation rose by about 1.05 percentage points after the March 2020 COVID reference point. Food and essential services rose, while health behaved differently.
A47: Q5 — Imported Oil vs CPI
A64: Q5 — Imported Oil | D64: I compared monthly changes in imported crude oil prices with inflation changes across CPI categories from 2021 to 2023.Oil prices showed major fluctuations, especially around 2022. Using Excel’s CORREL function, I checked which categories moved most closely with oil prices.Oils & Fats had the highest positive correlation at 0.404. This means Oils & Fats prices tended to move in the same direction as oil prices.However, the relationship was only moderate, not very strong.Fuel & Light also showed a relatively weak relationship.This shows that oil-price changes do not immediately or equally affect all CPI categories.Taxes, exchange rates and domestic pricing can delay or reduce the impact. Overall, oil prices influence inflation, but the impact is not immediate or one-to-one.

Sheet Project Guide
A1: India CPI Inflation Case Study — Project Guide
A4: Purpose | B4: Interview-ready analysis of India CPI inflation, category contribution, annual inflation, COVID impact, food inflation and imported crude-oil relationships.
A6: Questions Covered
A8: Q1 | B8: CPI contribution by broader categories — latest month May 2023; equal-weighted category construction.
A9: Q2 | B9: Annual Rural+Urban CPI YoY inflation from 2017; 2023 shown separately as Jan–May YTD.
A10: Q3 | B10: Food inflation over the 12 months ending May 2023, including MoM movement and biggest food-category change.
A11: Q4 | B11: COVID-19 impact using March 2020 as the reference milestone; pre/post 12-month comparison plus category focus.
A12: Q5 | B12: Imported Indian Basket crude-oil MoM changes for 2021–2023 and correlation with CPI-category MoM changes.
A15: Key Methodology / Interview Points
A17: Q1 | B17: AVERAGE for equal-weighted broader categories; contribution = category index ÷ sum of broader-category indices.
A18: Q2 | B18: Annual CPI = AVERAGEIFS of monthly General Index; YoY = current annual average ÷ previous annual average − 1.
A19: Q3 | B19: Food Index = AVERAGE of mapped food components; MoM = current index ÷ prior-month index − 1; absolute 12-month change by subtraction.
A20: Q4 | B20: Monthly YoY = current CPI ÷ same month previous year − 1; compare Apr-2019–Mar-2020 with Apr-2020–Mar-2021.
A21: Q5 | B21: MoM oil/CPI momentum followed by CORREL; ABS and RANK used to compare relationship strength. Correlation ≠ causation.
A24: Data Sources & Caveats
A26: • | B26: Primary CPI source: provided All-India CPI dataset; cleaned version retains 372 data rows and 30 columns.
A27: • | B27: Q5 oil source: Indian Basket crude-oil monthly price series; CPI correlation is limited to the overlapping CPI period Jan-2021 to May-2023 because the provided CPI dataset ends in May 2023.
A28: • | B28: Q2 and Q4 use linear interpolation only where required by the specific analysis and flag those observations; this does not alter the raw/clean source sheets.
A29: • | B29: Q1 uses equal weights across detailed categories because that is the case-study instruction, not the official CPI weighting system.
A30: • | B30: Q4 Essential Services is an analytical composite of Fuel & Light, Household Goods & Services and Transport & Communication; it is not an official CPI basket category.
A33: Interview Story — 60 Seconds
A34: I cleaned and standardized the CPI data, mapped detailed categories into broader analytical groups, and built five analyses. I first quantified how categories contribute to the CPI basket, then calculated annual inflation trends. I used March 2020 as a COVID milestone to compare pre- and post-onset inflation, and separately tested food inflation dynamics. Finally, I joined imported Indian Basket crude-oil prices with CPI data, calculated MoM movements and used CORREL to identify categories most associated with oil-price fluctuations. The key analytical point is that correlation indicates association, not causation, and monthly pass-through can be delayed or muted by taxes, administered prices, exchange rates and other supply shocks.

Sheet Raw Data
A1: Sector | B1: Year | C1: Month | D1: Cereals and products | E1: Meat and fish | F1: Egg | G1: Milk and products | H1: Oils and fats | I1: Fruits | J1: Vegetables | K1: Pulses and products | L1: Sugar and Confectionery | M1: Spices | N1: Non-alcoholic beverages | O1: Prepared meals, snacks, sweets etc. | P1: Food and beverages | Q1: Pan, tobacco and intoxicants | R1: Clothing | S1: Footwear | T1: Clothing and footwear | U1: Housing | V1: Fuel and light | W1: Household goods and services | X1: Health | Y1: Transport and communication | Z1: Recreation and amusement | AA1: Education | AB1: Personal care and effects | AC1: Miscellaneous | AD1: General index
A2: Rural | B2: 2013 | C2: January | D2: 107.5 | E2: 106.3 | F2: 108.1 | G2: 104.9 | H2: 106.1 | I2: 103.9 | J2: 101.9 | K2: 106.1 | L2: 106.8 | M2: 103.1 | N2: 104.8 | O2: 106.7 | P2: 105.5 | Q2: 105.1 | R2: 106.5 | S2: 105.8 | T2: 106.4 | V2: 105.5 | W2: 104.8 | X2: 104 | Y2: 103.3 | Z2: 103.4 | AA2: 103.8 | AB2: 104.7 | AC2: 104 | AD2: 105.1 | AE2: ← Dashboard
A3: Urban | B3: 2013 | C3: January | D3: 110.5 | E3: 109.1 | F3: 113 | G3: 103.6 | H3: 103.4 | I3: 102.3 | J3: 102.9 | K3: 105.8 | L3: 105.1 | M3: 101.8 | N3: 105.1 | O3: 107.9 | P3: 105.9 | Q3: 105.2 | R3: 105.9 | S3: 105 | T3: 105.8 | U3: 100.3 | V3: 105.4 | W3: 104.8 | X3: 104.1 | Y3: 103.2 | Z3: 102.9 | AA3: 103.5 | AB3: 104.3 | AC3: 103.7 | AD3: 104
A4: Rural+Urban | B4: 2013 | C4: January | D4: 108.4 | E4: 107.3 | F4: 110 | G4: 104.4 | H4: 105.1 | I4: 103.2 | J4: 102.2 | K4: 106 | L4: 106.2 | M4: 102.7 | N4: 104.9 | O4: 107.3 | P4: 105.6 | Q4: 105.1 | R4: 106.3 | S4: 105.5 | T4: 106.2 | U4: 100.3 | V4: 105.5 | W4: 104.8 | X4: 104 | Y4: 103.2 | Z4: 103.1 | AA4: 103.6 | AB4: 104.5 | AC4: 103.9 | AD4: 104.6
A5: Rural | B5: 2013 | C5: February | D5: 109.2 | E5: 108.7 | F5: 110.2 | G5: 105.4 | H5: 106.7 | I5: 104 | J5: 102.4 | K5: 105.9 | L5: 105.7 | M5: 103.1 | N5: 105.1 | O5: 107.7 | P5: 106.3 | Q5: 105.6 | R5: 107.1 | S5: 106.3 | T5: 107 | V5: 106.2 | W5: 105.2 | X5: 104.4 | Y5: 103.9 | Z5: 104 | AA5: 104.1 | AB5: 104.6 | AC5: 104.4 | AD5: 105.8
A6: Urban | B6: 2013 | C6: February | D6: 112.9 | E6: 112.9 | F6: 116.9 | G6: 104 | H6: 103.5 | I6: 103.1 | J6: 104.9 | K6: 104.1 | L6: 103.8 | M6: 102.3 | N6: 106 | O6: 109 | P6: 107.2 | Q6: 106 | R6: 106.6 | S6: 105.5 | T6: 106.4 | U6: 100.4 | V6: 105.7 | W6: 105.2 | X6: 104.7 | Y6: 104.4 | Z6: 103.3 | AA6: 103.7 | AB6: 104.3 | AC6: 104.3 | AD6: 104.7
A7: Rural+Urban | B7: 2013 | C7: February | D7: 110.4 | E7: 110.2 | F7: 112.8 | G7: 104.9 | H7: 105.5 | I7: 103.6 | J7: 103.2 | K7: 105.3 | L7: 105.1 | M7: 102.8 | N7: 105.5 | O7: 108.3 | P7: 106.6 | Q7: 105.7 | R7: 106.9 | S7: 106 | T7: 106.8 | U7: 100.4 | V7: 106 | W7: 105.2 | X7: 104.5 | Y7: 104.2 | Z7: 103.6 | AA7: 103.9 | AB7: 104.5 | AC7: 104.4 | AD7: 105.3
A8: Rural | B8: 2013 | C8: March | D8: 110.2 | E8: 108.8 | F8: 109.9 | G8: 105.6 | H8: 106.2 | I8: 105.7 | J8: 101.4 | K8: 105.7 | L8: 105 | M8: 103.3 | N8: 105.6 | O8: 108.2 | P8: 106.6 | Q8: 106.5 | R8: 107.6 | S8: 106.8 | T8: 107.5 | V8: 106.1 | W8: 105.6 | X8: 104.7 | Y8: 104.6 | Z8: 104 | AA8: 104.3 | AB8: 104.3 | AC8: 104.6 | AD8: 106
A9: Urban | B9: 2013 | C9: March | D9: 113.9 | E9: 111.4 | F9: 113.2 | G9: 104.3 | H9: 102.7 | I9: 104.9 | J9: 103.8 | K9: 103.5 | L9: 102.6 | M9: 102.4 | N9: 107 | O9: 109.8 | P9: 107.3 | Q9: 106.8 | R9: 107.2 | S9: 106 | T9: 107 | U9: 100.4 | V9: 106 | W9: 105.7 | X9: 105.2 | Y9: 105.5 | Z9: 103.5 | AA9: 103.8 | AB9: 104.2 | AC9: 104.9 | AD9: 105
A10: Rural+Urban | B10: 2013 | C10: March | D10: 111.4 | E10: 109.7 | F10: 111.2 | G10: 105.1 | H10: 104.9 | I10: 105.3 | J10: 102.2 | K10: 105 | L10: 104.2 | M10: 103 | N10: 106.2 | O10: 108.9 | P10: 106.9 | Q10: 106.6 | R10: 107.4 | S10: 106.5 | T10: 107.3 | U10: 100.4 | V10: 106.1 | W10: 105.6 | X10: 104.9 | Y10: 105.1 | Z10: 103.7 | AA10: 104 | AB10: 104.3 | AC10: 104.7 | AD10: 105.5
A11: Rural | B11: 2013 | C11: April | D11: 110.2 | E11: 109.5 | F11: 106.9 | G11: 106.3 | H11: 105.7 | I11: 108.3 | J11: 103.4 | K11: 105.7 | L11: 104.2 | M11: 103.2 | N11: 106.5 | O11: 108.8 | P11: 107.1 | Q11: 107.1 | R11: 108.1 | S11: 107.4 | T11: 108 | V11: 106.5 | W11: 106.1 | X11: 105.1 | Y11: 104.4 | Z11: 104.5 | AA11: 104.8 | AB11: 102.7 | AC11: 104.6 | AD11: 106.4
A12: Urban | B12: 2013 | C12: April | D12: 114.6 | E12: 113.4 | F12: 106 | G12: 104.7 | H12: 102.1 | I12: 109.5 | J12: 109.7 | K12: 104.6 | L12: 102 | M12: 103.5 | N12: 108.2 | O12: 110.6 | P12: 108.8 | Q12: 108.5 | R12: 107.9 | S12: 106.4 | T12: 107.7 | U12: 100.5 | V12: 106.4 | W12: 106.5 | X12: 105.7 | Y12: 105 | Z12: 104 | AA12: 105.2 | AB12: 103.2 | AC12: 105.1 | AD12: 105.7
A13: Rural+Urban | B13: 2013 | C13: April | D13: 111.6 | E13: 110.9 | F13: 106.6 | G13: 105.7 | H13: 104.4 | I13: 108.9 | J13: 105.5 | K13: 105.3 | L13: 103.5 | M13: 103.3 | N13: 107.2 | O13: 109.6 | P13: 107.7 | Q13: 107.5 | R13: 108 | S13: 107 | T13: 107.9 | U13: 100.5 | V13: 106.5 | W13: 106.3 | X13: 105.3 | Y13: 104.7 | Z13: 104.2 | AA13: 105 | AB13: 102.9 | AC13: 104.8 | AD13: 106.1
A14: Rural | B14: 2013 | C14: May | D14: 110.9 | E14: 109.8 | F14: 105.9 | G14: 107.5 | H14: 105.3 | I14: 108.1 | J14: 107.3 | K14: 106.1 | L14: 103.7 | M14: 104 | N14: 107.4 | O14: 109.9 | P14: 108.1 | Q14: 108.1 | R14: 108.8 | S14: 107.9 | T14: 108.6 | V14: 107.5 | W14: 106.8 | X14: 105.7 | Y14: 104.1 | Z14: 105 | AA14: 105.5 | AB14: 102.1 | AC14: 104.8 | AD14: 107.2
A15: Urban | B15: 2013 | C15: May | D15: 115.4 | E15: 114.2 | F15: 102.7 | G15: 105.5 | H15: 101.5 | I15: 110.6 | J15: 123.7 | K15: 105.2 | L15: 101.9 | M15: 105 | N15: 109.1 | O15: 111.3 | P15: 111.1 | Q15: 109.8 | R15: 108.5 | S15: 106.7 | T15: 108.3 | U15: 100.5 | V15: 107.2 | W15: 107.1 | X15: 106.2 | Y15: 103.9 | Z15: 104.6 | AA15: 105.7 | AB15: 102.6 | AC15: 104.9 | AD15: 106.6
A16: Rural+Urban | B16: 2013 | C16: May | D16: 112.3 | E16: 111.3 | F16: 104.7 | G16: 106.8 | H16: 103.9 | I16: 109.3 | J16: 112.9 | K16: 105.8 | L16: 103.1 | M16: 104.3 | N16: 108.1 | O16: 110.5 | P16: 109.2 | Q16: 108.6 | R16: 108.7 | S16: 107.4 | T16: 108.5 | U16: 100.5 | V16: 107.4 | W16: 106.9 | X16: 105.9 | Y16: 104 | Z16: 104.8 | AA16: 105.6 | AB16: 102.3 | AC16: 104.8 | AD16: 106.9
A17: Rural | B17: 2013 | C17: June | D17: 112.3 | E17: 112.1 | F17: 108.1 | G17: 108.3 | H17: 105.9 | I17: 109.2 | J17: 118 | K17: 106.8 | L17: 104.1 | M17: 105.4 | N17: 108.2 | O17: 111 | P17: 110.6 | Q17: 109 | R17: 109.7 | S17: 108.8 | T17: 109.5 | V17: 108.5 | W17: 107.5 | X17: 106.3 | Y17: 105 | Z17: 105.6 | AA17: 106.5 | AB17: 102.5 | AC17: 105.5 | AD17: 108.9
A18: Urban | B18: 2013 | C18: June | D18: 117 | E18: 120.1 | F18: 112.5 | G18: 107.3 | H18: 101.3 | I18: 112.4 | J18: 143.6 | K18: 105.4 | L18: 101.4 | M18: 106.4 | N18: 110 | O18: 112.2 | P18: 115 | Q18: 110.9 | R18: 109.2 | S18: 107.2 | T18: 108.9 | U18: 106.6 | V18: 108 | W18: 107.7 | X18: 106.5 | Y18: 105.2 | Z18: 105.2 | AA18: 108.1 | AB18: 103.3 | AC18: 106.1 | AD18: 109.7
A19: Rural+Urban | B19: 2013 | C19: June | D19: 113.8 | E19: 114.9 | F19: 109.8 | G19: 107.9 | H19: 104.2 | I19: 110.7 | J19: 126.7 | K19: 106.3 | L19: 103.2 | M19: 105.7 | N19: 109 | O19: 111.6 | P19: 112.2 | Q19: 109.5 | R19: 109.5 | S19: 108.1 | T19: 109.3 | U19: 106.6 | V19: 108.3 | W19: 107.6 | X19: 106.4 | Y19: 105.1 | Z19: 105.4 | AA19: 107.4 | AB19: 102.8 | AC19: 105.8 | AD19: 109.3
A20: Rural | B20: 2013 | C20: July | D20: 113.4 | E20: 114.9 | F20: 110.5 | G20: 109.3 | H20: 106.2 | I20: 110.3 | J20: 129.2 | K20: 107.1 | L20: 104.3 | M20: 106.4 | N20: 109.1 | O20: 112.1 | P20: 113.1 | Q20: 109.8 | R20: 110.5 | S20: 109.5 | T20: 110.3 | V20: 109.5 | W20: 108.3 | X20: 106.9 | Y20: 106.8 | Z20: 106.4 | AA20: 107.8 | AB20: 102.5 | AC20: 106.5 | AD20: 110.7
A21: Urban | B21: 2013 | C21: July | D21: 117.8 | E21: 119.2 | F21: 114 | G21: 108.3 | H21: 101.1 | I21: 113.2 | J21: 160.9 | K21: 105.1 | L21: 101.3 | M21: 107.5 | N21: 110.4 | O21: 113.1 | P21: 117.5 | Q21: 111.7 | R21: 109.8 | S21: 107.8 | T21: 109.5 | U21: 107.7 | V21: 108.6 | W21: 108.1 | X21: 107.1 | Y21: 107.3 | Z21: 105.9 | AA21: 110.1 | AB21: 103.2 | AC21: 107.3 | AD21: 111.4
A22: Rural+Urban | B22: 2013 | C22: July | D22: 114.8 | E22: 116.4 | F22: 111.9 | G22: 108.9 | H22: 104.3 | I22: 111.7 | J22: 140 | K22: 106.4 | L22: 103.3 | M22: 106.8 | N22: 109.6 | O22: 112.6 | P22: 114.7 | Q22: 110.3 | R22: 110.2 | S22: 108.8 | T22: 110 | U22: 107.7 | V22: 109.2 | W22: 108.2 | X22: 107 | Y22: 107.1 | Z22: 106.1 | AA22: 109.1 | AB22: 102.8 | AC22: 106.9 | AD22: 111
A23: Rural | B23: 2013 | C23: August | D23: 114.3 | E23: 115.4 | F23: 111.1 | G23: 110 | H23: 106.4 | I23: 110.8 | J23: 138.9 | K23: 107.4 | L23: 104.1 | M23: 106.9 | N23: 109.7 | O23: 112.6 | P23: 114.9 | Q23: 110.7 | R23: 111.3 | S23: 110.2 | T23: 111.1 | V23: 109.9 | W23: 108.7 | X23: 107.5 | Y23: 107.8 | Z23: 106.8 | AA23: 108.7 | AB23: 105 | AC23: 107.5 | AD23: 112.1
A24: Urban | B24: 2013 | C24: August | D24: 118.3 | E24: 120.4 | F24: 112.7 | G24: 108.9 | H24: 101.1 | I24: 108.7 | J24: 177 | K24: 104.7 | L24: 101 | M24: 108.5 | N24: 110.9 | O24: 114.3 | P24: 119.6 | Q24: 112.4 | R24: 110.6 | S24: 108.3 | T24: 110.2 | U24: 108.9 | V24: 109.3 | W24: 108.7 | X24: 107.6 | Y24: 108.1 | Z24: 106.5 | AA24: 110.8 | AB24: 106 | AC24: 108.3 | AD24: 112.7
A25: Rural+Urban | B25: 2013 | C25: August | D25: 115.6 | E25: 117.2 | F25: 111.7 | G25: 109.6 | H25: 104.5 | I25: 109.8 | J25: 151.8 | K25: 106.5 | L25: 103.1 | M25: 107.4 | N25: 110.2 | O25: 113.4 | P25: 116.6 | Q25: 111.2 | R25: 111 | S25: 109.4 | T25: 110.7 | U25: 108.9 | V25: 109.7 | W25: 108.7 | X25: 107.5 | Y25: 108 | Z25: 106.6 | AA25: 109.9 | AB25: 105.4 | AC25: 107.9 | AD25: 112.4
A26: Rural | B26: 2013 | C26: September | D26: 115.4 | E26: 115.7 | F26: 111.7 | G26: 111 | H26: 107.4 | I26: 110.9 | J26: 154 | K26: 108.1 | L26: 104.2 | M26: 107.9 | N26: 110.4 | O26: 114 | P26: 117.8 | Q26: 111.7 | R26: 112.7 | S26: 111.4 | T26: 112.5 | V26: 111.1 | W26: 109.6 | X26: 108.3 | Y26: 109.3 | Z26: 107.7 | AA26: 109.8 | AB26: 106.7 | AC26: 108.7 | AD26: 114.2
A27: Urban | B27: 2013 | C27: September | D27: 118.6 | E27: 119.1 | F27: 113.2 | G27: 109.6 | H27: 101.7 | I27: 103.2 | J27: 174.3 | K27: 105.1 | L27: 100.8 | M27: 109.1 | N27: 111.1 | O27: 115.4 | P27: 119.2 | Q27: 112.9 | R27: 111.4 | S27: 109 | T27: 111.1 | U27: 109.7 | V27: 109.5 | W27: 109.6 | X27: 107.9 | Y27: 110.4 | Z27: 107.4 | AA27: 111.2 | AB27: 106.9 | AC27: 109.4 | AD27: 113.2
A28: Rural+Urban | B28: 2013 | C28: September | D28: 116.4 | E28: 116.9 | F28: 112.3 | G28: 110.5 | H28: 105.3 | I28: 107.3 | J28: 160.9 | K28: 107.1 | L28: 103.1 | M28: 108.3 | N28: 110.7 | O28: 114.6 | P28: 118.3 | Q28: 112 | R28: 112.2 | S28: 110.4 | T28: 111.9 | U28: 109.7 | V28: 110.5 | W28: 109.6 | X28: 108.1 | Y28: 109.9 | Z28: 107.5 | AA28: 110.6 | AB28: 106.8 | AC28: 109 | AD28: 113.7
A29: Rural | B29: 2013 | C29: October | D29: 116.3 | E29: 115.4 | F29: 112.6 | G29: 111.7 | H29: 107.7 | I29: 113.2 | J29: 164.9 | K29: 108.3 | L29: 103.9 | M29: 108.2 | N29: 111.1 | O29: 114.9 | P29: 119.8 | Q29: 112.2 | R29: 113.6 | S29: 112.3 | T29: 113.4 | V29: 111.6 | W29: 110.4 | X29: 108.9 | Y29: 109.3 | Z29: 108.3 | AA29: 110.2 | AB29: 107.5 | AC29: 109.1 | AD29: 115.5
A30: Urban | B30: 2013 | C30: October | D30: 118.9 | E30: 118.1 | F30: 114.5 | G30: 110.4 | H30: 102.3 | I30: 106.2 | J30: 183.5 | K30: 105.3 | L30: 100.2 | M30: 109.6 | N30: 111.4 | O30: 116 | P30: 120.8 | Q30: 113.5 | R30: 112.5 | S30: 109.7 | T30: 112 | U30: 110.5 | V30: 109.7 | W30: 110.2 | X30: 108.2 | Y30: 109.7 | Z30: 108 | AA30: 111.3 | AB30: 107.3 | AC30: 109.4 | AD30: 114
A31: Rural+Urban | B31: 2013 | C31: October | D31: 117.1 | E31: 116.3 | F31: 113.3 | G31: 111.2 | H31: 105.7 | I31: 109.9 | J31: 171.2 | K31: 107.3 | L31: 102.7 | M31: 108.7 | N31: 111.2 | O31: 115.4 | P31: 120.2 | Q31: 112.5 | R31: 113.2 | S31: 111.2 | T31: 112.8 | U31: 110.5 | V31: 110.9 | W31: 110.3 | X31: 108.6 | Y31: 109.5 | Z31: 108.1 | AA31: 110.8 | AB31: 107.4 | AC31: 109.2 | AD31: 114.8
A32: Rural | B32: 2013 | C32: November | D32: 117.3 | E32: 114.9 | F32: 116.2 | G32: 112.8 | H32: 108.9 | I32: 116.6 | J32: 178.1 | K32: 109.1 | L32: 103.6 | M32: 109 | N32: 111.8 | O32: 116 | P32: 122.5 | Q32: 112.8 | R32: 114.6 | S32: 113.1 | T32: 114.4 | V32: 112.6 | W32: 111.3 | X32: 109.7 | Y32: 109.6 | Z32: 108.7 | AA32: 111 | AB32: 108.2 | AC32: 109.8 | AD32: 117.4
A33: Urban | B33: 2013 | C33: November | D33: 119.8 | E33: 116.3 | F33: 122.6 | G33: 112 | H33: 103.2 | I33: 110 | J33: 192.8 | K33: 106.3 | L33: 99.5 | M33: 110.3 | N33: 111.8 | O33: 117.1 | P33: 122.9 | Q33: 114.1 | R33: 113.5 | S33: 110.3 | T33: 113 | U33: 111.1 | V33: 110 | W33: 110.9 | X33: 108.6 | Y33: 109.5 | Z33: 108.5 | AA33: 111.3 | AB33: 107.9 | AC33: 109.6 | AD33: 115
A34: Rural+Urban | B34: 2013 | C34: November | D34: 118.1 | E34: 115.4 | F34: 118.7 | G34: 112.5 | H34: 106.8 | I34: 113.5 | J34: 183.1 | K34: 108.2 | L34: 102.2 | M34: 109.4 | N34: 111.8 | O34: 116.5 | P34: 122.6 | Q34: 113.1 | R34: 114.2 | S34: 111.9 | T34: 113.8 | U34: 111.1 | V34: 111.6 | W34: 111.1 | X34: 109.3 | Y34: 109.5 | Z34: 108.6 | AA34: 111.2 | AB34: 108.1 | AC34: 109.7 | AD34: 116.3
A35: Rural | B35: 2013 | C35: December | D35: 118.4 | E35: 115.9 | F35: 120.4 | G35: 113.8 | H35: 109.5 | I35: 115.5 | J35: 145.7 | K35: 109.5 | L35: 102.9 | M35: 109.8 | N35: 112.1 | O35: 116.8 | P35: 118.7 | Q35: 113.6 | R35: 115.8 | S35: 114 | T35: 115.5 | V35: 112.8 | W35: 112.1 | X35: 110.1 | Y35: 109.9 | Z35: 109.2 | AA35: 111.6 | AB35: 108.1 | AC35: 110.1 | AD35: 115.5
A36: Urban | B36: 2013 | C36: December | D36: 120.5 | E36: 118.1 | F36: 128.5 | G36: 112.8 | H36: 103.4 | I36: 110.7 | J36: 144.8 | K36: 107.1 | L36: 98.6 | M36: 111.9 | N36: 112.1 | O36: 118.1 | P36: 117.8 | Q36: 115 | R36: 114.2 | S36: 110.9 | T36: 113.7 | U36: 110.7 | V36: 110.4 | W36: 111.3 | X36: 109 | Y36: 109.7 | Z36: 108.9 | AA36: 111.4 | AB36: 107.7 | AC36: 109.8 | AD36: 113.3
A37: Rural+Urban | B37: 2013 | C37: December | D37: 119.1 | E37: 116.7 | F37: 123.5 | G37: 113.4 | H37: 107.3 | I37: 113.3 | J37: 145.4 | K37: 108.7 | L37: 101.5 | M37: 110.5 | N37: 112.1 | O37: 117.4 | P37: 118.4 | Q37: 114 | R37: 115.2 | S37: 112.7 | T37: 114.8 | U37: 110.7 | V37: 111.9 | W37: 111.7 | X37: 109.7 | Y37: 109.8 | Z37: 109 | AA37: 111.5 | AB37: 107.9 | AC37: 110 | AD37: 114.5
A38: Rural | B38: 2014 | C38: January | D38: 118.9 | E38: 117.1 | F38: 120.5 | G38: 114.4 | H38: 109 | I38: 115.5 | J38: 123.9 | K38: 109.6 | L38: 101.8 | M38: 110.2 | N38: 112.4 | O38: 117.3 | P38: 116 | Q38: 114 | R38: 116.5 | S38: 114.5 | T38: 116.2 | V38: 113 | W38: 112.6 | X38: 110.6 | Y38: 110.5 | Z38: 109.6 | AA38: 111.8 | AB38: 108.3 | AC38: 110.6 | AD38: 114.2
A39: Urban | B39: 2014 | C39: January | D39: 121.2 | E39: 122 | F39: 129.9 | G39: 113.6 | H39: 102.9 | I39: 112.1 | J39: 118.9 | K39: 107.5 | L39: 96.9 | M39: 112.7 | N39: 112.1 | O39: 119 | P39: 115.5 | Q39: 115.7 | R39: 114.8 | S39: 111.3 | T39: 114.3 | U39: 111.6 | V39: 111 | W39: 111.9 | X39: 109.7 | Y39: 110.8 | Z39: 109.8 | AA39: 111.5 | AB39: 108 | AC39: 110.5 | AD39: 112.9
A40: Rural+Urban | B40: 2014 | C40: January | D40: 119.6 | E40: 118.8 | F40: 124.1 | G40: 114.1 | H40: 106.8 | I40: 113.9 | J40: 122.2 | K40: 108.9 | L40: 100.2 | M40: 111 | N40: 112.3 | O40: 118.1 | P40: 115.8 | Q40: 114.5 | R40: 115.8 | S40: 113.2 | T40: 115.4 | U40: 111.6 | V40: 112.2 | W40: 112.3 | X40: 110.3 | Y40: 110.7 | Z40: 109.7 | AA40: 111.6 | AB40: 108.2 | AC40: 110.6 | AD40: 113.6
A41: Rural | B41: 2014 | C41: February | D41: 119.4 | E41: 117.7 | F41: 121.2 | G41: 115 | H41: 109 | I41: 116.6 | J41: 116 | K41: 109.8 | L41: 101.1 | M41: 110.4 | N41: 112.9 | O41: 117.8 | P41: 115.3 | Q41: 114.2 | R41: 117.1 | S41: 114.5 | T41: 116.7 | V41: 113.2 | W41: 112.9 | X41: 110.9 | Y41: 110.8 | Z41: 109.9 | AA41: 112 | AB41: 108.7 | AC41: 110.9 | AD41: 114
A42: Urban | B42: 2014 | C42: February | D42: 121.9 | E42: 122 | F42: 124.5 | G42: 115.2 | H42: 102.5 | I42: 114.1 | J42: 111.5 | K42: 108.2 | L42: 95.4 | M42: 113.5 | N42: 112.1 | O42: 119.9 | P42: 115.2 | Q42: 116.2 | R42: 115.3 | S42: 111.7 | T42: 114.7 | U42: 112.5 | V42: 111.1 | W42: 112.6 | X42: 110.4 | Y42: 111.3 | Z42: 110.3 | AA42: 111.6 | AB42: 108.7 | AC42: 111 | AD42: 113.1
A43: Rural+Urban | B43: 2014 | C43: February | D43: 120.2 | E43: 119.2 | F43: 122.5 | G43: 115.1 | H43: 106.6 | I43: 115.4 | J43: 114.5 | K43: 109.3 | L43: 99.2 | M43: 111.4 | N43: 112.6 | O43: 118.8 | P43: 115.3 | Q43: 114.7 | R43: 116.4 | S43: 113.3 | T43: 115.9 | U43: 112.5 | V43: 112.4 | W43: 112.8 | X43: 110.7 | Y43: 111.1 | Z43: 110.1 | AA43: 111.8 | AB43: 108.7 | AC43: 110.9 | AD43: 113.6
A44: Rural | B44: 2014 | C44: March | D44: 120.1 | E44: 118.1 | F44: 120.7 | G44: 116.1 | H44: 109.3 | I44: 119.6 | J44: 117.9 | K44: 110.2 | L44: 101.2 | M44: 110.7 | N44: 113 | O44: 118.3 | P44: 116.2 | Q44: 114.6 | R44: 117.5 | S44: 114.9 | T44: 117.2 | V44: 113.4 | W44: 113.4 | X44: 111.4 | Y44: 111.2 | Z44: 110.2 | AA44: 112.4 | AB44: 108.9 | AC44: 111.3 | AD44: 114.6
A45: Urban | B45: 2014 | C45: March | D45: 122.1 | E45: 121.4 | F45: 121.5 | G45: 116.2 | H45: 102.8 | I45: 117.7 | J45: 113.3 | K45: 108.9 | L45: 96.3 | M45: 114.1 | N45: 112.2 | O45: 120.5 | P45: 116 | Q45: 116.7 | R45: 115.8 | S45: 112.1 | T45: 115.2 | U45: 113.2 | V45: 110.9 | W45: 113 | X45: 110.8 | Y45: 111.6 | Z45: 110.9 | AA45: 111.8 | AB45: 109.2 | AC45: 111.4 | AD45: 113.7
A46: Rural+Urban | B46: 2014 | C46: Marcrh | D46: 120.7 | E46: 119.3 | F46: 121 | G46: 116.1 | H46: 106.9 | I46: 118.7 | J46: 116.3 | K46: 109.8 | L46: 99.6 | M46: 111.8 | N46: 112.7 | O46: 119.3 | P46: 116.1 | Q46: 115.2 | R46: 116.8 | S46: 113.7 | T46: 116.4 | U46: 113.2 | V46: 112.5 | W46: 113.2 | X46: 111.2 | Y46: 111.4 | Z46: 110.6 | AA46: 112 | AB46: 109 | AC46: 111.3 | AD46: 114.2
A47: Rural | B47: 2014 | C47: April | D47: 120.2 | E47: 118.9 | F47: 118.1 | G47: 117 | H47: 109.7 | I47: 125.5 | J47: 120.5 | K47: 111 | L47: 102.6 | M47: 111.2 | N47: 113.5 | O47: 118.7 | P47: 117.2 | Q47: 115.4 | R47: 118.1 | S47: 116.1 | T47: 117.8 | V47: 113.4 | W47: 113.7 | X47: 111.8 | Y47: 111.2 | Z47: 110.5 | AA47: 113 | AB47: 108.9 | AC47: 111.5 | AD47: 115.4
A48: Urban | B48: 2014 | C48: April | D48: 122.5 | E48: 121.7 | F48: 113.3 | G48: 117 | H48: 103.1 | I48: 126.7 | J48: 121.2 | K48: 111 | L48: 100.3 | M48: 115.3 | N48: 112.7 | O48: 121 | P48: 118.2 | Q48: 117.6 | R48: 116.3 | S48: 112.5 | T48: 115.7 | U48: 113.9 | V48: 110.9 | W48: 113.4 | X48: 111 | Y48: 111.2 | Z48: 111.2 | AA48: 112.5 | AB48: 109.1 | AC48: 111.4 | AD48: 114.7
A49: Rural+Urban | B49: 2014 | C49: April | D49: 120.9 | E49: 119.9 | F49: 116.2 | G49: 117 | H49: 107.3 | I49: 126.1 | J49: 120.7 | K49: 111 | L49: 101.8 | M49: 112.6 | N49: 113.2 | O49: 119.8 | P49: 117.6 | Q49: 116 | R49: 117.4 | S49: 114.6 | T49: 117 | U49: 113.9 | V49: 112.5 | W49: 113.6 | X49: 111.5 | Y49: 111.2 | Z49: 110.9 | AA49: 112.7 | AB49: 109 | AC49: 111.5 | AD49: 115.1
A50: Rural | B50: 2014 | C50: May | D50: 120.3 | E50: 120.2 | F50: 116.9 | G50: 118 | H50: 110.1 | I50: 126.3 | J50: 123.9 | K50: 111.5 | L50: 103.5 | M50: 111.6 | N50: 114.2 | O50: 119.2 | P50: 118.2 | Q50: 116.3 | R50: 118.7 | S50: 116.8 | T50: 118.5 | V50: 113.4 | W50: 114.1 | X50: 112.1 | Y50: 111.4 | Z50: 110.9 | AA50: 113.1 | AB50: 108.9 | AC50: 111.8 | AD50: 116
A51: Urban | B51: 2014 | C51: May | D51: 122.7 | E51: 124.1 | F51: 114.2 | G51: 119.1 | H51: 103.5 | I51: 129.2 | J51: 127 | K51: 112.6 | L51: 101.3 | M51: 117 | N51: 112.9 | O51: 121.7 | P51: 120 | Q51: 118.3 | R51: 116.8 | S51: 112.9 | T51: 116.2 | U51: 114.3 | V51: 111.1 | W51: 114.1 | X51: 111.2 | Y51: 111.3 | Z51: 111.5 | AA51: 112.9 | AB51: 109.3 | AC51: 111.7 | AD51: 115.6
A52: Rural+Urban | B52: 2014 | C52: May | D52: 121.1 | E52: 121.6 | F52: 115.9 | G52: 118.4 | H52: 107.7 | I52: 127.7 | J52: 125 | K52: 111.9 | L52: 102.8 | M52: 113.4 | N52: 113.7 | O52: 120.4 | P52: 118.9 | Q52: 116.8 | R52: 118 | S52: 115.2 | T52: 117.6 | U52: 114.3 | V52: 112.5 | W52: 114.1 | X52: 111.8 | Y52: 111.3 | Z52: 111.2 | AA52: 113 | AB52: 109.1 | AC52: 111.8 | AD52: 115.8
A53: Rural | B53: 2014 | C53: June | D53: 120.7 | E53: 121.6 | F53: 116.1 | G53: 119.3 | H53: 110.3 | I53: 125.8 | J53: 129.3 | K53: 112.2 | L53: 103.6 | M53: 112.3 | N53: 114.9 | O53: 120.1 | P53: 119.5 | Q53: 117.3 | R53: 119.7 | S53: 117.3 | T53: 119.3 | V53: 114.4 | W53: 114.9 | X53: 112.8 | Y53: 112.2 | Z53: 111.4 | AA53: 114.3 | AB53: 108 | AC53: 112.3 | AD53: 117
A54: Urban | B54: 2014 | C54: June | D54: 123.1 | E54: 125.9 | F54: 115.4 | G54: 120.4 | H54: 103.4 | I54: 131.2 | J54: 137.5 | K54: 112.8 | L54: 101.4 | M54: 118.3 | N54: 113.2 | O54: 122.4 | P54: 122 | Q54: 119 | R54: 117.4 | S54: 113.2 | T54: 116.7 | U54: 113.9 | V54: 111.2 | W54: 114.3 | X54: 111.4 | Y54: 111.5 | Z54: 111.8 | AA54: 115.1 | AB54: 108.7 | AC54: 112.2 | AD54: 116.4
A55: Rural+Urban | B55: 2014 | C55: June | D55: 121.5 | E55: 123.1 | F55: 115.8 | G55: 119.7 | H55: 107.8 | I55: 128.3 | J55: 132.1 | K55: 112.4 | L55: 102.9 | M55: 114.3 | N55: 114.2 | O55: 121.2 | P55: 120.4 | Q55: 117.8 | R55: 118.8 | S55: 115.6 | T55: 118.3 | U55: 113.9 | V55: 113.2 | W55: 114.6 | X55: 112.3 | Y55: 111.8 | Z55: 111.6 | AA55: 114.8 | AB55: 108.3 | AC55: 112.3 | AD55: 116.7
A56: Rural | B56: 2014 | C56: July | D56: 121.7 | E56: 122.5 | F56: 117.7 | G56: 120.6 | H56: 110.4 | I56: 129.1 | J56: 150.1 | K56: 113.2 | L56: 104.8 | M56: 113.3 | N56: 115.6 | O56: 120.9 | P56: 123.3 | Q56: 118 | R56: 120.7 | S56: 118.3 | T56: 120.3 | V56: 115.3 | W56: 115.4 | X56: 113.4 | Y56: 113.2 | Z56: 111.8 | AA56: 115.5 | AB56: 108.8 | AC56: 113.1 | AD56: 119.5
A57: Urban | B57: 2014 | C57: July | D57: 123.8 | E57: 126.4 | F57: 118 | G57: 121.6 | H57: 103.5 | I57: 133.7 | J57: 172.4 | K57: 113.1 | L57: 102.7 | M57: 120 | N57: 113.8 | O57: 123.4 | P57: 127.1 | Q57: 121 | R57: 118 | S57: 113.6 | T57: 117.4 | U57: 114.8 | V57: 111.6 | W57: 114.9 | X57: 111.5 | Y57: 113 | Z57: 112.4 | AA57: 117.8 | AB57: 109.7 | AC57: 113.5 | AD57: 118.9
A58: Rural+Urban | B58: 2014 | C58: July | D58: 122.4 | E58: 123.9 | F58: 117.8 | G58: 121 | H58: 107.9 | I58: 131.2 | J58: 157.7 | K58: 113.2 | L58: 104.1 | M58: 115.5 | N58: 114.8 | O58: 122.1 | P58: 124.7 | Q58: 118.8 | R58: 119.6 | S58: 116.3 | T58: 119.1 | U58: 114.8 | V58: 113.9 | W58: 115.2 | X58: 112.7 | Y58: 113.1 | Z58: 112.1 | AA58: 116.8 | AB58: 109.2 | AC58: 113.3 | AD58: 119.2
A59: Rural | B59: 2014 | C59: August | D59: 121.8 | E59: 122.8 | F59: 117.8 | G59: 121.9 | H59: 110.6 | I59: 129.7 | J59: 161.1 | K59: 114.1 | L59: 105.1 | M59: 114.6 | N59: 115.8 | O59: 121.7 | P59: 125.3 | Q59: 118.8 | R59: 120.9 | S59: 118.8 | T59: 120.7 | V59: 115.4 | W59: 115.9 | X59: 114 | Y59: 113.2 | Z59: 112.2 | AA59: 116.2 | AB59: 109.4 | AC59: 113.5 | AD59: 120.7
A60: Urban | B60: 2014 | C60: August | D60: 124.8 | E60: 127.3 | F60: 116.5 | G60: 122.2 | H60: 103.6 | I60: 132.7 | J60: 181.9 | K60: 115.2 | L60: 102.7 | M60: 122.1 | N60: 114.4 | O60: 124.7 | P60: 128.9 | Q60: 123 | R60: 118.6 | S60: 114.1 | T60: 117.9 | U60: 115.5 | V60: 111.8 | W60: 115.3 | X60: 112.2 | Y60: 112.5 | Z60: 112.9 | AA60: 119.2 | AB60: 110.5 | AC60: 113.9 | AD60: 119.9
A61: Rural+Urban | B61: 2014 | C61: August | D61: 122.7 | E61: 124.4 | F61: 117.3 | G61: 122 | H61: 108 | I61: 131.1 | J61: 168.2 | K61: 114.5 | L61: 104.3 | M61: 117.1 | N61: 115.2 | O61: 123.1 | P61: 126.6 | Q61: 119.9 | R61: 120 | S61: 116.8 | T61: 119.6 | U61: 115.5 | V61: 114 | W61: 115.6 | X61: 113.3 | Y61: 112.8 | Z61: 112.6 | AA61: 118 | AB61: 109.9 | AC61: 113.7 | AD61: 120.3
A62: Rural | B62: 2014 | C62: September | D62: 122.3 | E62: 122.4 | F62: 117.8 | G62: 122.7 | H62: 110.4 | I62: 129.8 | J62: 158.8 | K62: 115 | L62: 104.7 | M62: 114.9 | N62: 116.5 | O62: 122.6 | P62: 125.3 | Q62: 119.5 | R62: 121.7 | S62: 119.2 | T62: 121.3 | V62: 115.8 | W62: 116.7 | X62: 114.5 | Y62: 112.8 | Z62: 112.6 | AA62: 116.6 | AB62: 109.1 | AC62: 113.7 | AD62: 120.9
A63: Urban | B63: 2014 | C63: September | D63: 124.2 | E63: 125.4 | F63: 116.4 | G63: 122.7 | H63: 103.5 | I63: 124.5 | J63: 168.6 | K63: 116.9 | L63: 101.9 | M63: 122.9 | N63: 114.8 | O63: 125.2 | P63: 126.7 | Q63: 124.3 | R63: 119.2 | S63: 114.5 | T63: 118.4 | U63: 116.1 | V63: 111.8 | W63: 115.5 | X63: 112.3 | Y63: 111.2 | Z63: 113.4 | AA63: 120 | AB63: 110 | AC63: 113.6 | AD63: 119.2
A64: Rural+Urban | B64: 2014 | C64: September | D64: 122.9 | E64: 123.5 | F64: 117.3 | G64: 122.7 | H64: 107.9 | I64: 127.3 | J64: 162.1 | K64: 115.6 | L64: 103.8 | M64: 117.6 | N64: 115.8 | O64: 123.8 | P64: 125.8 | Q64: 120.8 | R64: 120.7 | S64: 117.2 | T64: 120.1 | U64: 116.1 | V64: 114.3 | W64: 116.1 | X64: 113.7 | Y64: 112 | Z64: 113.1 | AA64: 118.6 | AB64: 109.5 | AC64: 113.7 | AD64: 120.1
A65: Rural | B65: 2014 | C65: October | D65: 122.6 | E65: 122.5 | F65: 118.3 | G65: 123.2 | H65: 110.5 | I65: 128.9 | J65: 155.3 | K65: 115.5 | L65: 104 | M65: 115.3 | N65: 116.8 | O65: 123.2 | P65: 125.1 | Q65: 120 | R65: 122.7 | S65: 120.3 | T65: 122.3 | V65: 116.4 | W65: 117.5 | X65: 115.3 | Y65: 112.6 | Z65: 113 | AA65: 116.9 | AB65: 109.3 | AC65: 114 | AD65: 121
A66: Urban | B66: 2014 | C66: October | D66: 124.6 | E66: 126.1 | F66: 117.8 | G66: 123.1 | H66: 103.5 | I66: 123.5 | J66: 159.6 | K66: 117.4 | L66: 101.2 | M66: 123.8 | N66: 115.2 | O66: 125.9 | P66: 125.8 | Q66: 124.3 | R66: 119.6 | S66: 114.9 | T66: 118.9 | U66: 116.7 | V66: 112 | W66: 115.8 | X66: 112.6 | Y66: 111 | Z66: 113.6 | AA66: 120.2 | AB66: 110.1 | AC66: 113.7 | AD66: 119.1
A67: Rural+Urban | B67: 2014 | C67: October | D67: 123.2 | E67: 123.8 | F67: 118.1 | G67: 123.2 | H67: 107.9 | I67: 126.4 | J67: 156.8 | K67: 116.1 | L67: 103.1 | M67: 118.1 | N67: 116.1 | O67: 124.5 | P67: 125.4 | Q67: 121.1 | R67: 121.5 | S67: 118.1 | T67: 121 | U67: 116.7 | V67: 114.7 | W67: 116.7 | X67: 114.3 | Y67: 111.8 | Z67: 113.3 | AA67: 118.8 | AB67: 109.6 | AC67: 113.9 | AD67: 120.1
A68: Rural | B68: 2014 | C68: November | D68: 122.7 | E68: 122.6 | F68: 119.9 | G68: 124 | H68: 110.5 | I68: 128.8 | J68: 152 | K68: 116.2 | L68: 103.3 | M68: 115.8 | N68: 116.8 | O68: 124.5 | P68: 124.9 | Q68: 120.8 | R68: 123.3 | S68: 120.5 | T68: 122.9 | V68: 117.3 | W68: 118.1 | X68: 115.9 | Y68: 112 | Z68: 113.3 | AA68: 117.2 | AB68: 108.8 | AC68: 114.1 | AD68: 121.1
A69: Urban | B69: 2014 | C69: November | D69: 124.5 | E69: 125.6 | F69: 122.7 | G69: 124.6 | H69: 103.2 | I69: 122.2 | J69: 153.2 | K69: 119.3 | L69: 99.8 | M69: 124.6 | N69: 115.8 | O69: 126.9 | P69: 125.4 | Q69: 125.8 | R69: 120.3 | S69: 115.4 | T69: 119.5 | U69: 117.1 | V69: 112.6 | W69: 116.4 | X69: 113 | Y69: 109.7 | Z69: 114 | AA69: 120.3 | AB69: 109.6 | AC69: 113.4 | AD69: 119
A70: Rural+Urban | B70: 2014 | C70: November | D70: 123.3 | E70: 123.7 | F70: 121 | G70: 124.2 | H70: 107.8 | I70: 125.7 | J70: 152.4 | K70: 117.2 | L70: 102.1 | M70: 118.7 | N70: 116.4 | O70: 125.6 | P70: 125.1 | Q70: 122.1 | R70: 122.1 | S70: 118.4 | T70: 121.6 | U70: 117.1 | V70: 115.5 | W70: 117.3 | X70: 114.8 | Y70: 110.8 | Z70: 113.7 | AA70: 119 | AB70: 109.1 | AC70: 113.8 | AD70: 120.1
A71: Rural | B71: 2014 | C71: December | D71: 122.4 | E71: 122.4 | F71: 121.8 | G71: 124.2 | H71: 110.2 | I71: 128.6 | J71: 140.3 | K71: 116.3 | L71: 102 | M71: 116 | N71: 117.3 | O71: 124.8 | P71: 123.3 | Q71: 121.7 | R71: 123.8 | S71: 120.6 | T71: 123.3 | V71: 117.4 | W71: 118.2 | X71: 116.2 | Y71: 111.5 | Z71: 113.3 | AA71: 117.7 | AB71: 109.4 | AC71: 114.2 | AD71: 120.3
A72: Urban | B72: 2014 | C72: December | D72: 124 | E72: 124.7 | F72: 126.3 | G72: 124.9 | H72: 103 | I72: 122.3 | J72: 141 | K72: 120.1 | L72: 97.8 | M72: 125.4 | N72: 116.1 | O72: 127.6 | P72: 124 | Q72: 126.4 | R72: 120.7 | S72: 115.8 | T72: 120 | U72: 116.5 | V72: 113 | W72: 116.8 | X72: 113.2 | Y72: 108.8 | Z72: 114.3 | AA72: 120.7 | AB72: 110.4 | AC72: 113.4 | AD72: 118.4
A73: Rural+Urban | B73: 2014 | C73: December | D73: 122.9 | E73: 123.2 | F73: 123.5 | G73: 124.5 | H73: 107.6 | I73: 125.7 | J73: 140.5 | K73: 117.6 | L73: 100.6 | M73: 119.1 | N73: 116.8 | O73: 126.1 | P73: 123.6 | Q73: 123 | R73: 122.6 | S73: 118.6 | T73: 122 | U73: 116.5 | V73: 115.7 | W73: 117.5 | X73: 115.1 | Y73: 110.1 | Z73: 113.9 | AA73: 119.5 | AB73: 109.8 | AC73: 113.8 | AD73: 119.4
A74: Rural | B74: 2015 | C74: January | D74: 123.1 | E74: 123.1 | F74: 122.1 | G74: 124.9 | H74: 111 | I74: 130.4 | J74: 132.3 | K74: 117.2 | L74: 100.5 | M74: 117.2 | N74: 117.9 | O74: 125.6 | P74: 122.8 | Q74: 122.7 | R74: 124.4 | S74: 121.6 | T74: 124 | V74: 118.4 | W74: 118.9 | X74: 116.6 | Y74: 111 | Z74: 114 | AA74: 118.2 | AB74: 110.2 | AC74: 114.5 | AD74: 120.3
A75: Urban | B75: 2015 | C75: January | D75: 124 | E75: 125.5 | F75: 126.6 | G75: 125.2 | H75: 104.3 | I75: 121.3 | J75: 134.4 | K75: 122.9 | L75: 96.1 | M75: 126.6 | N75: 116.5 | O75: 128 | P75: 123.5 | Q75: 127.4 | R75: 121 | S75: 116.1 | T75: 120.2 | U75: 117.3 | V75: 113.4 | W75: 117.2 | X75: 113.7 | Y75: 107.9 | Z75: 114.6 | AA75: 120.8 | AB75: 111.4 | AC75: 113.4 | AD75: 118.5
A76: Rural+Urban | B76: 2015 | C76: January | D76: 123.4 | E76: 123.9 | F76: 123.8 | G76: 125 | H76: 108.5 | I76: 126.2 | J76: 133 | K76: 119.1 | L76: 99 | M76: 120.3 | N76: 117.3 | O76: 126.7 | P76: 123.1 | Q76: 124 | R76: 123.1 | S76: 119.3 | T76: 122.5 | U76: 117.3 | V76: 116.5 | W76: 118.1 | X76: 115.5 | Y76: 109.4 | Z76: 114.3 | AA76: 119.7 | AB76: 110.7 | AC76: 114 | AD76: 119.5
A77: Rural | B77: 2015 | C77: February | D77: 123.4 | E77: 124.4 | F77: 122.1 | G77: 125.8 | H77: 111.5 | I77: 129.4 | J77: 128.2 | K77: 118.8 | L77: 100 | M77: 118.6 | N77: 118.8 | O77: 126.8 | P77: 122.8 | Q77: 124.2 | R77: 125.4 | S77: 122.7 | T77: 125 | V77: 120 | W77: 119.6 | X77: 117.7 | Y77: 110.9 | Z77: 114.8 | AA77: 118.7 | AB77: 110.8 | AC77: 115 | AD77: 120.6
A78: Urban | B78: 2015 | C78: February | D78: 124.3 | E78: 126.5 | F78: 119.5 | G78: 125.6 | H78: 104.9 | I78: 121.6 | J78: 131.8 | K78: 125.1 | L78: 95 | M78: 127.7 | N78: 116.8 | O78: 128.6 | P78: 123.7 | Q78: 128.1 | R78: 121.3 | S78: 116.5 | T78: 120.6 | U78: 118.1 | V78: 114 | W78: 117.7 | X78: 114.1 | Y78: 106.8 | Z78: 114.9 | AA78: 120.4 | AB78: 111.7 | AC78: 113.2 | AD78: 118.7
A79: Rural+Urban | B79: 2015 | C79: February | D79: 123.7 | E79: 125.1 | F79: 121.1 | G79: 125.7 | H79: 109.1 | I79: 125.8 | J79: 129.4 | K79: 120.9 | L79: 98.3 | M79: 121.6 | N79: 118 | O79: 127.6 | P79: 123.1 | Q79: 125.2 | R79: 123.8 | S79: 120.1 | T79: 123.3 | U79: 118.1 | V79: 117.7 | W79: 118.7 | X79: 116.3 | Y79: 108.7 | Z79: 114.9 | AA79: 119.7 | AB79: 111.2 | AC79: 114.1 | AD79: 119.7
A80: Rural | B80: 2015 | C80: March | D80: 123.3 | E80: 124.7 | F80: 118.9 | G80: 126 | H80: 111.8 | I80: 130.9 | J80: 128 | K80: 119.9 | L80: 98.9 | M80: 119.4 | N80: 118.9 | O80: 127.7 | P80: 123.1 | Q80: 124.7 | R80: 126 | S80: 122.9 | T80: 125.5 | V80: 120.6 | W80: 120.2 | X80: 118.2 | Y80: 111.6 | Z80: 115.5 | AA80: 119.4 | AB80: 110.8 | AC80: 115.5 | AD80: 121.1
A81: Urban | B81: 2015 | C81: March | D81: 124 | E81: 126.7 | F81: 113.5 | G81: 125.9 | H81: 104.8 | I81: 123.8 | J81: 131.4 | K81: 127.2 | L81: 93.2 | M81: 127.4 | N81: 117 | O81: 129.2 | P81: 123.9 | Q81: 128.8 | R81: 121.7 | S81: 116.9 | T81: 120.9 | U81: 118.6 | V81: 114.4 | W81: 118 | X81: 114.3 | Y81: 108.4 | Z81: 115.4 | AA81: 120.6 | AB81: 111.3 | AC81: 113.8 | AD81: 119.1
A82: Rural+Urban | B82: 2015 | C82: March | D82: 123.5 | E82: 125.4 | F82: 116.8 | G82: 126 | H82: 109.2 | I82: 127.6 | J82: 129.2 | K82: 122.4 | L82: 97 | M82: 122.1 | N82: 118.1 | O82: 128.4 | P82: 123.4 | Q82: 125.8 | R82: 124.3 | S82: 120.4 | T82: 123.7 | U82: 118.6 | V82: 118.3 | W82: 119.2 | X82: 116.7 | Y82: 109.9 | Z82: 115.4 | AA82: 120.1 | AB82: 111 | AC82: 114.7 | AD82: 120.2
A83: Rural | B83: 2015 | C83: April | D83: 123.3 | E83: 125.5 | F83: 117.2 | G83: 126.8 | H83: 111.9 | I83: 134.2 | J83: 127.5 | K83: 121.5 | L83: 97.8 | M83: 119.8 | N83: 119.4 | O83: 128.7 | P83: 123.6 | Q83: 125.7 | R83: 126.4 | S83: 123.3 | T83: 126 | V83: 121.2 | W83: 120.9 | X83: 118.6 | Y83: 111.9 | Z83: 116.2 | AA83: 119.9 | AB83: 111.6 | AC83: 116 | AD83: 121.5
A84: Urban | B84: 2015 | C84: April | D84: 123.8 | E84: 128.2 | F84: 110 | G84: 126.3 | H84: 104.5 | I84: 130.6 | J84: 130.8 | K84: 131.3 | L84: 91.6 | M84: 127.7 | N84: 117.2 | O84: 129.5 | P84: 124.6 | Q84: 130.1 | R84: 122.1 | S84: 117.2 | T84: 121.3 | U84: 119.2 | V84: 114.7 | W84: 118.4 | X84: 114.6 | Y84: 108.4 | Z84: 115.6 | AA84: 121.7 | AB84: 111.8 | AC84: 114.2 | AD84: 119.7
A85: Rural+Urban | B85: 2015 | C85: April | D85: 123.5 | E85: 126.4 | F85: 114.4 | G85: 126.6 | H85: 109.2 | I85: 132.5 | J85: 128.6 | K85: 124.8 | L85: 95.7 | M85: 122.4 | N85: 118.5 | O85: 129.1 | P85: 124 | Q85: 126.9 | R85: 124.7 | S85: 120.8 | T85: 124.1 | U85: 119.2 | V85: 118.7 | W85: 119.7 | X85: 117.1 | Y85: 110.1 | Z85: 115.9 | AA85: 121 | AB85: 111.7 | AC85: 115.1 | AD85: 120.7
A86: Rural | B86: 2015 | C86: May | D86: 123.5 | E86: 127.1 | F86: 117.3 | G86: 127.7 | H86: 112.5 | I86: 134.1 | J86: 128.5 | K86: 124.3 | L86: 97.6 | M86: 120.7 | N86: 120.2 | O86: 129.8 | P86: 124.4 | Q86: 126.7 | R86: 127.3 | S86: 124.1 | T86: 126.8 | V86: 121.9 | W86: 121.5 | X86: 119.4 | Y86: 113.3 | Z86: 116.7 | AA86: 120.5 | AB86: 112.3 | AC86: 116.9 | AD86: 122.4
A87: Urban | B87: 2015 | C87: May | D87: 123.8 | E87: 129.7 | F87: 111.3 | G87: 126.6 | H87: 105.2 | I87: 130.8 | J87: 135.6 | K87: 142.6 | L87: 90.8 | M87: 128.8 | N87: 117.7 | O87: 129.9 | P87: 126.1 | Q87: 131.3 | R87: 122.4 | S87: 117.4 | T87: 121.6 | U87: 119.6 | V87: 114.9 | W87: 118.7 | X87: 114.9 | Y87: 110.8 | Z87: 116 | AA87: 122 | AB87: 112.4 | AC87: 115.2 | AD87: 120.7
A88: Rural+Urban | B88: 2015 | C88: May | D88: 123.6 | E88: 128 | F88: 115 | G88: 127.3 | H88: 109.8 | I88: 132.6 | J88: 130.9 | K88: 130.5 | L88: 95.3 | M88: 123.4 | N88: 119.2 | O88: 129.8 | P88: 125 | Q88: 127.9 | R88: 125.4 | S88: 121.3 | T88: 124.7 | U88: 119.6 | V88: 119.2 | W88: 120.2 | X88: 117.7 | Y88: 112 | Z88: 116.3 | AA88: 121.4 | AB88: 112.3 | AC88: 116.1 | AD88: 121.6
A89: Rural | B89: 2015 | C89: June | D89: 124.1 | E89: 130.4 | F89: 122.1 | G89: 128.7 | H89: 114.1 | I89: 133.2 | J89: 135.2 | K89: 131.9 | L89: 96.3 | M89: 123 | N89: 121.1 | O89: 131.2 | P89: 126.6 | Q89: 128.2 | R89: 128.4 | S89: 125.1 | T89: 128 | V89: 122.6 | W89: 122.8 | X89: 120.4 | Y89: 114.2 | Z89: 117.9 | AA89: 122 | AB89: 113 | AC89: 117.9 | AD89: 124.1
A90: Urban | B90: 2015 | C90: June | D90: 123.6 | E90: 134.4 | F90: 120.9 | G90: 127.3 | H90: 106 | I90: 132.3 | J90: 146.7 | K90: 148.1 | L90: 89.8 | M90: 130.5 | N90: 118 | O90: 130.5 | P90: 128.5 | Q90: 132.1 | R90: 123.2 | S90: 117.6 | T90: 122.3 | U90: 119 | V90: 115.1 | W90: 119.2 | X90: 115.4 | Y90: 111.7 | Z90: 116.2 | AA90: 123.8 | AB90: 112.5 | AC90: 116 | AD90: 121.7
A91: Rural+Urban | B91: 2015 | C91: June | D91: 123.9 | E91: 131.8 | F91: 121.6 | G91: 128.2 | H91: 111.1 | I91: 132.8 | J91: 139.1 | K91: 137.4 | L91: 94.1 | M91: 125.5 | N91: 119.8 | O91: 130.9 | P91: 127.3 | Q91: 129.2 | R91: 126.4 | S91: 122 | T91: 125.7 | U91: 119 | V91: 119.8 | W91: 121.1 | X91: 118.5 | Y91: 112.9 | Z91: 116.9 | AA91: 123.1 | AB91: 112.8 | AC91: 117 | AD91: 123
A92: Rural | B92: 2015 | C92: July | D92: 124 | E92: 131.5 | F92: 122 | G92: 128.7 | H92: 113.5 | I92: 133.3 | J92: 140.8 | K92: 133.8 | L92: 94.1 | M92: 123.4 | N92: 121 | O92: 131.7 | P92: 127.5 | Q92: 129.4 | R92: 128.8 | S92: 125.5 | T92: 128.3 | V92: 123 | W92: 123 | X92: 120.8 | Y92: 114.1 | Z92: 118 | AA92: 122.9 | AB92: 112.7 | AC92: 118.1 | AD92: 124.7
A93: Urban | B93: 2015 | C93: July | D93: 123.2 | E93: 134.3 | F93: 119.5 | G93: 127.7 | H93: 106.3 | I93: 132.8 | J93: 153.5 | K93: 149.5 | L93: 85.7 | M93: 131.5 | N93: 118.3 | O93: 131.1 | P93: 129.5 | Q93: 133.1 | R93: 123.5 | S93: 117.9 | T93: 122.7 | U93: 119.9 | V93: 115.3 | W93: 119.5 | X93: 116 | Y93: 111.5 | Z93: 116.6 | AA93: 125.4 | AB93: 111.7 | AC93: 116.3 | AD93: 122.4
A94: Rural+Urban | B94: 2015 | C94: July | D94: 123.7 | E94: 132.5 | F94: 121 | G94: 128.3 | H94: 110.9 | I94: 133.1 | J94: 145.1 | K94: 139.1 | L94: 91.3 | M94: 126.1 | N94: 119.9 | O94: 131.4 | P94: 128.2 | Q94: 130.4 | R94: 126.7 | S94: 122.3 | T94: 126.1 | U94: 119.9 | V94: 120.1 | W94: 121.3 | X94: 119 | Y94: 112.7 | Z94: 117.2 | AA94: 124.4 | AB94: 112.3 | AC94: 117.2 | AD94: 123.6
A95: Rural | B95: 2015 | C95: August | D95: 124.7 | E95: 131.3 | F95: 121.3 | G95: 128.8 | H95: 114 | I95: 134.2 | J95: 153.6 | K95: 137.9 | L95: 93.1 | M95: 123.9 | N95: 121.5 | O95: 132.5 | P95: 129.8 | Q95: 130.1 | R95: 129.5 | S95: 126.3 | T95: 129 | V95: 123.8 | W95: 123.7 | X95: 121.1 | Y95: 113.6 | Z95: 118.5 | AA95: 123.6 | AB95: 112.5 | AC95: 118.2 | AD95: 126.1
A96: Urban | B96: 2015 | C96: August | D96: 123.1 | E96: 131.7 | F96: 118.1 | G96: 128 | H96: 106.8 | I96: 130.1 | J96: 165.5 | K96: 156 | L96: 85.3 | M96: 132.7 | N96: 118.8 | O96: 131.7 | P96: 131.1 | Q96: 134.2 | R96: 123.7 | S96: 118.2 | T96: 122.9 | U96: 120.9 | V96: 115.3 | W96: 120 | X96: 116.6 | Y96: 109.9 | Z96: 117.2 | AA96: 126.2 | AB96: 112 | AC96: 116.2 | AD96: 123.2
A97: Rural+Urban | B97: 2015 | C97: August | D97: 124.2 | E97: 131.4 | F97: 120.1 | G97: 128.5 | H97: 111.4 | I97: 132.3 | J97: 157.6 | K97: 144 | L97: 90.5 | M97: 126.8 | N97: 120.4 | O97: 132.1 | P97: 130.3 | Q97: 131.2 | R97: 127.2 | S97: 122.9 | T97: 126.6 | U97: 120.9 | V97: 120.6 | W97: 122 | X97: 119.4 | Y97: 111.7 | Z97: 117.8 | AA97: 125.1 | AB97: 112.3 | AC97: 117.2 | AD97: 124.8
A98: Rural | B98: 2015 | C98: September | D98: 125.1 | E98: 131.1 | F98: 120.7 | G98: 129.2 | H98: 114.7 | I98: 132.3 | J98: 158.9 | K98: 142.1 | L98: 92.5 | M98: 125.4 | N98: 121.9 | O98: 132.7 | P98: 131 | Q98: 131 | R98: 130.4 | S98: 126.8 | T98: 129.9 | V98: 123.7 | W98: 124.5 | X98: 121.4 | Y98: 113.8 | Z98: 119.6 | AA98: 124.5 | AB98: 113.7 | AC98: 118.8 | AD98: 127
A99: Urban | B99: 2015 | C99: September | D99: 123.4 | E99: 129 | F99: 115.6 | G99: 128.3 | H99: 107 | I99: 124 | J99: 168.5 | K99: 165.4 | L99: 86.3 | M99: 134.4 | N99: 119.1 | O99: 132.3 | P99: 131.5 | Q99: 134.7 | R99: 124 | S99: 118.6 | T99: 123.2 | U99: 121.6 | V99: 115.1 | W99: 120.4 | X99: 117.1 | Y99: 109.1 | Z99: 117.3 | AA99: 126.5 | AB99: 112.9 | AC99: 116.2 | AD99: 123.5
A100: Rural+Urban | B100: 2015 | C100: September | D100: 124.6 | E100: 130.4 | F100: 118.7 | G100: 128.9 | H100: 111.9 | I100: 128.4 | J100: 162.2 | K100: 150 | L100: 90.4 | M100: 128.4 | N100: 120.7 | O100: 132.5 | P100: 131.2 | Q100: 132 | R100: 127.9 | S100: 123.4 | T100: 127.2 | U100: 121.6 | V100: 120.4 | W100: 122.6 | X100: 119.8 | Y100: 111.3 | Z100: 118.3 | AA100: 125.7 | AB100: 113.4 | AC100: 117.5 | AD100: 125.4
...

Sheet Clean Data
A1: Sector | B1: Year | C1: Month | D1: Cereals and products | E1: Meat and fish | F1: Egg | G1: Milk and products | H1: Oils and fats | I1: Fruits | J1: Vegetables | K1: Pulses and products | L1: Sugar and Confectionery | M1: Spices | N1: Non-alcoholic beverages | O1: Prepared meals, snacks, sweets etc. | P1: Food and beverages | Q1: Pan, tobacco and intoxicants | R1: Clothing | S1: Footwear | T1: Clothing and footwear | U1: Housing | V1: Fuel and light | W1: Household goods and services | X1: Health | Y1: Transport and communication | Z1: Recreation and amusement | AA1: Education | AB1: Personal care and effects | AC1: Miscellaneous | AD1: General index
A2: Rural | B2: 2013 | C2: January | D2: 107.5 | E2: 106.3 | F2: 108.1 | G2: 104.9 | H2: 106.1 | I2: 103.9 | J2: 101.9 | K2: 106.1 | L2: 106.8 | M2: 103.1 | N2: 104.8 | O2: 106.7 | P2: 105.5 | Q2: 105.1 | R2: 106.5 | S2: 105.8 | T2: 106.4 | V2: 105.5 | W2: 104.8 | X2: 104 | Y2: 103.3 | Z2: 103.4 | AA2: 103.8 | AB2: 104.7 | AC2: 104 | AD2: 105.1 | AE2: ← Dashboard
A3: Urban | B3: 2013 | C3: January | D3: 110.5 | E3: 109.1 | F3: 113 | G3: 103.6 | H3: 103.4 | I3: 102.3 | J3: 102.9 | K3: 105.8 | L3: 105.1 | M3: 101.8 | N3: 105.1 | O3: 107.9 | P3: 105.9 | Q3: 105.2 | R3: 105.9 | S3: 105 | T3: 105.8 | U3: 100.3 | V3: 105.4 | W3: 104.8 | X3: 104.1 | Y3: 103.2 | Z3: 102.9 | AA3: 103.5 | AB3: 104.3 | AC3: 103.7 | AD3: 104
A4: Rural+Urban | B4: 2013 | C4: January | D4: 108.4 | E4: 107.3 | F4: 110 | G4: 104.4 | H4: 105.1 | I4: 103.2 | J4: 102.2 | K4: 106 | L4: 106.2 | M4: 102.7 | N4: 104.9 | O4: 107.3 | P4: 105.6 | Q4: 105.1 | R4: 106.3 | S4: 105.5 | T4: 106.2 | U4: 100.3 | V4: 105.5 | W4: 104.8 | X4: 104 | Y4: 103.2 | Z4: 103.1 | AA4: 103.6 | AB4: 104.5 | AC4: 103.9 | AD4: 104.6
A5: Rural | B5: 2013 | C5: February | D5: 109.2 | E5: 108.7 | F5: 110.2 | G5: 105.4 | H5: 106.7 | I5: 104 | J5: 102.4 | K5: 105.9 | L5: 105.7 | M5: 103.1 | N5: 105.1 | O5: 107.7 | P5: 106.3 | Q5: 105.6 | R5: 107.1 | S5: 106.3 | T5: 107 | V5: 106.2 | W5: 105.2 | X5: 104.4 | Y5: 103.9 | Z5: 104 | AA5: 104.1 | AB5: 104.6 | AC5: 104.4 | AD5: 105.8
A6: Urban | B6: 2013 | C6: February | D6: 112.9 | E6: 112.9 | F6: 116.9 | G6: 104 | H6: 103.5 | I6: 103.1 | J6: 104.9 | K6: 104.1 | L6: 103.8 | M6: 102.3 | N6: 106 | O6: 109 | P6: 107.2 | Q6: 106 | R6: 106.6 | S6: 105.5 | T6: 106.4 | U6: 100.4 | V6: 105.7 | W6: 105.2 | X6: 104.7 | Y6: 104.4 | Z6: 103.3 | AA6: 103.7 | AB6: 104.3 | AC6: 104.3 | AD6: 104.7
A7: Rural+Urban | B7: 2013 | C7: February | D7: 110.4 | E7: 110.2 | F7: 112.8 | G7: 104.9 | H7: 105.5 | I7: 103.6 | J7: 103.2 | K7: 105.3 | L7: 105.1 | M7: 102.8 | N7: 105.5 | O7: 108.3 | P7: 106.6 | Q7: 105.7 | R7: 106.9 | S7: 106 | T7: 106.8 | U7: 100.4 | V7: 106 | W7: 105.2 | X7: 104.5 | Y7: 104.2 | Z7: 103.6 | AA7: 103.9 | AB7: 104.5 | AC7: 104.4 | AD7: 105.3
A8: Rural | B8: 2013 | C8: March | D8: 110.2 | E8: 108.8 | F8: 109.9 | G8: 105.6 | H8: 106.2 | I8: 105.7 | J8: 101.4 | K8: 105.7 | L8: 105 | M8: 103.3 | N8: 105.6 | O8: 108.2 | P8: 106.6 | Q8: 106.5 | R8: 107.6 | S8: 106.8 | T8: 107.5 | V8: 106.1 | W8: 105.6 | X8: 104.7 | Y8: 104.6 | Z8: 104 | AA8: 104.3 | AB8: 104.3 | AC8: 104.6 | AD8: 106
A9: Urban | B9: 2013 | C9: March | D9: 113.9 | E9: 111.4 | F9: 113.2 | G9: 104.3 | H9: 102.7 | I9: 104.9 | J9: 103.8 | K9: 103.5 | L9: 102.6 | M9: 102.4 | N9: 107 | O9: 109.8 | P9: 107.3 | Q9: 106.8 | R9: 107.2 | S9: 106 | T9: 107 | U9: 100.4 | V9: 106 | W9: 105.7 | X9: 105.2 | Y9: 105.5 | Z9: 103.5 | AA9: 103.8 | AB9: 104.2 | AC9: 104.9 | AD9: 105
A10: Rural+Urban | B10: 2013 | C10: March | D10: 111.4 | E10: 109.7 | F10: 111.2 | G10: 105.1 | H10: 104.9 | I10: 105.3 | J10: 102.2 | K10: 105 | L10: 104.2 | M10: 103 | N10: 106.2 | O10: 108.9 | P10: 106.9 | Q10: 106.6 | R10: 107.4 | S10: 106.5 | T10: 107.3 | U10: 100.4 | V10: 106.1 | W10: 105.6 | X10: 104.9 | Y10: 105.1 | Z10: 103.7 | AA10: 104 | AB10: 104.3 | AC10: 104.7 | AD10: 105.5
A11: Rural | B11: 2013 | C11: April | D11: 110.2 | E11: 109.5 | F11: 106.9 | G11: 106.3 | H11: 105.7 | I11: 108.3 | J11: 103.4 | K11: 105.7 | L11: 104.2 | M11: 103.2 | N11: 106.5 | O11: 108.8 | P11: 107.1 | Q11: 107.1 | R11: 108.1 | S11: 107.4 | T11: 108 | V11: 106.5 | W11: 106.1 | X11: 105.1 | Y11: 104.4 | Z11: 104.5 | AA11: 104.8 | AB11: 102.7 | AC11: 104.6 | AD11: 106.4
A12: Urban | B12: 2013 | C12: April | D12: 114.6 | E12: 113.4 | F12: 106 | G12: 104.7 | H12: 102.1 | I12: 109.5 | J12: 109.7 | K12: 104.6 | L12: 102 | M12: 103.5 | N12: 108.2 | O12: 110.6 | P12: 108.8 | Q12: 108.5 | R12: 107.9 | S12: 106.4 | T12: 107.7 | U12: 100.5 | V12: 106.4 | W12: 106.5 | X12: 105.7 | Y12: 105 | Z12: 104 | AA12: 105.2 | AB12: 103.2 | AC12: 105.1 | AD12: 105.7
A13: Rural+Urban | B13: 2013 | C13: April | D13: 111.6 | E13: 110.9 | F13: 106.6 | G13: 105.7 | H13: 104.4 | I13: 108.9 | J13: 105.5 | K13: 105.3 | L13: 103.5 | M13: 103.3 | N13: 107.2 | O13: 109.6 | P13: 107.7 | Q13: 107.5 | R13: 108 | S13: 107 | T13: 107.9 | U13: 100.5 | V13: 106.5 | W13: 106.3 | X13: 105.3 | Y13: 104.7 | Z13: 104.2 | AA13: 105 | AB13: 102.9 | AC13: 104.8 | AD13: 106.1
A14: Rural | B14: 2013 | C14: May | D14: 110.9 | E14: 109.8 | F14: 105.9 | G14: 107.5 | H14: 105.3 | I14: 108.1 | J14: 107.3 | K14: 106.1 | L14: 103.7 | M14: 104 | N14: 107.4 | O14: 109.9 | P14: 108.1 | Q14: 108.1 | R14: 108.8 | S14: 107.9 | T14: 108.6 | V14: 107.5 | W14: 106.8 | X14: 105.7 | Y14: 104.1 | Z14: 105 | AA14: 105.5 | AB14: 102.1 | AC14: 104.8 | AD14: 107.2
A15: Urban | B15: 2013 | C15: May | D15: 115.4 | E15: 114.2 | F15: 102.7 | G15: 105.5 | H15: 101.5 | I15: 110.6 | J15: 123.7 | K15: 105.2 | L15: 101.9 | M15: 105 | N15: 109.1 | O15: 111.3 | P15: 111.1 | Q15: 109.8 | R15: 108.5 | S15: 106.7 | T15: 108.3 | U15: 100.5 | V15: 107.2 | W15: 107.1 | X15: 106.2 | Y15: 103.9 | Z15: 104.6 | AA15: 105.7 | AB15: 102.6 | AC15: 104.9 | AD15: 106.6
A16: Rural+Urban | B16: 2013 | C16: May | D16: 112.3 | E16: 111.3 | F16: 104.7 | G16: 106.8 | H16: 103.9 | I16: 109.3 | J16: 112.9 | K16: 105.8 | L16: 103.1 | M16: 104.3 | N16: 108.1 | O16: 110.5 | P16: 109.2 | Q16: 108.6 | R16: 108.7 | S16: 107.4 | T16: 108.5 | U16: 100.5 | V16: 107.4 | W16: 106.9 | X16: 105.9 | Y16: 104 | Z16: 104.8 | AA16: 105.6 | AB16: 102.3 | AC16: 104.8 | AD16: 106.9
A17: Rural | B17: 2013 | C17: June | D17: 112.3 | E17: 112.1 | F17: 108.1 | G17: 108.3 | H17: 105.9 | I17: 109.2 | J17: 118 | K17: 106.8 | L17: 104.1 | M17: 105.4 | N17: 108.2 | O17: 111 | P17: 110.6 | Q17: 109 | R17: 109.7 | S17: 108.8 | T17: 109.5 | V17: 108.5 | W17: 107.5 | X17: 106.3 | Y17: 105 | Z17: 105.6 | AA17: 106.5 | AB17: 102.5 | AC17: 105.5 | AD17: 108.9
A18: Urban | B18: 2013 | C18: June | D18: 117 | E18: 120.1 | F18: 112.5 | G18: 107.3 | H18: 101.3 | I18: 112.4 | J18: 143.6 | K18: 105.4 | L18: 101.4 | M18: 106.4 | N18: 110 | O18: 112.2 | P18: 115 | Q18: 110.9 | R18: 109.2 | S18: 107.2 | T18: 108.9 | U18: 106.6 | V18: 108 | W18: 107.7 | X18: 106.5 | Y18: 105.2 | Z18: 105.2 | AA18: 108.1 | AB18: 103.3 | AC18: 106.1 | AD18: 109.7
A19: Rural+Urban | B19: 2013 | C19: June | D19: 113.8 | E19: 114.9 | F19: 109.8 | G19: 107.9 | H19: 104.2 | I19: 110.7 | J19: 126.7 | K19: 106.3 | L19: 103.2 | M19: 105.7 | N19: 109 | O19: 111.6 | P19: 112.2 | Q19: 109.5 | R19: 109.5 | S19: 108.1 | T19: 109.3 | U19: 106.6 | V19: 108.3 | W19: 107.6 | X19: 106.4 | Y19: 105.1 | Z19: 105.4 | AA19: 107.4 | AB19: 102.8 | AC19: 105.8 | AD19: 109.3
A20: Rural | B20: 2013 | C20: July | D20: 113.4 | E20: 114.9 | F20: 110.5 | G20: 109.3 | H20: 106.2 | I20: 110.3 | J20: 129.2 | K20: 107.1 | L20: 104.3 | M20: 106.4 | N20: 109.1 | O20: 112.1 | P20: 113.1 | Q20: 109.8 | R20: 110.5 | S20: 109.5 | T20: 110.3 | V20: 109.5 | W20: 108.3 | X20: 106.9 | Y20: 106.8 | Z20: 106.4 | AA20: 107.8 | AB20: 102.5 | AC20: 106.5 | AD20: 110.7
A21: Urban | B21: 2013 | C21: July | D21: 117.8 | E21: 119.2 | F21: 114 | G21: 108.3 | H21: 101.1 | I21: 113.2 | J21: 160.9 | K21: 105.1 | L21: 101.3 | M21: 107.5 | N21: 110.4 | O21: 113.1 | P21: 117.5 | Q21: 111.7 | R21: 109.8 | S21: 107.8 | T21: 109.5 | U21: 107.7 | V21: 108.6 | W21: 108.1 | X21: 107.1 | Y21: 107.3 | Z21: 105.9 | AA21: 110.1 | AB21: 103.2 | AC21: 107.3 | AD21: 111.4
A22: Rural+Urban | B22: 2013 | C22: July | D22: 114.8 | E22: 116.4 | F22: 111.9 | G22: 108.9 | H22: 104.3 | I22: 111.7 | J22: 140 | K22: 106.4 | L22: 103.3 | M22: 106.8 | N22: 109.6 | O22: 112.6 | P22: 114.7 | Q22: 110.3 | R22: 110.2 | S22: 108.8 | T22: 110 | U22: 107.7 | V22: 109.2 | W22: 108.2 | X22: 107 | Y22: 107.1 | Z22: 106.1 | AA22: 109.1 | AB22: 102.8 | AC22: 106.9 | AD22: 111
A23: Rural | B23: 2013 | C23: August | D23: 114.3 | E23: 115.4 | F23: 111.1 | G23: 110 | H23: 106.4 | I23: 110.8 | J23: 138.9 | K23: 107.4 | L23: 104.1 | M23: 106.9 | N23: 109.7 | O23: 112.6 | P23: 114.9 | Q23: 110.7 | R23: 111.3 | S23: 110.2 | T23: 111.1 | V23: 109.9 | W23: 108.7 | X23: 107.5 | Y23: 107.8 | Z23: 106.8 | AA23: 108.7 | AB23: 105 | AC23: 107.5 | AD23: 112.1
A24: Urban | B24: 2013 | C24: August | D24: 118.3 | E24: 120.4 | F24: 112.7 | G24: 108.9 | H24: 101.1 | I24: 108.7 | J24: 177 | K24: 104.7 | L24: 101 | M24: 108.5 | N24: 110.9 | O24: 114.3 | P24: 119.6 | Q24: 112.4 | R24: 110.6 | S24: 108.3 | T24: 110.2 | U24: 108.9 | V24: 109.3 | W24: 108.7 | X24: 107.6 | Y24: 108.1 | Z24: 106.5 | AA24: 110.8 | AB24: 106 | AC24: 108.3 | AD24: 112.7
A25: Rural+Urban | B25: 2013 | C25: August | D25: 115.6 | E25: 117.2 | F25: 111.7 | G25: 109.6 | H25: 104.5 | I25: 109.8 | J25: 151.8 | K25: 106.5 | L25: 103.1 | M25: 107.4 | N25: 110.2 | O25: 113.4 | P25: 116.6 | Q25: 111.2 | R25: 111 | S25: 109.4 | T25: 110.7 | U25: 108.9 | V25: 109.7 | W25: 108.7 | X25: 107.5 | Y25: 108 | Z25: 106.6 | AA25: 109.9 | AB25: 105.4 | AC25: 107.9 | AD25: 112.4
A26: Rural | B26: 2013 | C26: September | D26: 115.4 | E26: 115.7 | F26: 111.7 | G26: 111 | H26: 107.4 | I26: 110.9 | J26: 154 | K26: 108.1 | L26: 104.2 | M26: 107.9 | N26: 110.4 | O26: 114 | P26: 117.8 | Q26: 111.7 | R26: 112.7 | S26: 111.4 | T26: 112.5 | V26: 111.1 | W26: 109.6 | X26: 108.3 | Y26: 109.3 | Z26: 107.7 | AA26: 109.8 | AB26: 106.7 | AC26: 108.7 | AD26: 114.2
A27: Urban | B27: 2013 | C27: September | D27: 118.6 | E27: 119.1 | F27: 113.2 | G27: 109.6 | H27: 101.7 | I27: 103.2 | J27: 174.3 | K27: 105.1 | L27: 100.8 | M27: 109.1 | N27: 111.1 | O27: 115.4 | P27: 119.2 | Q27: 112.9 | R27: 111.4 | S27: 109 | T27: 111.1 | U27: 109.7 | V27: 109.5 | W27: 109.6 | X27: 107.9 | Y27: 110.4 | Z27: 107.4 | AA27: 111.2 | AB27: 106.9 | AC27: 109.4 | AD27: 113.2
A28: Rural+Urban | B28: 2013 | C28: September | D28: 116.4 | E28: 116.9 | F28: 112.3 | G28: 110.5 | H28: 105.3 | I28: 107.3 | J28: 160.9 | K28: 107.1 | L28: 103.1 | M28: 108.3 | N28: 110.7 | O28: 114.6 | P28: 118.3 | Q28: 112 | R28: 112.2 | S28: 110.4 | T28: 111.9 | U28: 109.7 | V28: 110.5 | W28: 109.6 | X28: 108.1 | Y28: 109.9 | Z28: 107.5 | AA28: 110.6 | AB28: 106.8 | AC28: 109 | AD28: 113.7
A29: Rural | B29: 2013 | C29: October | D29: 116.3 | E29: 115.4 | F29: 112.6 | G29: 111.7 | H29: 107.7 | I29: 113.2 | J29: 164.9 | K29: 108.3 | L29: 103.9 | M29: 108.2 | N29: 111.1 | O29: 114.9 | P29: 119.8 | Q29: 112.2 | R29: 113.6 | S29: 112.3 | T29: 113.4 | V29: 111.6 | W29: 110.4 | X29: 108.9 | Y29: 109.3 | Z29: 108.3 | AA29: 110.2 | AB29: 107.5 | AC29: 109.1 | AD29: 115.5
A30: Urban | B30: 2013 | C30: October | D30: 118.9 | E30: 118.1 | F30: 114.5 | G30: 110.4 | H30: 102.3 | I30: 106.2 | J30: 183.5 | K30: 105.3 | L30: 100.2 | M30: 109.6 | N30: 111.4 | O30: 116 | P30: 120.8 | Q30: 113.5 | R30: 112.5 | S30: 109.7 | T30: 112 | U30: 110.5 | V30: 109.7 | W30: 110.2 | X30: 108.2 | Y30: 109.7 | Z30: 108 | AA30: 111.3 | AB30: 107.3 | AC30: 109.4 | AD30: 114
A31: Rural+Urban | B31: 2013 | C31: October | D31: 117.1 | E31: 116.3 | F31: 113.3 | G31: 111.2 | H31: 105.7 | I31: 109.9 | J31: 171.2 | K31: 107.3 | L31: 102.7 | M31: 108.7 | N31: 111.2 | O31: 115.4 | P31: 120.2 | Q31: 112.5 | R31: 113.2 | S31: 111.2 | T31: 112.8 | U31: 110.5 | V31: 110.9 | W31: 110.3 | X31: 108.6 | Y31: 109.5 | Z31: 108.1 | AA31: 110.8 | AB31: 107.4 | AC31: 109.2 | AD31: 114.8
A32: Rural | B32: 2013 | C32: November | D32: 117.3 | E32: 114.9 | F32: 116.2 | G32: 112.8 | H32: 108.9 | I32: 116.6 | J32: 178.1 | K32: 109.1 | L32: 103.6 | M32: 109 | N32: 111.8 | O32: 116 | P32: 122.5 | Q32: 112.8 | R32: 114.6 | S32: 113.1 | T32: 114.4 | V32: 112.6 | W32: 111.3 | X32: 109.7 | Y32: 109.6 | Z32: 108.7 | AA32: 111 | AB32: 108.2 | AC32: 109.8 | AD32: 117.4
A33: Urban | B33: 2013 | C33: November | D33: 119.8 | E33: 116.3 | F33: 122.6 | G33: 112 | H33: 103.2 | I33: 110 | J33: 192.8 | K33: 106.3 | L33: 99.5 | M33: 110.3 | N33: 111.8 | O33: 117.1 | P33: 122.9 | Q33: 114.1 | R33: 113.5 | S33: 110.3 | T33: 113 | U33: 111.1 | V33: 110 | W33: 110.9 | X33: 108.6 | Y33: 109.5 | Z33: 108.5 | AA33: 111.3 | AB33: 107.9 | AC33: 109.6 | AD33: 115
A34: Rural+Urban | B34: 2013 | C34: November | D34: 118.1 | E34: 115.4 | F34: 118.7 | G34: 112.5 | H34: 106.8 | I34: 113.5 | J34: 183.1 | K34: 108.2 | L34: 102.2 | M34: 109.4 | N34: 111.8 | O34: 116.5 | P34: 122.6 | Q34: 113.1 | R34: 114.2 | S34: 111.9 | T34: 113.8 | U34: 111.1 | V34: 111.6 | W34: 111.1 | X34: 109.3 | Y34: 109.5 | Z34: 108.6 | AA34: 111.2 | AB34: 108.1 | AC34: 109.7 | AD34: 116.3
A35: Rural | B35: 2013 | C35: December | D35: 118.4 | E35: 115.9 | F35: 120.4 | G35: 113.8 | H35: 109.5 | I35: 115.5 | J35: 145.7 | K35: 109.5 | L35: 102.9 | M35: 109.8 | N35: 112.1 | O35: 116.8 | P35: 118.7 | Q35: 113.6 | R35: 115.8 | S35: 114 | T35: 115.5 | V35: 112.8 | W35: 112.1 | X35: 110.1 | Y35: 109.9 | Z35: 109.2 | AA35: 111.6 | AB35: 108.1 | AC35: 110.1 | AD35: 115.5
A36: Urban | B36: 2013 | C36: December | D36: 120.5 | E36: 118.1 | F36: 128.5 | G36: 112.8 | H36: 103.4 | I36: 110.7 | J36: 144.8 | K36: 107.1 | L36: 98.6 | M36: 111.9 | N36: 112.1 | O36: 118.1 | P36: 117.8 | Q36: 115 | R36: 114.2 | S36: 110.9 | T36: 113.7 | U36: 110.7 | V36: 110.4 | W36: 111.3 | X36: 109 | Y36: 109.7 | Z36: 108.9 | AA36: 111.4 | AB36: 107.7 | AC36: 109.8 | AD36: 113.3
A37: Rural+Urban | B37: 2013 | C37: December | D37: 119.1 | E37: 116.7 | F37: 123.5 | G37: 113.4 | H37: 107.3 | I37: 113.3 | J37: 145.4 | K37: 108.7 | L37: 101.5 | M37: 110.5 | N37: 112.1 | O37: 117.4 | P37: 118.4 | Q37: 114 | R37: 115.2 | S37: 112.7 | T37: 114.8 | U37: 110.7 | V37: 111.9 | W37: 111.7 | X37: 109.7 | Y37: 109.8 | Z37: 109 | AA37: 111.5 | AB37: 107.9 | AC37: 110 | AD37: 114.5
A38: Rural | B38: 2014 | C38: January | D38: 118.9 | E38: 117.1 | F38: 120.5 | G38: 114.4 | H38: 109 | I38: 115.5 | J38: 123.9 | K38: 109.6 | L38: 101.8 | M38: 110.2 | N38: 112.4 | O38: 117.3 | P38: 116 | Q38: 114 | R38: 116.5 | S38: 114.5 | T38: 116.2 | V38: 113 | W38: 112.6 | X38: 110.6 | Y38: 110.5 | Z38: 109.6 | AA38: 111.8 | AB38: 108.3 | AC38: 110.6 | AD38: 114.2
A39: Urban | B39: 2014 | C39: January | D39: 121.2 | E39: 122 | F39: 129.9 | G39: 113.6 | H39: 102.9 | I39: 112.1 | J39: 118.9 | K39: 107.5 | L39: 96.9 | M39: 112.7 | N39: 112.1 | O39: 119 | P39: 115.5 | Q39: 115.7 | R39: 114.8 | S39: 111.3 | T39: 114.3 | U39: 111.6 | V39: 111 | W39: 111.9 | X39: 109.7 | Y39: 110.8 | Z39: 109.8 | AA39: 111.5 | AB39: 108 | AC39: 110.5 | AD39: 112.9
A40: Rural+Urban | B40: 2014 | C40: January | D40: 119.6 | E40: 118.8 | F40: 124.1 | G40: 114.1 | H40: 106.8 | I40: 113.9 | J40: 122.2 | K40: 108.9 | L40: 100.2 | M40: 111 | N40: 112.3 | O40: 118.1 | P40: 115.8 | Q40: 114.5 | R40: 115.8 | S40: 113.2 | T40: 115.4 | U40: 111.6 | V40: 112.2 | W40: 112.3 | X40: 110.3 | Y40: 110.7 | Z40: 109.7 | AA40: 111.6 | AB40: 108.2 | AC40: 110.6 | AD40: 113.6
A41: Rural | B41: 2014 | C41: February | D41: 119.4 | E41: 117.7 | F41: 121.2 | G41: 115 | H41: 109 | I41: 116.6 | J41: 116 | K41: 109.8 | L41: 101.1 | M41: 110.4 | N41: 112.9 | O41: 117.8 | P41: 115.3 | Q41: 114.2 | R41: 117.1 | S41: 114.5 | T41: 116.7 | V41: 113.2 | W41: 112.9 | X41: 110.9 | Y41: 110.8 | Z41: 109.9 | AA41: 112 | AB41: 108.7 | AC41: 110.9 | AD41: 114
A42: Urban | B42: 2014 | C42: February | D42: 121.9 | E42: 122 | F42: 124.5 | G42: 115.2 | H42: 102.5 | I42: 114.1 | J42: 111.5 | K42: 108.2 | L42: 95.4 | M42: 113.5 | N42: 112.1 | O42: 119.9 | P42: 115.2 | Q42: 116.2 | R42: 115.3 | S42: 111.7 | T42: 114.7 | U42: 112.5 | V42: 111.1 | W42: 112.6 | X42: 110.4 | Y42: 111.3 | Z42: 110.3 | AA42: 111.6 | AB42: 108.7 | AC42: 111 | AD42: 113.1
A43: Rural+Urban | B43: 2014 | C43: February | D43: 120.2 | E43: 119.2 | F43: 122.5 | G43: 115.1 | H43: 106.6 | I43: 115.4 | J43: 114.5 | K43: 109.3 | L43: 99.2 | M43: 111.4 | N43: 112.6 | O43: 118.8 | P43: 115.3 | Q43: 114.7 | R43: 116.4 | S43: 113.3 | T43: 115.9 | U43: 112.5 | V43: 112.4 | W43: 112.8 | X43: 110.7 | Y43: 111.1 | Z43: 110.1 | AA43: 111.8 | AB43: 108.7 | AC43: 110.9 | AD43: 113.6
A44: Rural | B44: 2014 | C44: March | D44: 120.1 | E44: 118.1 | F44: 120.7 | G44: 116.1 | H44: 109.3 | I44: 119.6 | J44: 117.9 | K44: 110.2 | L44: 101.2 | M44: 110.7 | N44: 113 | O44: 118.3 | P44: 116.2 | Q44: 114.6 | R44: 117.5 | S44: 114.9 | T44: 117.2 | V44: 113.4 | W44: 113.4 | X44: 111.4 | Y44: 111.2 | Z44: 110.2 | AA44: 112.4 | AB44: 108.9 | AC44: 111.3 | AD44: 114.6
A45: Urban | B45: 2014 | C45: March | D45: 122.1 | E45: 121.4 | F45: 121.5 | G45: 116.2 | H45: 102.8 | I45: 117.7 | J45: 113.3 | K45: 108.9 | L45: 96.3 | M45: 114.1 | N45: 112.2 | O45: 120.5 | P45: 116 | Q45: 116.7 | R45: 115.8 | S45: 112.1 | T45: 115.2 | U45: 113.2 | V45: 110.9 | W45: 113 | X45: 110.8 | Y45: 111.6 | Z45: 110.9 | AA45: 111.8 | AB45: 109.2 | AC45: 111.4 | AD45: 113.7
A46: Rural+Urban | B46: 2014 | C46: March | D46: 120.7 | E46: 119.3 | F46: 121 | G46: 116.1 | H46: 106.9 | I46: 118.7 | J46: 116.3 | K46: 109.8 | L46: 99.6 | M46: 111.8 | N46: 112.7 | O46: 119.3 | P46: 116.1 | Q46: 115.2 | R46: 116.8 | S46: 113.7 | T46: 116.4 | U46: 113.2 | V46: 112.5 | W46: 113.2 | X46: 111.2 | Y46: 111.4 | Z46: 110.6 | AA46: 112 | AB46: 109 | AC46: 111.3 | AD46: 114.2
A47: Rural | B47: 2014 | C47: April | D47: 120.2 | E47: 118.9 | F47: 118.1 | G47: 117 | H47: 109.7 | I47: 125.5 | J47: 120.5 | K47: 111 | L47: 102.6 | M47: 111.2 | N47: 113.5 | O47: 118.7 | P47: 117.2 | Q47: 115.4 | R47: 118.1 | S47: 116.1 | T47: 117.8 | V47: 113.4 | W47: 113.7 | X47: 111.8 | Y47: 111.2 | Z47: 110.5 | AA47: 113 | AB47: 108.9 | AC47: 111.5 | AD47: 115.4
A48: Urban | B48: 2014 | C48: April | D48: 122.5 | E48: 121.7 | F48: 113.3 | G48: 117 | H48: 103.1 | I48: 126.7 | J48: 121.2 | K48: 111 | L48: 100.3 | M48: 115.3 | N48: 112.7 | O48: 121 | P48: 118.2 | Q48: 117.6 | R48: 116.3 | S48: 112.5 | T48: 115.7 | U48: 113.9 | V48: 110.9 | W48: 113.4 | X48: 111 | Y48: 111.2 | Z48: 111.2 | AA48: 112.5 | AB48: 109.1 | AC48: 111.4 | AD48: 114.7
A49: Rural+Urban | B49: 2014 | C49: April | D49: 120.9 | E49: 119.9 | F49: 116.2 | G49: 117 | H49: 107.3 | I49: 126.1 | J49: 120.7 | K49: 111 | L49: 101.8 | M49: 112.6 | N49: 113.2 | O49: 119.8 | P49: 117.6 | Q49: 116 | R49: 117.4 | S49: 114.6 | T49: 117 | U49: 113.9 | V49: 112.5 | W49: 113.6 | X49: 111.5 | Y49: 111.2 | Z49: 110.9 | AA49: 112.7 | AB49: 109 | AC49: 111.5 | AD49: 115.1
A50: Rural | B50: 2014 | C50: May | D50: 120.3 | E50: 120.2 | F50: 116.9 | G50: 118 | H50: 110.1 | I50: 126.3 | J50: 123.9 | K50: 111.5 | L50: 103.5 | M50: 111.6 | N50: 114.2 | O50: 119.2 | P50: 118.2 | Q50: 116.3 | R50: 118.7 | S50: 116.8 | T50: 118.5 | V50: 113.4 | W50: 114.1 | X50: 112.1 | Y50: 111.4 | Z50: 110.9 | AA50: 113.1 | AB50: 108.9 | AC50: 111.8 | AD50: 116
A51: Urban | B51: 2014 | C51: May | D51: 122.7 | E51: 124.1 | F51: 114.2 | G51: 119.1 | H51: 103.5 | I51: 129.2 | J51: 127 | K51: 112.6 | L51: 101.3 | M51: 117 | N51: 112.9 | O51: 121.7 | P51: 120 | Q51: 118.3 | R51: 116.8 | S51: 112.9 | T51: 116.2 | U51: 114.3 | V51: 111.1 | W51: 114.1 | X51: 111.2 | Y51: 111.3 | Z51: 111.5 | AA51: 112.9 | AB51: 109.3 | AC51: 111.7 | AD51: 115.6
A52: Rural+Urban | B52: 2014 | C52: May | D52: 121.1 | E52: 121.6 | F52: 115.9 | G52: 118.4 | H52: 107.7 | I52: 127.7 | J52: 125 | K52: 111.9 | L52: 102.8 | M52: 113.4 | N52: 113.7 | O52: 120.4 | P52: 118.9 | Q52: 116.8 | R52: 118 | S52: 115.2 | T52: 117.6 | U52: 114.3 | V52: 112.5 | W52: 114.1 | X52: 111.8 | Y52: 111.3 | Z52: 111.2 | AA52: 113 | AB52: 109.1 | AC52: 111.8 | AD52: 115.8
A53: Rural | B53: 2014 | C53: June | D53: 120.7 | E53: 121.6 | F53: 116.1 | G53: 119.3 | H53: 110.3 | I53: 125.8 | J53: 129.3 | K53: 112.2 | L53: 103.6 | M53: 112.3 | N53: 114.9 | O53: 120.1 | P53: 119.5 | Q53: 117.3 | R53: 119.7 | S53: 117.3 | T53: 119.3 | V53: 114.4 | W53: 114.9 | X53: 112.8 | Y53: 112.2 | Z53: 111.4 | AA53: 114.3 | AB53: 108 | AC53: 112.3 | AD53: 117
A54: Urban | B54: 2014 | C54: June | D54: 123.1 | E54: 125.9 | F54: 115.4 | G54: 120.4 | H54: 103.4 | I54: 131.2 | J54: 137.5 | K54: 112.8 | L54: 101.4 | M54: 118.3 | N54: 113.2 | O54: 122.4 | P54: 122 | Q54: 119 | R54: 117.4 | S54: 113.2 | T54: 116.7 | U54: 113.9 | V54: 111.2 | W54: 114.3 | X54: 111.4 | Y54: 111.5 | Z54: 111.8 | AA54: 115.1 | AB54: 108.7 | AC54: 112.2 | AD54: 116.4
A55: Rural+Urban | B55: 2014 | C55: June | D55: 121.5 | E55: 123.1 | F55: 115.8 | G55: 119.7 | H55: 107.8 | I55: 128.3 | J55: 132.1 | K55: 112.4 | L55: 102.9 | M55: 114.3 | N55: 114.2 | O55: 121.2 | P55: 120.4 | Q55: 117.8 | R55: 118.8 | S55: 115.6 | T55: 118.3 | U55: 113.9 | V55: 113.2 | W55: 114.6 | X55: 112.3 | Y55: 111.8 | Z55: 111.6 | AA55: 114.8 | AB55: 108.3 | AC55: 112.3 | AD55: 116.7
A56: Rural | B56: 2014 | C56: July | D56: 121.7 | E56: 122.5 | F56: 117.7 | G56: 120.6 | H56: 110.4 | I56: 129.1 | J56: 150.1 | K56: 113.2 | L56: 104.8 | M56: 113.3 | N56: 115.6 | O56: 120.9 | P56: 123.3 | Q56: 118 | R56: 120.7 | S56: 118.3 | T56: 120.3 | V56: 115.3 | W56: 115.4 | X56: 113.4 | Y56: 113.2 | Z56: 111.8 | AA56: 115.5 | AB56: 108.8 | AC56: 113.1 | AD56: 119.5
A57: Urban | B57: 2014 | C57: July | D57: 123.8 | E57: 126.4 | F57: 118 | G57: 121.6 | H57: 103.5 | I57: 133.7 | J57: 172.4 | K57: 113.1 | L57: 102.7 | M57: 120 | N57: 113.8 | O57: 123.4 | P57: 127.1 | Q57: 121 | R57: 118 | S57: 113.6 | T57: 117.4 | U57: 114.8 | V57: 111.6 | W57: 114.9 | X57: 111.5 | Y57: 113 | Z57: 112.4 | AA57: 117.8 | AB57: 109.7 | AC57: 113.5 | AD57: 118.9
A58: Rural+Urban | B58: 2014 | C58: July | D58: 122.4 | E58: 123.9 | F58: 117.8 | G58: 121 | H58: 107.9 | I58: 131.2 | J58: 157.7 | K58: 113.2 | L58: 104.1 | M58: 115.5 | N58: 114.8 | O58: 122.1 | P58: 124.7 | Q58: 118.8 | R58: 119.6 | S58: 116.3 | T58: 119.1 | U58: 114.8 | V58: 113.9 | W58: 115.2 | X58: 112.7 | Y58: 113.1 | Z58: 112.1 | AA58: 116.8 | AB58: 109.2 | AC58: 113.3 | AD58: 119.2
A59: Rural | B59: 2014 | C59: August | D59: 121.8 | E59: 122.8 | F59: 117.8 | G59: 121.9 | H59: 110.6 | I59: 129.7 | J59: 161.1 | K59: 114.1 | L59: 105.1 | M59: 114.6 | N59: 115.8 | O59: 121.7 | P59: 125.3 | Q59: 118.8 | R59: 120.9 | S59: 118.8 | T59: 120.7 | V59: 115.4 | W59: 115.9 | X59: 114 | Y59: 113.2 | Z59: 112.2 | AA59: 116.2 | AB59: 109.4 | AC59: 113.5 | AD59: 120.7
A60: Urban | B60: 2014 | C60: August | D60: 124.8 | E60: 127.3 | F60: 116.5 | G60: 122.2 | H60: 103.6 | I60: 132.7 | J60: 181.9 | K60: 115.2 | L60: 102.7 | M60: 122.1 | N60: 114.4 | O60: 124.7 | P60: 128.9 | Q60: 123 | R60: 118.6 | S60: 114.1 | T60: 117.9 | U60: 115.5 | V60: 111.8 | W60: 115.3 | X60: 112.2 | Y60: 112.5 | Z60: 112.9 | AA60: 119.2 | AB60: 110.5 | AC60: 113.9 | AD60: 119.9
A61: Rural+Urban | B61: 2014 | C61: August | D61: 122.7 | E61: 124.4 | F61: 117.3 | G61: 122 | H61: 108 | I61: 131.1 | J61: 168.2 | K61: 114.5 | L61: 104.3 | M61: 117.1 | N61: 115.2 | O61: 123.1 | P61: 126.6 | Q61: 119.9 | R61: 120 | S61: 116.8 | T61: 119.6 | U61: 115.5 | V61: 114 | W61: 115.6 | X61: 113.3 | Y61: 112.8 | Z61: 112.6 | AA61: 118 | AB61: 109.9 | AC61: 113.7 | AD61: 120.3
A62: Rural | B62: 2014 | C62: September | D62: 122.3 | E62: 122.4 | F62: 117.8 | G62: 122.7 | H62: 110.4 | I62: 129.8 | J62: 158.8 | K62: 115 | L62: 104.7 | M62: 114.9 | N62: 116.5 | O62: 122.6 | P62: 125.3 | Q62: 119.5 | R62: 121.7 | S62: 119.2 | T62: 121.3 | V62: 115.8 | W62: 116.7 | X62: 114.5 | Y62: 112.8 | Z62: 112.6 | AA62: 116.6 | AB62: 109.1 | AC62: 113.7 | AD62: 120.9
A63: Urban | B63: 2014 | C63: September | D63: 124.2 | E63: 125.4 | F63: 116.4 | G63: 122.7 | H63: 103.5 | I63: 124.5 | J63: 168.6 | K63: 116.9 | L63: 101.9 | M63: 122.9 | N63: 114.8 | O63: 125.2 | P63: 126.7 | Q63: 124.3 | R63: 119.2 | S63: 114.5 | T63: 118.4 | U63: 116.1 | V63: 111.8 | W63: 115.5 | X63: 112.3 | Y63: 111.2 | Z63: 113.4 | AA63: 120 | AB63: 110 | AC63: 113.6 | AD63: 119.2
A64: Rural+Urban | B64: 2014 | C64: September | D64: 122.9 | E64: 123.5 | F64: 117.3 | G64: 122.7 | H64: 107.9 | I64: 127.3 | J64: 162.1 | K64: 115.6 | L64: 103.8 | M64: 117.6 | N64: 115.8 | O64: 123.8 | P64: 125.8 | Q64: 120.8 | R64: 120.7 | S64: 117.2 | T64: 120.1 | U64: 116.1 | V64: 114.3 | W64: 116.1 | X64: 113.7 | Y64: 112 | Z64: 113.1 | AA64: 118.6 | AB64: 109.5 | AC64: 113.7 | AD64: 120.1
A65: Rural | B65: 2014 | C65: October | D65: 122.6 | E65: 122.5 | F65: 118.3 | G65: 123.2 | H65: 110.5 | I65: 128.9 | J65: 155.3 | K65: 115.5 | L65: 104 | M65: 115.3 | N65: 116.8 | O65: 123.2 | P65: 125.1 | Q65: 120 | R65: 122.7 | S65: 120.3 | T65: 122.3 | V65: 116.4 | W65: 117.5 | X65: 115.3 | Y65: 112.6 | Z65: 113 | AA65: 116.9 | AB65: 109.3 | AC65: 114 | AD65: 121
A66: Urban | B66: 2014 | C66: October | D66: 124.6 | E66: 126.1 | F66: 117.8 | G66: 123.1 | H66: 103.5 | I66: 123.5 | J66: 159.6 | K66: 117.4 | L66: 101.2 | M66: 123.8 | N66: 115.2 | O66: 125.9 | P66: 125.8 | Q66: 124.3 | R66: 119.6 | S66: 114.9 | T66: 118.9 | U66: 116.7 | V66: 112 | W66: 115.8 | X66: 112.6 | Y66: 111 | Z66: 113.6 | AA66: 120.2 | AB66: 110.1 | AC66: 113.7 | AD66: 119.1
A67: Rural+Urban | B67: 2014 | C67: October | D67: 123.2 | E67: 123.8 | F67: 118.1 | G67: 123.2 | H67: 107.9 | I67: 126.4 | J67: 156.8 | K67: 116.1 | L67: 103.1 | M67: 118.1 | N67: 116.1 | O67: 124.5 | P67: 125.4 | Q67: 121.1 | R67: 121.5 | S67: 118.1 | T67: 121 | U67: 116.7 | V67: 114.7 | W67: 116.7 | X67: 114.3 | Y67: 111.8 | Z67: 113.3 | AA67: 118.8 | AB67: 109.6 | AC67: 113.9 | AD67: 120.1
A68: Rural | B68: 2014 | C68: November | D68: 122.7 | E68: 122.6 | F68: 119.9 | G68: 124 | H68: 110.5 | I68: 128.8 | J68: 152 | K68: 116.2 | L68: 103.3 | M68: 115.8 | N68: 116.8 | O68: 124.5 | P68: 124.9 | Q68: 120.8 | R68: 123.3 | S68: 120.5 | T68: 122.9 | V68: 117.3 | W68: 118.1 | X68: 115.9 | Y68: 112 | Z68: 113.3 | AA68: 117.2 | AB68: 108.8 | AC68: 114.1 | AD68: 121.1
A69: Urban | B69: 2014 | C69: November | D69: 124.5 | E69: 125.6 | F69: 122.7 | G69: 124.6 | H69: 103.2 | I69: 122.2 | J69: 153.2 | K69: 119.3 | L69: 99.8 | M69: 124.6 | N69: 115.8 | O69: 126.9 | P69: 125.4 | Q69: 125.8 | R69: 120.3 | S69: 115.4 | T69: 119.5 | U69: 117.1 | V69: 112.6 | W69: 116.4 | X69: 113 | Y69: 109.7 | Z69: 114 | AA69: 120.3 | AB69: 109.6 | AC69: 113.4 | AD69: 119
A70: Rural+Urban | B70: 2014 | C70: November | D70: 123.3 | E70: 123.7 | F70: 121 | G70: 124.2 | H70: 107.8 | I70: 125.7 | J70: 152.4 | K70: 117.2 | L70: 102.1 | M70: 118.7 | N70: 116.4 | O70: 125.6 | P70: 125.1 | Q70: 122.1 | R70: 122.1 | S70: 118.4 | T70: 121.6 | U70: 117.1 | V70: 115.5 | W70: 117.3 | X70: 114.8 | Y70: 110.8 | Z70: 113.7 | AA70: 119 | AB70: 109.1 | AC70: 113.8 | AD70: 120.1
A71: Rural | B71: 2014 | C71: December | D71: 122.4 | E71: 122.4 | F71: 121.8 | G71: 124.2 | H71: 110.2 | I71: 128.6 | J71: 140.3 | K71: 116.3 | L71: 102 | M71: 116 | N71: 117.3 | O71: 124.8 | P71: 123.3 | Q71: 121.7 | R71: 123.8 | S71: 120.6 | T71: 123.3 | V71: 117.4 | W71: 118.2 | X71: 116.2 | Y71: 111.5 | Z71: 113.3 | AA71: 117.7 | AB71: 109.4 | AC71: 114.2 | AD71: 120.3
A72: Urban | B72: 2014 | C72: December | D72: 124 | E72: 124.7 | F72: 126.3 | G72: 124.9 | H72: 103 | I72: 122.3 | J72: 141 | K72: 120.1 | L72: 97.8 | M72: 125.4 | N72: 116.1 | O72: 127.6 | P72: 124 | Q72: 126.4 | R72: 120.7 | S72: 115.8 | T72: 120 | U72: 116.5 | V72: 113 | W72: 116.8 | X72: 113.2 | Y72: 108.8 | Z72: 114.3 | AA72: 120.7 | AB72: 110.4 | AC72: 113.4 | AD72: 118.4
A73: Rural+Urban | B73: 2014 | C73: December | D73: 122.9 | E73: 123.2 | F73: 123.5 | G73: 124.5 | H73: 107.6 | I73: 125.7 | J73: 140.5 | K73: 117.6 | L73: 100.6 | M73: 119.1 | N73: 116.8 | O73: 126.1 | P73: 123.6 | Q73: 123 | R73: 122.6 | S73: 118.6 | T73: 122 | U73: 116.5 | V73: 115.7 | W73: 117.5 | X73: 115.1 | Y73: 110.1 | Z73: 113.9 | AA73: 119.5 | AB73: 109.8 | AC73: 113.8 | AD73: 119.4
A74: Rural | B74: 2015 | C74: January | D74: 123.1 | E74: 123.1 | F74: 122.1 | G74: 124.9 | H74: 111 | I74: 130.4 | J74: 132.3 | K74: 117.2 | L74: 100.5 | M74: 117.2 | N74: 117.9 | O74: 125.6 | P74: 122.8 | Q74: 122.7 | R74: 124.4 | S74: 121.6 | T74: 124 | V74: 118.4 | W74: 118.9 | X74: 116.6 | Y74: 111 | Z74: 114 | AA74: 118.2 | AB74: 110.2 | AC74: 114.5 | AD74: 120.3
A75: Urban | B75: 2015 | C75: January | D75: 124 | E75: 125.5 | F75: 126.6 | G75: 125.2 | H75: 104.3 | I75: 121.3 | J75: 134.4 | K75: 122.9 | L75: 96.1 | M75: 126.6 | N75: 116.5 | O75: 128 | P75: 123.5 | Q75: 127.4 | R75: 121 | S75: 116.1 | T75: 120.2 | U75: 117.3 | V75: 113.4 | W75: 117.2 | X75: 113.7 | Y75: 107.9 | Z75: 114.6 | AA75: 120.8 | AB75: 111.4 | AC75: 113.4 | AD75: 118.5
A76: Rural+Urban | B76: 2015 | C76: January | D76: 123.4 | E76: 123.9 | F76: 123.8 | G76: 125 | H76: 108.5 | I76: 126.2 | J76: 133 | K76: 119.1 | L76: 99 | M76: 120.3 | N76: 117.3 | O76: 126.7 | P76: 123.1 | Q76: 124 | R76: 123.1 | S76: 119.3 | T76: 122.5 | U76: 117.3 | V76: 116.5 | W76: 118.1 | X76: 115.5 | Y76: 109.4 | Z76: 114.3 | AA76: 119.7 | AB76: 110.7 | AC76: 114 | AD76: 119.5
A77: Rural | B77: 2015 | C77: February | D77: 123.4 | E77: 124.4 | F77: 122.1 | G77: 125.8 | H77: 111.5 | I77: 129.4 | J77: 128.2 | K77: 118.8 | L77: 100 | M77: 118.6 | N77: 118.8 | O77: 126.8 | P77: 122.8 | Q77: 124.2 | R77: 125.4 | S77: 122.7 | T77: 125 | V77: 120 | W77: 119.6 | X77: 117.7 | Y77: 110.9 | Z77: 114.8 | AA77: 118.7 | AB77: 110.8 | AC77: 115 | AD77: 120.6
A78: Urban | B78: 2015 | C78: February | D78: 124.3 | E78: 126.5 | F78: 119.5 | G78: 125.6 | H78: 104.9 | I78: 121.6 | J78: 131.8 | K78: 125.1 | L78: 95 | M78: 127.7 | N78: 116.8 | O78: 128.6 | P78: 123.7 | Q78: 128.1 | R78: 121.3 | S78: 116.5 | T78: 120.6 | U78: 118.1 | V78: 114 | W78: 117.7 | X78: 114.1 | Y78: 106.8 | Z78: 114.9 | AA78: 120.4 | AB78: 111.7 | AC78: 113.2 | AD78: 118.7
A79: Rural+Urban | B79: 2015 | C79: February | D79: 123.7 | E79: 125.1 | F79: 121.1 | G79: 125.7 | H79: 109.1 | I79: 125.8 | J79: 129.4 | K79: 120.9 | L79: 98.3 | M79: 121.6 | N79: 118 | O79: 127.6 | P79: 123.1 | Q79: 125.2 | R79: 123.8 | S79: 120.1 | T79: 123.3 | U79: 118.1 | V79: 117.7 | W79: 118.7 | X79: 116.3 | Y79: 108.7 | Z79: 114.9 | AA79: 119.7 | AB79: 111.2 | AC79: 114.1 | AD79: 119.7
A80: Rural | B80: 2015 | C80: March | D80: 123.3 | E80: 124.7 | F80: 118.9 | G80: 126 | H80: 111.8 | I80: 130.9 | J80: 128 | K80: 119.9 | L80: 98.9 | M80: 119.4 | N80: 118.9 | O80: 127.7 | P80: 123.1 | Q80: 124.7 | R80: 126 | S80: 122.9 | T80: 125.5 | V80: 120.6 | W80: 120.2 | X80: 118.2 | Y80: 111.6 | Z80: 115.5 | AA80: 119.4 | AB80: 110.8 | AC80: 115.5 | AD80: 121.1
A81: Urban | B81: 2015 | C81: March | D81: 124 | E81: 126.7 | F81: 113.5 | G81: 125.9 | H81: 104.8 | I81: 123.8 | J81: 131.4 | K81: 127.2 | L81: 93.2 | M81: 127.4 | N81: 117 | O81: 129.2 | P81: 123.9 | Q81: 128.8 | R81: 121.7 | S81: 116.9 | T81: 120.9 | U81: 118.6 | V81: 114.4 | W81: 118 | X81: 114.3 | Y81: 108.4 | Z81: 115.4 | AA81: 120.6 | AB81: 111.3 | AC81: 113.8 | AD81: 119.1
A82: Rural+Urban | B82: 2015 | C82: March | D82: 123.5 | E82: 125.4 | F82: 116.8 | G82: 126 | H82: 109.2 | I82: 127.6 | J82: 129.2 | K82: 122.4 | L82: 97 | M82: 122.1 | N82: 118.1 | O82: 128.4 | P82: 123.4 | Q82: 125.8 | R82: 124.3 | S82: 120.4 | T82: 123.7 | U82: 118.6 | V82: 118.3 | W82: 119.2 | X82: 116.7 | Y82: 109.9 | Z82: 115.4 | AA82: 120.1 | AB82: 111 | AC82: 114.7 | AD82: 120.2
A83: Rural | B83: 2015 | C83: April | D83: 123.3 | E83: 125.5 | F83: 117.2 | G83: 126.8 | H83: 111.9 | I83: 134.2 | J83: 127.5 | K83: 121.5 | L83: 97.8 | M83: 119.8 | N83: 119.4 | O83: 128.7 | P83: 123.6 | Q83: 125.7 | R83: 126.4 | S83: 123.3 | T83: 126 | V83: 121.2 | W83: 120.9 | X83: 118.6 | Y83: 111.9 | Z83: 116.2 | AA83: 119.9 | AB83: 111.6 | AC83: 116 | AD83: 121.5
A84: Urban | B84: 2015 | C84: April | D84: 123.8 | E84: 128.2 | F84: 110 | G84: 126.3 | H84: 104.5 | I84: 130.6 | J84: 130.8 | K84: 131.3 | L84: 91.6 | M84: 127.7 | N84: 117.2 | O84: 129.5 | P84: 124.6 | Q84: 130.1 | R84: 122.1 | S84: 117.2 | T84: 121.3 | U84: 119.2 | V84: 114.7 | W84: 118.4 | X84: 114.6 | Y84: 108.4 | Z84: 115.6 | AA84: 121.7 | AB84: 111.8 | AC84: 114.2 | AD84: 119.7
A85: Rural+Urban | B85: 2015 | C85: April | D85: 123.5 | E85: 126.4 | F85: 114.4 | G85: 126.6 | H85: 109.2 | I85: 132.5 | J85: 128.6 | K85: 124.8 | L85: 95.7 | M85: 122.4 | N85: 118.5 | O85: 129.1 | P85: 124 | Q85: 126.9 | R85: 124.7 | S85: 120.8 | T85: 124.1 | U85: 119.2 | V85: 118.7 | W85: 119.7 | X85: 117.1 | Y85: 110.1 | Z85: 115.9 | AA85: 121 | AB85: 111.7 | AC85: 115.1 | AD85: 120.7
A86: Rural | B86: 2015 | C86: May | D86: 123.5 | E86: 127.1 | F86: 117.3 | G86: 127.7 | H86: 112.5 | I86: 134.1 | J86: 128.5 | K86: 124.3 | L86: 97.6 | M86: 120.7 | N86: 120.2 | O86: 129.8 | P86: 124.4 | Q86: 126.7 | R86: 127.3 | S86: 124.1 | T86: 126.8 | V86: 121.9 | W86: 121.5 | X86: 119.4 | Y86: 113.3 | Z86: 116.7 | AA86: 120.5 | AB86: 112.3 | AC86: 116.9 | AD86: 122.4
A87: Urban | B87: 2015 | C87: May | D87: 123.8 | E87: 129.7 | F87: 111.3 | G87: 126.6 | H87: 105.2 | I87: 130.8 | J87: 135.6 | K87: 142.6 | L87: 90.8 | M87: 128.8 | N87: 117.7 | O87: 129.9 | P87: 126.1 | Q87: 131.3 | R87: 122.4 | S87: 117.4 | T87: 121.6 | U87: 119.6 | V87: 114.9 | W87: 118.7 | X87: 114.9 | Y87: 110.8 | Z87: 116 | AA87: 122 | AB87: 112.4 | AC87: 115.2 | AD87: 120.7
A88: Rural+Urban | B88: 2015 | C88: May | D88: 123.6 | E88: 128 | F88: 115 | G88: 127.3 | H88: 109.8 | I88: 132.6 | J88: 130.9 | K88: 130.5 | L88: 95.3 | M88: 123.4 | N88: 119.2 | O88: 129.8 | P88: 125 | Q88: 127.9 | R88: 125.4 | S88: 121.3 | T88: 124.7 | U88: 119.6 | V88: 119.2 | W88: 120.2 | X88: 117.7 | Y88: 112 | Z88: 116.3 | AA88: 121.4 | AB88: 112.3 | AC88: 116.1 | AD88: 121.6
A89: Rural | B89: 2015 | C89: June | D89: 124.1 | E89: 130.4 | F89: 122.1 | G89: 128.7 | H89: 114.1 | I89: 133.2 | J89: 135.2 | K89: 131.9 | L89: 96.3 | M89: 123 | N89: 121.1 | O89: 131.2 | P89: 126.6 | Q89: 128.2 | R89: 128.4 | S89: 125.1 | T89: 128 | V89: 122.6 | W89: 122.8 | X89: 120.4 | Y89: 114.2 | Z89: 117.9 | AA89: 122 | AB89: 113 | AC89: 117.9 | AD89: 124.1
A90: Urban | B90: 2015 | C90: June | D90: 123.6 | E90: 134.4 | F90: 120.9 | G90: 127.3 | H90: 106 | I90: 132.3 | J90: 146.7 | K90: 148.1 | L90: 89.8 | M90: 130.5 | N90: 118 | O90: 130.5 | P90: 128.5 | Q90: 132.1 | R90: 123.2 | S90: 117.6 | T90: 122.3 | U90: 119 | V90: 115.1 | W90: 119.2 | X90: 115.4 | Y90: 111.7 | Z90: 116.2 | AA90: 123.8 | AB90: 112.5 | AC90: 116 | AD90: 121.7
A91: Rural+Urban | B91: 2015 | C91: June | D91: 123.9 | E91: 131.8 | F91: 121.6 | G91: 128.2 | H91: 111.1 | I91: 132.8 | J91: 139.1 | K91: 137.4 | L91: 94.1 | M91: 125.5 | N91: 119.8 | O91: 130.9 | P91: 127.3 | Q91: 129.2 | R91: 126.4 | S91: 122 | T91: 125.7 | U91: 119 | V91: 119.8 | W91: 121.1 | X91: 118.5 | Y91: 112.9 | Z91: 116.9 | AA91: 123.1 | AB91: 112.8 | AC91: 117 | AD91: 123
A92: Rural | B92: 2015 | C92: July | D92: 124 | E92: 131.5 | F92: 122 | G92: 128.7 | H92: 113.5 | I92: 133.3 | J92: 140.8 | K92: 133.8 | L92: 94.1 | M92: 123.4 | N92: 121 | O92: 131.7 | P92: 127.5 | Q92: 129.4 | R92: 128.8 | S92: 125.5 | T92: 128.3 | V92: 123 | W92: 123 | X92: 120.8 | Y92: 114.1 | Z92: 118 | AA92: 122.9 | AB92: 112.7 | AC92: 118.1 | AD92: 124.7
A93: Urban | B93: 2015 | C93: July | D93: 123.2 | E93: 134.3 | F93: 119.5 | G93: 127.7 | H93: 106.3 | I93: 132.8 | J93: 153.5 | K93: 149.5 | L93: 85.7 | M93: 131.5 | N93: 118.3 | O93: 131.1 | P93: 129.5 | Q93: 133.1 | R93: 123.5 | S93: 117.9 | T93: 122.7 | U93: 119.9 | V93: 115.3 | W93: 119.5 | X93: 116 | Y93: 111.5 | Z93: 116.6 | AA93: 125.4 | AB93: 111.7 | AC93: 116.3 | AD93: 122.4
A94: Rural+Urban | B94: 2015 | C94: July | D94: 123.7 | E94: 132.5 | F94: 121 | G94: 128.3 | H94: 110.9 | I94: 133.1 | J94: 145.1 | K94: 139.1 | L94: 91.3 | M94: 126.1 | N94: 119.9 | O94: 131.4 | P94: 128.2 | Q94: 130.4 | R94: 126.7 | S94: 122.3 | T94: 126.1 | U94: 119.9 | V94: 120.1 | W94: 121.3 | X94: 119 | Y94: 112.7 | Z94: 117.2 | AA94: 124.4 | AB94: 112.3 | AC94: 117.2 | AD94: 123.6
A95: Rural | B95: 2015 | C95: August | D95: 124.7 | E95: 131.3 | F95: 121.3 | G95: 128.8 | H95: 114 | I95: 134.2 | J95: 153.6 | K95: 137.9 | L95: 93.1 | M95: 123.9 | N95: 121.5 | O95: 132.5 | P95: 129.8 | Q95: 130.1 | R95: 129.5 | S95: 126.3 | T95: 129 | V95: 123.8 | W95: 123.7 | X95: 121.1 | Y95: 113.6 | Z95: 118.5 | AA95: 123.6 | AB95: 112.5 | AC95: 118.2 | AD95: 126.1
A96: Urban | B96: 2015 | C96: August | D96: 123.1 | E96: 131.7 | F96: 118.1 | G96: 128 | H96: 106.8 | I96: 130.1 | J96: 165.5 | K96: 156 | L96: 85.3 | M96: 132.7 | N96: 118.8 | O96: 131.7 | P96: 131.1 | Q96: 134.2 | R96: 123.7 | S96: 118.2 | T96: 122.9 | U96: 120.9 | V96: 115.3 | W96: 120 | X96: 116.6 | Y96: 109.9 | Z96: 117.2 | AA96: 126.2 | AB96: 112 | AC96: 116.2 | AD96: 123.2
A97: Rural+Urban | B97: 2015 | C97: August | D97: 124.2 | E97: 131.4 | F97: 120.1 | G97: 128.5 | H97: 111.4 | I97: 132.3 | J97: 157.6 | K97: 144 | L97: 90.5 | M97: 126.8 | N97: 120.4 | O97: 132.1 | P97: 130.3 | Q97: 131.2 | R97: 127.2 | S97: 122.9 | T97: 126.6 | U97: 120.9 | V97: 120.6 | W97: 122 | X97: 119.4 | Y97: 111.7 | Z97: 117.8 | AA97: 125.1 | AB97: 112.3 | AC97: 117.2 | AD97: 124.8
A98: Rural | B98: 2015 | C98: September | D98: 125.1 | E98: 131.1 | F98: 120.7 | G98: 129.2 | H98: 114.7 | I98: 132.3 | J98: 158.9 | K98: 142.1 | L98: 92.5 | M98: 125.4 | N98: 121.9 | O98: 132.7 | P98: 131 | Q98: 131 | R98: 130.4 | S98: 126.8 | T98: 129.9 | V98: 123.7 | W98: 124.5 | X98: 121.4 | Y98: 113.8 | Z98: 119.6 | AA98: 124.5 | AB98: 113.7 | AC98: 118.8 | AD98: 127
A99: Urban | B99: 2015 | C99: September | D99: 123.4 | E99: 129 | F99: 115.6 | G99: 128.3 | H99: 107 | I99: 124 | J99: 168.5 | K99: 165.4 | L99: 86.3 | M99: 134.4 | N99: 119.1 | O99: 132.3 | P99: 131.5 | Q99: 134.7 | R99: 124 | S99: 118.6 | T99: 123.2 | U99: 121.6 | V99: 115.1 | W99: 120.4 | X99: 117.1 | Y99: 109.1 | Z99: 117.3 | AA99: 126.5 | AB99: 112.9 | AC99: 116.2 | AD99: 123.5
A100: Rural+Urban | B100: 2015 | C100: September | D100: 124.6 | E100: 130.4 | F100: 118.7 | G100: 128.9 | H100: 111.9 | I100: 128.4 | J100: 162.2 | K100: 150 | L100: 90.4 | M100: 128.4 | N100: 120.7 | O100: 132.5 | P100: 131.2 | Q100: 132 | R100: 127.9 | S100: 123.4 | T100: 127.2 | U100: 121.6 | V100: 120.4 | W100: 122.6 | X100: 119.8 | Y100: 111.3 | Z100: 118.3 | AA100: 125.7 | AB100: 113.4 | AC100: 117.5 | AD100: 125.4
...

Sheet Data Quality Check
A1: Data Cleaning & Quality Check
E2: ← Dashboard
A3: Check | B3: Before Cleaning | C3: Action Taken | D3: After Cleaning
A4: Rows | B4: 372 | C4: No rows removed | D4: 372
A5: Columns | B5: 30 | C5: No columns removed | D5: 30
A6: Duplicate rows | B6: 0 | C6: Checked; none found | D6: 0
A7: Month typo | B7: Marcrh (1 row) | C7: Corrected to March | D7: No invalid month labels
A8: Month whitespace | B8: November + trailing space | C8: Trimmed text | D8: All month labels standardized
A9: Housing '-' values | B9: 4 | C9: Converted '-' to missing numeric value | D9: Missing values retained as blank/NA
A10: Numeric CPI fields | B10: Housing was text/object | C10: Converted CPI measure columns to numeric | D10: Housing and all CPI measures numeric
A13: Missing-value policy
A14: Missing values are not automatically replaced. They remain blank/NA unless a specific requires an imputation method (for example, a moving average). This prevents fabricated CPI values.
A18: Excel / Data Cleaning Method Notes
A19: TRIM / text standardization | B19: Whitespace was removed from text fields such as Month and Sector so categories match consistently.
A20: Numeric conversion | B20: CPI measurement fields were converted to numeric data types; non-numeric '-' values were treated as missing.
A21: Missing values | B21: Missing values are retained unless a specific requires an estimation method. Any such estimation is documented directly in the relevant analysis sheet.

Sheet Category Mapping
A1: Detailed CPI Category | B1: Broader Category | C1: Mapping Logic
A2: Cereals and products | B2: Food | C2: Food & beverages component | D2: ← Dashboard
A3: Meat and fish | B3: Food | C3: Food & beverages component
A4: Egg | B4: Food | C4: Food & beverages component
A5: Milk and products | B5: Food | C5: Food & beverages component
A6: Oils and fats | B6: Food | C6: Food & beverages component
A7: Fruits | B7: Food | C7: Food & beverages component
A8: Vegetables | B8: Food | C8: Food & beverages component
A9: Pulses and products | B9: Food | C9: Food & beverages component
A10: Sugar and Confectionery | B10: Food | C10: Food & beverages component
A11: Spices | B11: Food | C11: Food & beverages component
A12: Non-alcoholic beverages | B12: Food | C12: Food & beverages component
A13: Prepared meals, snacks, sweets etc. | B13: Food | C13: Food & beverages component
A14: Pan, tobacco and intoxicants | B14: Pan, Tobacco & Intoxicants | C14: Standalone broad category
... A24: Personal care and effects | B24: Personal Care & Effects | C24: Miscellaneous component
A27: Q1 Note
A28: Aggregate/index columns are intentionally excluded from this mapping to avoid double-counting.
A29: Excluded from component-level calculations: Food and beverages, Clothing and footwear, Miscellaneous, General index.
A30: The case study specifies equal weights across categories; the calculation methodology will be documented in the Q1 Analysis sheet.

Sheet Q1 Analysis
A1: India CPI Inflation Case Study — Q1 Analysis
E2: ← Dashboard
A3: Question | B3: Based on the latest month's data, identifing the contribution of different broader categories towards the CPI calculation.
A6: Latest Year | B6: 2023 | C6: Latest Month | D6: May
A7: Sector Used | B7: 32
A9: Calculation
A10: For each broader category, the underlying detailed CPI index values are averaged using equal weights, as instructed by the case study. Contribution % = Broader Category Index ÷ Sum of Broader Category Indices × 100. Aggregate/index columns are excluded to avoid double-counting.
A14: Broader Category | B14: Components Used | C14: Category Index | D14: Contribution %
A15: ='Q1 Calculation'!A7 -> Food | B15: ='Q1 Calculation'!C7 -> 12 | C15: ='Q1 Calculation'!E7 -> 175.78182 | D15: ='Q1 Calculation'!F7 -> 0.088873772
A16: ='Q1 Calculation'!A8 -> Pan, Tobacco & Intoxicants | B16: ='Q1 Calculation'!C8 -> 1 | C16: ='Q1 Calculation'!E8 -> 201 | D16: ='Q1 Calculation'!F8 -> 0.10162387
A17: ='Q1 Calculation'!A9 -> Clothing & Footwear | B17: ='Q1 Calculation'!C9 -> 2 | C17: ='Q1 Calculation'!E9 -> 183.5 | D17: ='Q1 Calculation'!F9 -> 0.092776018
A18: ='Q1 Calculation'!A10 -> Housing | B18: ='Q1 Calculation'!C10 -> 1 | C18: ='Q1 Calculation'!E10 -> 175.6 | D18: ='Q1 Calculation'!F10 -> 0.088781847
A19: ='Q1 Calculation'!A11 -> Fuel & Light | B19: ='Q1 Calculation'!C11 -> 1 | C19: ='Q1 Calculation'!E11 -> 182.8 | D19: ='Q1 Calculation'!F11 -> 0.092422104
A20: ='Q1 Calculation'!A12 -> Household Goods & Services | B20: ='Q1 Calculation'!C12 -> 1 | C20: ='Q1 Calculation'!E12 -> 175.2 | D20: ='Q1 Calculation'!F12 -> 0.08857961
A21: ='Q1 Calculation'!A13 -> Health | B21: ='Q1 Calculation'!C13 -> 1 | C21: ='Q1 Calculation'!E13 -> 185.7 | D21: ='Q1 Calculation'!F13 -> 0.093888319
A22: ='Q1 Calculation'!A14 -> Transport & Communication | B22: ='Q1 Calculation'!C14 -> 1 | C22: ='Q1 Calculation'!E14 -> 164.8 | D22: ='Q1 Calculation'!F14 -> 0.08332146
A23: ='Q1 Calculation'!A15 -> Recreation & Amusement | B23: ='Q1 Calculation'!C15 -> 1 | C23: ='Q1 Calculation'!E15 -> 171.2 | D23: ='Q1 Calculation'!F15 -> 0.086557244
A24: ='Q1 Calculation'!A16 -> Education | B24: ='Q1 Calculation'!C16 -> 1 | C24: ='Q1 Calculation'!E16 -> 177.1 | D24: ='Q1 Calculation'!F16 -> 0.089540234
A25: ='Q1 Calculation'!A17 -> Personal Care & Effects | B25: ='Q1 Calculation'!C17 -> 1 | C25: ='Q1 Calculation'!E17 -> 185.2 | D25: ='Q1 Calculation'!F17 -> 0.093635524
A26: Total | C26: =SUM(C15:C25) -> 1977.8818 | D26: =SUM(D15:D25) -> 1
A29: Key Result | B29: =INDEX(A15:A25,MATCH(MAX(D15:D25),D15:D25,0)) -> Pan, Tobacco & Intoxicants | D29: =MAX(D15:D25) -> 0.10162387
A30: Highest Contributing Category | B30: Pan, Tobacco & Intoxicants | C30: Contribution | D30: 0.10154507
A32: Interview Insight
A33: In May 2023, under the case study's equal-weight assumption, Pan, Tobacco & Intoxicants has the highest calculated contribution to the CPI basket at 10.15%.
A37: Function / Method Notes
A38: AVERAGE | B38: Used in Q1 Calculation to derive each broader category's equal-weighted index from its detailed CPI components.
A39: SUM | B39: Used to total broader-category indices and to verify that contribution percentages sum to 100%.
A40: IF | B40: Used for the contribution validation check, returning OK/CHECK based on whether the total equals 100%.
A41: Key-result formulas
A42: INDEX + MATCH + MAX | B42: Finds the category name associated with the highest Contribution %; MAX finds the highest contribution.

Sheet Q1 Calculation
A1: Q1 — CPI Broad Category Calculation
L2: ← Dashboard
A3: Latest Period | B3: May 2023 | D3: Sector | E3: Rural+Urban
J5: Latest Period Component Values
A6: Broader Category | B6: Underlying Components | C6: Components Used | D6: Sum of Component Indices | E6: Equal-Weighted Category Index | F6: Contribution % | G6: Contribution Check | H6: Formula / Logic | J6: Detailed Category | K6: Index Value
A7: Food | B7: Cereals and products, Meat and fish, Egg, Milk and products, Oils and fats, Fruits, Vegetables, Pulses and products, Sugar and Confectionery, Spices, Non-alcoholic beverages, Prepared meals, snacks, sweets etc. | C7: 12 | D7: =$K$7+$K$8+$K$9+$K$10+$K$11+$K$12+$K$13+$K$14+$K$16+$K$17 -> 1810.9 | E7: =AVERAGE($K$7,$K$8,$K$9,$K$10,$K$11,$K$12,$K$13,$K$14,$K$15,$K$16,$K$17) -> 175.78182 | F7: =E7/SUM($E$7:$E$17) -> 0.088873772 | G7: =IF(ABS(SUM($F$7:$F$17)-1)<0.000001,"OK","CHECK") -> OK | H7: SUM of underlying component indices → total component index; AVERAGE of underlying component indices → equal-weighted broader-category index; contribution = category index ÷ SUM of all broader-category indices. | J7: Cereals and products | K7: 173.7
A8: Pan, Tobacco & Intoxicants | B8: Pan, tobacco and intoxicants | C8: 1 | D8: =$K$19 -> 201 | E8: =D8/C8 -> 201 | F8: =E8/SUM($E$7:$E$17) -> 0.10162387 | G8: =IF(ABS(SUM($F$7:$F$17)-1)<0.000001,"OK","CHECK") -> OK | H8: Average underlying detailed CPI indices; contribution = category index ÷ sum of category indices | J8: Meat and fish | K8: 214.3
A9: Clothing & Footwear | B9: Clothing, Footwear | C9: 2 | D9: =$K$20+$K$21 -> 367 | E9: =AVERAGE($K$20,$K$21) -> 183.5 | F9: =E9/SUM($E$7:$E$17) -> 0.092776018 | G9: =IF(ABS(SUM($F$7:$F$17)-1)<0.000001,"OK","CHECK") -> OK | H9: SUM of underlying component indices → total component index; AVERAGE of underlying component indices → equal-weighted broader-category index; contribution = category index ÷ SUM of all broader-category indices. | J9: Egg | K9: 173.2
A10: Housing | B10: Housing | C10: 1 | D10: =$K$22 -> 175.6 | E10: =AVERAGE($K$22) -> 175.6 | F10: =E10/SUM($E$7:$E$17) -> 0.088781847 | G10: =IF(ABS(SUM($F$7:$F$17)-1)<0.000001,"OK","CHECK") -> OK | H10: SUM of underlying component indices → total component index; AVERAGE of underlying component indices → equal-weighted broader-category index; contribution = category index ÷ SUM of all broader-category indices. | J10: Milk and products | K10: 179.5
A11: Fuel & Light | B11: Fuel and light | C11: 1 | D11: =$K$23 -> 182.8 | E11: =AVERAGE($K$23) -> 182.8 | F11: =E11/SUM($E$7:$E$17) -> 0.092422104 | G11: =IF(ABS(SUM($F$7:$F$17)-1)<0.000001,"OK","CHECK") -> OK | H11: SUM of underlying component indices → total component index; AVERAGE of underlying component indices → equal-weighted broader-category index; contribution = category index ÷ SUM of all broader-category indices. | J11: Oils and fats | K11: 170
A12: Household Goods & Services | B12: Household goods and services | C12: 1 | D12: =$K$24 -> 175.2 | E12: =AVERAGE($K$24) -> 175.2 | F12: =E12/SUM($E$7:$E$17) -> 0.08857961 | G12: =IF(ABS(SUM($F$7:$F$17)-1)<0.000001,"OK","CHECK") -> OK | H12: SUM of underlying component indices → total component index; AVERAGE of underlying component indices → equal-weighted broader-category index; contribution = category index ÷ SUM of all broader-category indices. | J12: Fruits | K12: 172.2
A13: Health | B13: Health | C13: 1 | D13: =$K$25 -> 185.7 | E13: =AVERAGE($K$25) -> 185.7 | F13: =E13/SUM($E$7:$E$17) -> 0.093888319 | G13: =IF(ABS(SUM($F$7:$F$17)-1)<0.000001,"OK","CHECK") -> OK | H13: SUM of underlying component indices → total component index; AVERAGE of underlying component indices → equal-weighted broader-category index; contribution = category index ÷ SUM of all broader-category indices. | J13: Vegetables | K13: 161
A14: Transport & Communication | B14: Transport and communication | C14: 1 | D14: =$K$26 -> 164.8 | E14: =AVERAGE($K$26) -> 164.8 | F14: =E14/SUM($E$7:$E$17) -> 0.08332146 | G14: =IF(ABS(SUM($F$7:$F$17)-1)<0.000001,"OK","CHECK") -> OK | H14: SUM of underlying component indices → total component index; AVERAGE of underlying component indices → equal-weighted broader-category index; contribution = category index ÷ SUM of all broader-category indices. | J14: Pulses and products | K14: 175.6
A15: Recreation & Amusement | B15: Recreation and amusement | C15: 1 | D15: =$K$27 -> 171.2 | E15: =AVERAGE($K$27) -> 171.2 | F15: =E15/SUM($E$7:$E$17) -> 0.086557244 | G15: =IF(ABS(SUM($F$7:$F$17)-1)<0.000001,"OK","CHECK") -> OK | H15: SUM of underlying component indices → total component index; AVERAGE of underlying component indices → equal-weighted broader-category index; contribution = category index ÷ SUM of all broader-category indices. | J15: Sugar and Confectionery | K15: 122.7
A16: Education | B16: Education | C16: 1 | D16: =$K$28 -> 177.1 | E16: =AVERAGE($K$28) -> 177.1 | F16: =E16/SUM($E$7:$E$17) -> 0.089540234 | G16: =IF(ABS(SUM($F$7:$F$17)-1)<0.000001,"OK","CHECK") -> OK | H16: SUM of underlying component indices → total component index; AVERAGE of underlying component indices → equal-weighted broader-category index; contribution = category index ÷ SUM of all broader-category indices. | J16: Spices | K16: 218
A17: Personal Care & Effects | B17: Personal care and effects | C17: 1 | D17: =$K$29 -> 185.2 | E17: =AVERAGE($K$29) -> 185.2 | F17: =E17/SUM($E$7:$E$17) -> 0.093635524 | G17: =IF(ABS(SUM($F$7:$F$17)-1)<0.000001,"OK","CHECK") -> OK | H17: SUM of underlying component indices → total component index; AVERAGE of underlying component indices → equal-weighted broader-category index; contribution = category index ÷ SUM of all broader-category indices. | J17: Non-alcoholic beverages | K17: 173.4
A18: TOTAL | C18: =SUM(C7:C17) -> 23 | D18: =SUM(D7:D17) -> 3796.5 | E18: =SUM(E7:E17) -> 1977.8818 | F18: =SUM(F7:F17) -> 1 | G18: =IF(ABS(F18-1)<0.000001,"PASS — 100%","CHECK") -> PASS — 100% | J18: Prepared meals, snacks, sweets etc. | K18: 194.2
J19: Pan, tobacco and intoxicants | K19: 201
J20: Clothing | K20: 187.3
A21: Q1 Answer | J21: Footwear | K21: 179.7
A22: Highest Contribution | B22: =INDEX(A7:A17,MATCH(MAX(F7:F17),F7:F17,0)) -> Pan, Tobacco & Intoxicants | C22: Contribution | D22: =MAX(F7:F17) -> 0.10162387 | J22: Housing | K22: 175.6
J23: Fuel and light | K23: 182.8
J24: Household goods and services | K24: 175.2
A25: Note | B25: The calculation follows the case-study instruction to use equal weights. Detailed CPI component indices are averaged within each broader category; aggregate columns such as Food and beverages, Clothing and footwear, Miscellaneous, and General index are excluded. | J25: Health | K25: 185.7
J26: Transport and communication | K26: 164.8
J27: Recreation and amusement | K27: 171.2
J28: Education | K28: 177.1
J29: Personal care and effects | K29: 185.2
A32: Excel Function / Calculation Guide
A33: SUM | B33: Adds the underlying CPI component indices within each broader category and totals the category results.
A34: AVERAGE | B34: Calculates the equal-weighted broader-category CPI index from its underlying detailed categories.
A35: SUM + division | B35: Calculates each category's contribution as Category Index ÷ SUM of all broader-category indices.
A36: IF + SUM | B36: Checks whether all contribution percentages add to 100%.

Sheet Q1 Contribution
A1: Q1 — Contribution of Broader Categories
G2: ← Dashboard
A3: Latest Period | B3: May 2023 | D3: Sector | E3: Rural+Urban
A5: Rank | B5: Broader Category | C5: Category Index | D5: Contribution % | E5: Contribution Check | F5: Interpretation
A6: =RANK(D6,$D$6:$D$16,0) -> 7 | B6: Food | C6: ='Q1 Calculation'!E7 -> 175.78182 | D6: ='Q1 Calculation'!F7 -> 0.088873772 | E6: =IF(ABS(SUM($D$6:$D$16)-1)<0.000001,"OK","CHECK") -> OK | F6: =IF(D6=MAX($D$6:$D$16),"Highest contribution","")
A7: =RANK(D7,$D$6:$D$16,0) -> 1 | B7: Pan, Tobacco & Intoxicants | C7: ='Q1 Calculation'!E8 -> 201 | D7: ='Q1 Calculation'!F8 -> 0.10162387 | E7: =IF(ABS(SUM($D$6:$D$16)-1)<0.000001,"OK","CHECK") -> OK | F7: =IF(D7=MAX($D$6:$D$16),"Highest contribution","") -> Highest contribution
A8: =RANK(D8,$D$6:$D$16,0) -> 4 | B8: Clothing & Footwear | C8: ='Q1 Calculation'!E9 -> 183.5 | D8: ='Q1 Calculation'!F9 -> 0.092776018 | E8: =IF(ABS(SUM($D$6:$D$16)-1)<0.000001,"OK","CHECK") -> OK | F8: =IF(D8=MAX($D$6:$D$16),"Highest contribution","")
A9: =RANK(D9,$D$6:$D$16,0) -> 8 | B9: Housing | C9: ='Q1 Calculation'!E10 -> 175.6 | D9: ='Q1 Calculation'!F10 -> 0.088781847 | E9: =IF(ABS(SUM($D$6:$D$16)-1)<0.000001,"OK","CHECK") -> OK | F9: =IF(D9=MAX($D$6:$D$16),"Highest contribution","")
A10: =RANK(D10,$D$6:$D$16,0) -> 5 | B10: Fuel & Light | C10: ='Q1 Calculation'!E11 -> 182.8 | D10: ='Q1 Calculation'!F11 -> 0.092422104 | E10: =IF(ABS(SUM($D$6:$D$16)-1)<0.000001,"OK","CHECK") -> OK | F10: =IF(D10=MAX($D$6:$D$16),"Highest contribution","")
A11: =RANK(D11,$D$6:$D$16,0) -> 9 | B11: Household Goods & Services | C11: ='Q1 Calculation'!E12 -> 175.2 | D11: ='Q1 Calculation'!F12 -> 0.08857961 | E11: =IF(ABS(SUM($D$6:$D$16)-1)<0.000001,"OK","CHECK") -> OK | F11: =IF(D11=MAX($D$6:$D$16),"Highest contribution","")
A12: =RANK(D12,$D$6:$D$16,0) -> 2 | B12: Health | C12: ='Q1 Calculation'!E13 -> 185.7 | D12: ='Q1 Calculation'!F13 -> 0.093888319 | E12: =IF(ABS(SUM($D$6:$D$16)-1)<0.000001,"OK","CHECK") -> OK | F12: =IF(D12=MAX($D$6:$D$16),"Highest contribution","")
A13: =RANK(D13,$D$6:$D$16,0) -> 11 | B13: Transport & Communication | C13: ='Q1 Calculation'!E14 -> 164.8 | D13: ='Q1 Calculation'!F14 -> 0.08332146 | E13: =IF(ABS(SUM($D$6:$D$16)-1)<0.000001,"OK","CHECK") -> OK | F13: =IF(D13=MAX($D$6:$D$16),"Highest contribution","")
A14: =RANK(D14,$D$6:$D$16,0) -> 10 | B14: Recreation & Amusement | C14: ='Q1 Calculation'!E15 -> 171.2 | D14: ='Q1 Calculation'!F15 -> 0.086557244 | E14: =IF(ABS(SUM($D$6:$D$16)-1)<0.000001,"OK","CHECK") -> OK | F14: =IF(D14=MAX($D$6:$D$16),"Highest contribution","")
A15: =RANK(D15,$D$6:$D$16,0) -> 6 | B15: Education | C15: ='Q1 Calculation'!E16 -> 177.1 | D15: ='Q1 Calculation'!F16 -> 0.089540234 | E15: =IF(ABS(SUM($D$6:$D$16)-1)<0.000001,"OK","CHECK") -> OK | F15: =IF(D15=MAX($D$6:$D$16),"Highest contribution","")
A16: =RANK(D16,$D$6:$D$16,0) -> 3 | B16: Personal Care & Effects | C16: ='Q1 Calculation'!E17 -> 185.2 | D16: ='Q1 Calculation'!F17 -> 0.093635524 | E16: =IF(ABS(SUM($D$6:$D$16)-1)<0.000001,"OK","CHECK") -> OK | F16: =IF(D16=MAX($D$6:$D$16),"Highest contribution","")
B17: TOTAL | C17: =SUM(C6:C16) -> 1977.8818 | D17: =SUM(D6:D16) -> 1 | E17: =IF(ABS(D17-1)<0.000001,"PASS — 100%","CHECK") -> PASS — 100%
A20: Key Takeaway
A21: Highest Contributor | B21: =INDEX(B6:B16,MATCH(MAX(D6:D16),D6:D16,0)) -> Pan, Tobacco & Intoxicants | C21: Contribution | D21: =MAX(D6:D16) -> 0.10162387
A24: Function / Method Notes
A25: RANK.EQ | B25: Ranks categories by Contribution % so the largest contribution receives rank 1.
A26: MAX | B26: Finds the highest Contribution % for the key result and highest-contribution flag.
A27: INDEX + MATCH | B27: Returns the category name associated with the maximum Contribution %.
A28: SUM + IF | B28: SUM checks that all contribution percentages equal 100%; IF returns the validation status.

Sheet Q1 Pivot
A1: Q1 — Pivot Table Summary
F2: ← Dashboard
A3: Latest Period | B3: May 2023 | D3: Sector | E3: Rural+Urban
A5: Rank | B5: Broader Category | C5: Category Index | D5: Contribution % | E5: Components Used
A6: =RANK(D6,$D$6:$D$16,0) -> 7 | B6: ='Q1 Calculation'!A7 -> Food | C6: ='Q1 Calculation'!E7 -> 175.78182 | D6: ='Q1 Calculation'!F7 -> 0.088873772 | E6: ='Q1 Calculation'!C7 -> 12
A7: =RANK(D7,$D$6:$D$16,0) -> 1 | B7: ='Q1 Calculation'!A8 -> Pan, Tobacco & Intoxicants | C7: ='Q1 Calculation'!E8 -> 201 | D7: ='Q1 Calculation'!F8 -> 0.10162387 | E7: ='Q1 Calculation'!C8 -> 1
A8: =RANK(D8,$D$6:$D$16,0) -> 4 | B8: ='Q1 Calculation'!A9 -> Clothing & Footwear | C8: ='Q1 Calculation'!E9 -> 183.5 | D8: ='Q1 Calculation'!F9 -> 0.092776018 | E8: ='Q1 Calculation'!C9 -> 2
A9: =RANK(D9,$D$6:$D$16,0) -> 8 | B9: ='Q1 Calculation'!A10 -> Housing | C9: ='Q1 Calculation'!E10 -> 175.6 | D9: ='Q1 Calculation'!F10 -> 0.088781847 | E9: ='Q1 Calculation'!C10 -> 1
A10: =RANK(D10,$D$6:$D$16,0) -> 5 | B10: ='Q1 Calculation'!A11 -> Fuel & Light | C10: ='Q1 Calculation'!E11 -> 182.8 | D10: ='Q1 Calculation'!F11 -> 0.092422104 | E10: ='Q1 Calculation'!C11 -> 1
A11: =RANK(D11,$D$6:$D$16,0) -> 9 | B11: ='Q1 Calculation'!A12 -> Household Goods & Services | C11: ='Q1 Calculation'!E12 -> 175.2 | D11: ='Q1 Calculation'!F12 -> 0.08857961 | E11: ='Q1 Calculation'!C12 -> 1
A12: =RANK(D12,$D$6:$D$16,0) -> 2 | B12: ='Q1 Calculation'!A13 -> Health | C12: ='Q1 Calculation'!E13 -> 185.7 | D12: ='Q1 Calculation'!F13 -> 0.093888319 | E12: ='Q1 Calculation'!C13 -> 1
A13: =RANK(D13,$D$6:$D$16,0) -> 11 | B13: ='Q1 Calculation'!A14 -> Transport & Communication | C13: ='Q1 Calculation'!E14 -> 164.8 | D13: ='Q1 Calculation'!F14 -> 0.08332146 | E13: ='Q1 Calculation'!C14 -> 1
A14: =RANK(D14,$D$6:$D$16,0) -> 10 | B14: ='Q1 Calculation'!A15 -> Recreation & Amusement | C14: ='Q1 Calculation'!E15 -> 171.2 | D14: ='Q1 Calculation'!F15 -> 0.086557244 | E14: ='Q1 Calculation'!C15 -> 1
A15: =RANK(D15,$D$6:$D$16,0) -> 6 | B15: ='Q1 Calculation'!A16 -> Education | C15: ='Q1 Calculation'!E16 -> 177.1 | D15: ='Q1 Calculation'!F16 -> 0.089540234 | E15: ='Q1 Calculation'!C16 -> 1
A16: =RANK(D16,$D$6:$D$16,0) -> 3 | B16: ='Q1 Calculation'!A17 -> Personal Care & Effects | C16: ='Q1 Calculation'!E17 -> 185.2 | D16: ='Q1 Calculation'!F17 -> 0.093635524 | E16: ='Q1 Calculation'!C17 -> 1
B17: TOTAL | C17: =SUM(C6:C16) -> 1977.8818 | D17: =SUM(D6:D16) -> 1 | E17: =SUM(E6:E16) -> 23
A20: Pivot Insight
A21: The pivot summary ranks the broader CPI categories by their calculated contribution for May 2023. The highest contributor is Pan, Tobacco & Intoxicants at 10.15%.
A26: Function / Method Notes
A27: RANK.EQ | B27: Ranks the broader categories by Contribution %.
A28: SUM | B28: Totals Category Index, Contribution %, and Components Used for validation/summary.

Sheet Q1 Visualization
A1: Q1 — CPI Contribution Visualization
G2: ← Dashboard
A3: Broader Category Contribution — May 2023
A5: Broader Category | B5: Contribution %
A6: ='Q1 Contribution'!B6 -> Food | B6: ='Q1 Contribution'!D6 -> 0.088873772
A7: ='Q1 Contribution'!B7 -> Pan, Tobacco & Intoxicants | B7: ='Q1 Contribution'!D7 -> 0.10162387
A8: ='Q1 Contribution'!B8 -> Clothing & Footwear | B8: ='Q1 Contribution'!D8 -> 0.092776018
A9: ='Q1 Contribution'!B9 -> Housing | B9: ='Q1 Contribution'!D9 -> 0.088781847
A10: ='Q1 Contribution'!B10 -> Fuel & Light | B10: ='Q1 Contribution'!D10 -> 0.092422104
A11: ='Q1 Contribution'!B11 -> Household Goods & Services | B11: ='Q1 Contribution'!D11 -> 0.08857961
A12: ='Q1 Contribution'!B12 -> Health | B12: ='Q1 Contribution'!D12 -> 0.093888319
A13: ='Q1 Contribution'!B13 -> Transport & Communication | B13: ='Q1 Contribution'!D13 -> 0.08332146
A14: ='Q1 Contribution'!B14 -> Recreation & Amusement | B14: ='Q1 Contribution'!D14 -> 0.086557244
A15: ='Q1 Contribution'!B15 -> Education | B15: ='Q1 Contribution'!D15 -> 0.089540234
A16: ='Q1 Contribution'!B16 -> Personal Care & Effects | B16: ='Q1 Contribution'!D16 -> 0.093635524
A20: Q1 Insight
A21: Pan, Tobacco & Intoxicants has the largest calculated contribution at 10.15%. Transport & Communication has the smallest at 8.33%. The result reflects the equal-weight methodology used to group detailed CPI categories.
A25: Function / Method Notes
A26: Linked formulas | B26: Visualization source values are linked to Q1 Contribution so the chart updates when the underlying calculation changes.
A27: Bar Chart | B27: Used to compare the contribution percentage across broader CPI categories; a horizontal bar chart is suitable for multiple category labels.

Sheet Q2 Calculation
A1: Q2 — YoY CPI Inflation Calculation
A3: Scope | B3: Rural+Urban — General Index (entire basket) | D3: Trend Start | E3: 2017
A5: Methodology
A6: Annual CPI is the average of monthly General Index values for Rural+Urban. YoY inflation = (current-year average index ÷ previous-year average index − 1) × 100. 2017–2022 are compared as complete calendar years. 2023 is shown separately as YTD Jan–May and is not ranked against full years. Missing monthly General Index observations needed for annual averages were linearly interpolated between adjacent observed months.
A10: Excel Formula Used for Annual Average | B10: =AVERAGEIFS('Q2 Monthly Data'!$D:$D,'Q2 Monthly Data'!$A:$A,A13) -> 129.2
A11: YoY Formula | B11: Current Year Average ÷ Previous Year Average − 1
A12: Year | B12: Period | C12: Months Used | D12: Annual Average CPI | E12: Previous Year Average | F12: YoY Inflation
A13: 2016 | B13: Full year | C13: 12 | D13: =AVERAGEIFS('Q2 Monthly Data'!$D:$D,'Q2 Monthly Data'!$A:$A,A13) -> 129.2
A14: 2017 | B14: Full year | C14: 12 | D14: =AVERAGEIFS('Q2 Monthly Data'!$D:$D,'Q2 Monthly Data'!$A:$A,A14) -> 133.5 | E14: =D13 -> 129.2 | F14: =(D14/E14)-1 -> 0.033281734
A15: 2018 | B15: Full year | C15: 12 | D15: =AVERAGEIFS('Q2 Monthly Data'!$D:$D,'Q2 Monthly Data'!$A:$A,A15) -> 138.775 | E15: =D14 -> 133.5 | F15: =(D15/E15)-1 -> 0.039513109
A16: 2019 | B16: Full year | C16: 12 | D16: =AVERAGEIFS('Q2 Monthly Data'!$D:$D,'Q2 Monthly Data'!$A:$A,A16) -> 143.93333 | E16: =D15 -> 138.775 | F16: =(D16/E16)-1 -> 0.03717048
A17: 2020 | B17: Full year | C17: 12 | D17: =AVERAGEIFS('Q2 Monthly Data'!$D:$D,'Q2 Monthly Data'!$A:$A,A17) -> 152.85 | E17: =D16 -> 143.93333 | F17: =(D17/E17)-1 -> 0.061949977
A18: 2021 | B18: Full year | C18: 12 | D18: =AVERAGEIFS('Q2 Monthly Data'!$D:$D,'Q2 Monthly Data'!$A:$A,A18) -> 161.45833 | E18: =D17 -> 152.85 | F18: =(D18/E18)-1 -> 0.056318831
A19: 2022 | B19: Full year | C19: 12 | D19: =AVERAGEIFS('Q2 Monthly Data'!$D:$D,'Q2 Monthly Data'!$A:$A,A19) -> 172.15 | E19: =D18 -> 161.45833 | F19: =(D19/E19)-1 -> 0.066219355
A20: 2023 | B20: YTD Jan-May | C20: 5 | D20: =AVERAGEIFS('Q2 Monthly Data'!$D:$D,'Q2 Monthly Data'!$A:$A,A20) -> 177.62 | E20: =D19 -> 172.15 | F20: =(D20/E20)-1 -> 0.031774615
A23: Highest Full-Year Inflation Year | B23: =INDEX(A14:A19,MATCH(MAX(F14:F19),F14:F19,0)) -> 2022 | C23: Highest YoY Inflation | D23: =MAX(F14:F19) -> 0.066219355
A24: Function / Method Notes
A25: AVERAGEIFS | B25: Averages the monthly Rural+Urban General Index values for each year using the Year criterion.
A26: YoY formula | B26: Calculates year-over-year inflation as (Current Year Average ÷ Previous Year Average) − 1.
A27: Linear interpolation | B27: Used only to estimate missing monthly General Index values needed for an annual average; estimated months are flagged in the monthly-data sheet.
A28: MAX | B28: Used to identify the highest full-year YoY inflation rate.
A30: Key-result formulas
A31: INDEX + MATCH + MAX | B31: Identifies the year with the highest full-year YoY inflation; MAX finds the highest rate and INDEX+MATCH returns its year.

Sheet Q2 Monthly Data
A1: Year | B1: Month | C1: Observed General Index | D1: General Index for Q2
A2: 2013 | B2: January | C2: 104.6 | D2: 104.6 | E2: ← Dashboard
A3: 2013 | B3: February | C3: 105.3 | D3: 105.3
A4: 2013 | B4: March | C4: 105.5 | D4: 105.5
A5: 2013 | B5: April | C5: 106.1 | D5: 106.1
A6: 2013 | B6: May | C6: 106.9 | D6: 106.9
A7: 2013 | B7: June | C7: 109.3 | D7: 109.3
A8: 2013 | B8: July | C8: 111 | D8: 111
A9: 2013 | B9: August | C9: 112.4 | D9: 112.4
A10: 2013 | B10: September | C10: 113.7 | D10: 113.7
A11: 2013 | B11: October | C11: 114.8 | D11: 114.8
A12: 2013 | B12: November | C12: 116.3 | D12: 116.3
A13: 2013 | B13: December | C13: 114.5 | D13: 114.5
A14: 2014 | B14: January | C14: 113.6 | D14: 113.6
... A76: 2019 | B76: March | C76: 140.4 | D76: 140.4
A77: 2019 | B77: April | D77: 141.2
A78: 2019 | B78: May | C78: 142 | D78: 142
A79: 2019 | B79: June | C79: 142.9 | D79: 142.9
A80: 2019 | B80: July | C80: 144.2 | D80: 144.2
A81: 2019 | B81: August | C81: 145 | D81: 145
A82: 2019 | B82: September | C82: 145.8 | D82: 145.8
A83: 2019 | B83: October | C83: 147.2 | D83: 147.2
A84: 2019 | B84: November | C84: 148.6 | D84: 148.6
A85: 2019 | B85: December | C85: 150.4 | D85: 150.4
A86: 2020 | B86: January | C86: 150.2 | D86: 150.2
A87: 2020 | B87: February | C87: 149.1 | D87: 149.1
A88: 2020 | B88: March | C88: 148.6 | D88: 148.6
A89: 2020 | B89: April | D89: 149.66667
A90: 2020 | B90: May | D90: 150.73333
A91: 2020 | B91: June | C91: 151.8 | D91: 151.8
A92: 2020 | B92: July | C92: 151.8 | D92: 151.8
A93: 2020 | B93: August | C93: 153.9 | D93: 153.9
A94: 2020 | B94: September | C94: 154.7 | D94: 154.7
A95: 2020 | B95: October | C95: 156.4 | D95: 156.4
A96: 2020 | B96: November | C96: 158.4 | D96: 158.4
A97: 2020 | B97: December | C97: 158.9 | D97: 158.9
A98: 2021 | B98: January | C98: 157.3 | D98: 157.3
A99: 2021 | B99: February | C99: 156.6 | D99: 156.6
A100: 2021 | B100: March | C100: 156.8 | D100: 156.8
A101: 2021 | B101: April | C101: 157.8 | D101: 157.8
A102: 2021 | B102: May | C102: 160.4 | D102: 160.4
... A126: 2023 | B126: May | C126: 179.1 | D126: 179.1
A128: Data note | B128: Missing monthly General Index observations used in Q2 annual averages were linearly interpolated between adjacent observed months. This is documented here for transparency.
A129: Data Transformation Notes
A130: Text cleaning | B130: Month and Sector labels were standardized by trimming whitespace and correcting the source typo 'Marcrh' to 'March'.
A131: Numeric conversion | B131: CPI fields were converted to numeric values; '-' is treated as missing rather than as zero.
A132: Missing-value treatment | B132: Missing General Index observations used for Q2 annual averages were estimated by linear interpolation between adjacent observed months.

Sheet Q2 Visualization
A1: Q2 — YoY CPI Inflation Trend
G2: ← Dashboard
A3: Trend | B3: 2017–2022 full-year comparison | D3: Highest Year | E3: ='Q2 Calculation'!B23 -> 2022 | F3: ='Q2 Calculation'!D23 -> 0.066219355
A5: Year | B5: YoY Inflation %
A6: ='Q2 Calculation'!A13 -> 2016 | B6: ='Q2 Calculation'!F13 -> 0
A7: ='Q2 Calculation'!A14 -> 2017 | B7: ='Q2 Calculation'!F14 -> 0.033281734
A8: ='Q2 Calculation'!A15 -> 2018 | B8: ='Q2 Calculation'!F15 -> 0.039513109
A9: ='Q2 Calculation'!A16 -> 2019 | B9: ='Q2 Calculation'!F16 -> 0.03717048
A10: ='Q2 Calculation'!A17 -> 2020 | B10: ='Q2 Calculation'!F17 -> 0.061949977
A11: ='Q2 Calculation'!A18 -> 2021 | B11: ='Q2 Calculation'!F18 -> 0.056318831
A14: Highest Inflation Year | B14: 2022 | C14: 0.066219355
A16: Q2 Insight — Why 2022 Stands Out
A17: 2022 records the highest full-year YoY CPI inflation in this analysis at 6.62%. The increase was driven by global commodity shocks, post-COVID supply constraints, food and energy pressures, adverse weather, and broader pass-through into core prices.
A24: Function / Method Notes
A25: AVERAGEIFS | B25: Annual average General Index is calculated in Q2 Calculation using AVERAGEIFS on the monthly cleaned data.
A26: YoY formula | B26: The trend uses the year-over-year percentage change between consecutive annual averages.

Sheet Q2 Research
A1: Q2 — Research: Why Inflation Was Highest in 2022
F2: ← Dashboard
A3: Finding | B3: 2022 had the highest full-year YoY CPI increase: 6.62%.
A5: Driver | B5: Evidence / Interpretation | C5: Source | D5: Source Link | E5: Interview-ready takeaway
A6: Russia–Ukraine war & global commodity prices | B6: RBI reports that the war exacerbated post-COVID supply constraints and caused global shortages in key food, energy and other commodities. | C6: RBI Annual Report 2022-23 | D6: https://www.rbi.org.in/scripts/AnnualReportPublications.aspx?Id=1373 | E6: The war amplified imported cost pressures, especially in food and energy.
A7: Food-price pressures | B7: RBI links higher food prices to global food-price shocks, supply shortages and adverse domestic weather; cereals, vegetables, milk and spices were important drivers. | C7: RBI Annual Report 2022-23 | D7: https://www.rbi.org.in/scripts/AnnualReportPublications.aspx?Id=1373 | E7: Food inflation was a major contributor to headline CPI.
A8: Fuel and energy prices | B8: RBI reports fuel and light inflation averaging 10.3% in 2022-23, reflecting higher kerosene and LPG prices after the rise in global energy prices. | C8: RBI Annual Report 2022-23 | D8: https://www.rbi.org.in/scripts/AnnualReportPublications.aspx?Id=1373 | E8: Higher energy costs affected household prices and production costs.
A9: Domestic weather / supply disruption | B9: The Economic Survey states that excessive summer heat and uneven rainfall affected farm output, reducing supply and raising prices of some products. | C9: Economic Survey 2022-23 | D9: https://www.indiabudget.gov.in/budget2023-24/economicsurvey/doc/echapter.pdf | E9: Weather-related supply shocks added to food-price pressure.
A10: Pass-through to core inflation | B10: RBI reports elevated core inflation as higher input costs passed through to goods and services, alongside recovering domestic demand. | C10: RBI Annual Report 2022-23 | D10: https://www.rbi.org.in/scripts/AnnualReportPublications.aspx?Id=1373 | E10: The inflation shock broadened beyond food and fuel into core categories.
A13: Overall explanation
A14: 2022 recorded the highest full-year YoY CPI increase in this dataset-based analysis. The evidence points to a largely supply-side and imported-inflation shock: the Russia–Ukraine conflict intensified global food and energy price pressures while post-pandemic supply constraints persisted. Domestic weather disruptions added to food price pressure, and higher input costs gradually passed through to core goods and services.
A20: Source note | B20: Research is based on official RBI and Government of India publications.

Sheet Q3 Calculation
A1: Q3 — Food Inflation Analysis (12 Months Ending May 2023)
R2: ← Dashboard
A3: Analysis Period | B3: June 2022 – May 2023 | D3: Sector | E3: Rural+Urban | G3: Food Index | H3: Equal-weighted AVERAGE
A5: Methodology
A6: After finding out food inflation is being the reason of affecting yoy inflation we tried to find out mom trend in the food inflation for overall food bucket and also the absolute change in the individual food categories plus which food category contributing most to the mom inflation for the 12 month period ending on may 2023,for that we use avg function to get avg of all individual food categories for that month and then to find monthly change we use formula current mmonth food index/previous month-1
A11: Year | B11: Month | C11: Cereals and products | D11: Meat and fish | E11: Egg | F11: Milk and products | G11: Oils and fats | H11: Fruits | I11: Vegetables | J11: Pulses and products | K11: Sugar and Confectionery | L11: Spices | M11: Non-alcoholic beverages | N11: Prepared meals, snacks, sweets etc. | O11: Avg Food Index | P11: Previous Month Food Index | Q11: MoM Food Inflation %
A12: 2022 | B12: May | C12: 154.1 | D12: 217 | E12: 162.4 | F12: 164.9 | G12: 202.4 | H12: 171 | I12: 174.9 | J12: 164.7 | K12: 119.7 | L12: 184.9 | M12: 167.1 | N12: 182.5 | O12: =AVERAGE(C12:N12) -> 172.13333
A13: 2022 | B13: June | C13: 155 | D13: 219.4 | E13: 170.8 | F13: 165.8 | G13: 200.9 | H13: 169.7 | I13: 182.3 | J13: 164.3 | K13: 119.9 | L13: 187.1 | M13: 167.9 | N13: 183.9 | O13: =AVERAGE(C13:N13) -> 173.91667 | P13: =O12 -> 172.13333 | Q13: =O13/P13-1 -> 0.010360186
A14: 2022 | B14: July | C14: 156.5 | D14: 213 | E14: 175.2 | F14: 166.6 | G14: 195.8 | H14: 174.2 | I14: 182.1 | J14: 164.3 | K14: 120 | L14: 190 | M14: 168.4 | N14: 185.2 | O14: =AVERAGE(C14:N14) -> 174.275 | P14: =O13 -> 173.91667 | Q14: =O14/P14-1 -> 0.0020603737
A15: 2022 | B15: August | C15: 160.3 | D15: 206.5 | E15: 169.2 | F15: 168.1 | G15: 192.4 | H15: 172.9 | I15: 186.7 | J15: 167.2 | K15: 120.9 | L15: 193.6 | M15: 168.8 | N15: 186.3 | O15: =AVERAGE(C15:N15) -> 174.40833 | P15: =O14 -> 174.275 | Q15: =O15/P15-1 -> 0.00076507436
A16: 2022 | B16: September | C16: 163.5 | D16: 209.2 | E16: 169.7 | F16: 169.7 | G16: 188.7 | H16: 165.7 | I16: 191.8 | J16: 169.1 | K16: 121.6 | L16: 197.3 | M16: 169.4 | N16: 187.4 | O16: =AVERAGE(C16:N16) -> 175.25833 | P16: =O15 -> 174.40833 | Q16: =O16/P16-1 -> 0.0048736203
A17: 2022 | B17: October | C17: 165.2 | D17: 210.9 | E17: 170.9 | F17: 170.9 | G17: 186.5 | H17: 163.8 | I17: 199.7 | J17: 169.8 | K17: 121.9 | L17: 199.9 | M17: 169.9 | N17: 188.3 | O17: =AVERAGE(C17:N17) -> 176.475 | P17: =O16 -> 175.25833 | Q17: =O17/P17-1 -> 0.006942133
A18: 2022 | B18: November | C18: 167.4 | D18: 209.4 | E18: 181.4 | F18: 172.3 | G18: 188.9 | H18: 160.7 | I18: 183.1 | J18: 170.5 | K18: 122.1 | L18: 202.8 | M18: 170.4 | N18: 189.5 | O18: =AVERAGE(C18:N18) -> 176.54167 | P18: =O17 -> 176.475 | Q18: =O18/P18-1 -> 0.00037776833
A19: 2022 | B19: December | C19: 169.2 | D19: 209 | E19: 190.2 | F19: 173.6 | G19: 188.5 | H19: 158 | I19: 159.9 | J19: 170.8 | K19: 121.8 | L19: 205.2 | M19: 171 | N19: 190.3 | O19: =AVERAGE(C19:N19) -> 175.625 | P19: =O18 -> 176.54167 | Q19: =O19/P19-1 -> -0.0051923531
A20: 2023 | B20: January | C20: 173.8 | D20: 210.7 | E20: 194.5 | F20: 174.6 | G20: 187.2 | H20: 158.3 | I20: 153.9 | J20: 170.9 | K20: 121.1 | L20: 208.4 | M20: 171.4 | N20: 191.2 | O20: =AVERAGE(C20:N20) -> 176.33333 | P20: =O19 -> 175.625 | Q20: =O20/P20-1 -> 0.0040332147
A21: 2023 | B21: February | C21: 174.4 | D21: 207.7 | E21: 175.2 | F21: 177.3 | G21: 179.3 | H21: 169.5 | I21: 152.7 | J21: 171 | K21: 120 | L21: 209.7 | M21: 172.3 | N21: 193 | O21: =AVERAGE(C21:N21) -> 175.175 | P21: =O20 -> 176.33333 | Q21: =O21/P21-1 -> -0.0065689981
A22: 2023 | B22: March | C22: 174.4 | D22: 207.7 | E22: 175.2 | F22: 177.3 | G22: 179.2 | H22: 169.5 | I22: 152.8 | J22: 171.1 | K22: 120 | L22: 209.7 | M22: 172.3 | N22: 193 | O22: =AVERAGE(C22:N22) -> 175.18333 | P22: =O21 -> 175.175 | Q22: =O22/P22-1 -> 4.7571476e-05
A23: 2023 | B23: April | C23: 173.8 | D23: 209.3 | E23: 169.6 | F23: 178.4 | G23: 174.9 | H23: 176.3 | I23: 155.4 | J23: 173.4 | K23: 121.3 | L23: 212.9 | M23: 172.9 | N23: 193.5 | O23: =AVERAGE(C23:N23) -> 175.975 | P23: =O22 -> 175.18333 | Q23: =O23/P23-1 -> 0.0045190753
A24: 2023 | B24: May | C24: 173.7 | D24: 214.3 | E24: 173.2 | F24: 179.5 | G24: 170 | H24: 172.2 | I24: 161 | J24: 175.6 | K24: 122.7 | L24: 218 | M24: 173.4 | N24: 194.2 | O24: =AVERAGE(C24:N24) -> 177.31667 | P24: =O23 -> 175.975 | Q24: =O24/P24-1 -> 0.007624189
A27: 12-Month Summary
A28: Metric | B28: Value | C28: Function / Method Used
A29: Highest MoM Food Inflation | B29: =MAX(Q13:Q24) -> 0.010360186 | C29: MAX
A30: Highest Inflation Month | B30: =INDEX(B13:B24,MATCH(MAX(Q13:Q24),Q13:Q24,0)) -> June | C30: INDEX + MATCH + MAX
A31: Lowest MoM Food Inflation | B31: =MIN(Q13:Q24) -> -0.0065689981 | C31: MIN
A32: Lowest Inflation Month | B32: =INDEX(B13:B24,MATCH(MIN(Q13:Q24),Q13:Q24,0)) -> February | C32: INDEX + MATCH + MIN
A33: May 2022 Food Index | B33: =O12 -> 172.13333 | C33: Direct reference
A34: May 2023 Food Index | B34: =O24 -> 177.31667 | C34: Direct reference
A35: Absolute Food Index Change | B35: =B34-B33 -> 5.1833333 | C35: Subtraction
A36: Food Index % Change | B36: =B34/B33-1 -> 0.030112316 | C36: Percentage-change formula
A39: Individual Food Category Change — May 2022 to May 2023 | B39: and to find absolute change we subtrated may 2023 individual food category index with may 2022 index value and to find change inn the percentage we used may2023/may2022-1
A40: Food Category | B40: May 2022 Index | C40: May 2023 Index | D40: Absolute Change | E40: % Change | F40: Contribution to Positive Food Change %
A41: Cereals and products | B41: =C12 -> 154.1 | C41: =C24 -> 173.7 | D41: =C41-B41 -> 19.6 | E41: =C41/B41-1 -> 0.12719014 | F41: =IF(D41>0,D41/SUMIF($D$41:$D$52,">0",$D$41:$D$52),0) -> 0.17625899
A42: Meat and fish | B42: =D12 -> 217 | C42: =D24 -> 214.3 | D42: =C42-B42 -> -2.7 | E42: =C42/B42-1 -> -0.012442396 | F42: =IF(D42>0,D42/SUMIF($D$41:$D$52,">0",$D$41:$D$52),0) -> 0
A43: Egg | B43: =E12 -> 162.4 | C43: =E24 -> 173.2 | D43: =C43-B43 -> 10.8 | E43: =C43/B43-1 -> 0.066502463 | F43: =IF(D43>0,D43/SUMIF($D$41:$D$52,">0",$D$41:$D$52),0) -> 0.097122302
A44: Milk and products | B44: =F12 -> 164.9 | C44: =F24 -> 179.5 | D44: =C44-B44 -> 14.6 | E44: =C44/B44-1 -> 0.088538508 | F44: =IF(D44>0,D44/SUMIF($D$41:$D$52,">0",$D$41:$D$52),0) -> 0.13129496
A45: Oils and fats | B45: =G12 -> 202.4 | C45: =G24 -> 170 | D45: =C45-B45 -> -32.4 | E45: =C45/B45-1 -> -0.16007905 | F45: =IF(D45>0,D45/SUMIF($D$41:$D$52,">0",$D$41:$D$52),0) -> 0
A46: Fruits | B46: =H12 -> 171 | C46: =H24 -> 172.2 | D46: =C46-B46 -> 1.2 | E46: =C46/B46-1 -> 0.0070175439 | F46: =IF(D46>0,D46/SUMIF($D$41:$D$52,">0",$D$41:$D$52),0) -> 0.010791367
A47: Vegetables | B47: =I12 -> 174.9 | C47: =I24 -> 161 | D47: =C47-B47 -> -13.9 | E47: =C47/B47-1 -> -0.079473985 | F47: =IF(D47>0,D47/SUMIF($D$41:$D$52,">0",$D$41:$D$52),0) -> 0
A48: Pulses and products | B48: =J12 -> 164.7 | C48: =J24 -> 175.6 | D48: =C48-B48 -> 10.9 | E48: =C48/B48-1 -> 0.066180935 | F48: =IF(D48>0,D48/SUMIF($D$41:$D$52,">0",$D$41:$D$52),0) -> 0.098021583
A49: Sugar and Confectionery | B49: =K12 -> 119.7 | C49: =K24 -> 122.7 | D49: =C49-B49 -> 3 | E49: =C49/B49-1 -> 0.025062657 | F49: =IF(D49>0,D49/SUMIF($D$41:$D$52,">0",$D$41:$D$52),0) -> 0.026978417
A50: Spices | B50: =L12 -> 184.9 | C50: =L24 -> 218 | D50: =C50-B50 -> 33.1 | E50: =C50/B50-1 -> 0.17901568 | F50: =IF(D50>0,D50/SUMIF($D$41:$D$52,">0",$D$41:$D$52),0) -> 0.29766187
A51: Non-alcoholic beverages | B51: =M12 -> 167.1 | C51: =M24 -> 173.4 | D51: =C51-B51 -> 6.3 | E51: =C51/B51-1 -> 0.037701975 | F51: =IF(D51>0,D51/SUMIF($D$41:$D$52,">0",$D$41:$D$52),0) -> 0.056654676
A52: Prepared meals, snacks, sweets etc. | B52: =N12 -> 182.5 | C52: =N24 -> 194.2 | D52: =C52-B52 -> 11.7 | E52: =C52/B52-1 -> 0.064109589 | F52: =IF(D52>0,D52/SUMIF($D$41:$D$52,">0",$D$41:$D$52),0) -> 0.10521583
A53: Biggest Individual Food Contributor | B53: =INDEX(A41:A52,MATCH(MAX(D41:D52),D41:D52,0)) -> Spices | C53: Absolute Change | D53: =MAX(D41:D52) -> 33.1 | E53: MAX + INDEX + MATCH
A56: Function / Method Notes
A57: AVERAGE | B57: Equal-weighted Food Index from detailed Food categories.
A58: COUNT | B58: Counts numeric Food components used in each monthly Food Index.
A59: MAX | B59: Finds highest MoM Food inflation and largest individual Food-category absolute change.
A60: MIN | B60: Finds lowest MoM Food inflation.
A61: INDEX + MATCH | B61: Returns the month/category associated with the MAX or MIN result.
A62: SUMIF | B62: Sums positive individual Food-category changes for contribution-to-positive-change percentages.
A63: Subtraction | B63: Calculates absolute May-23 minus May-22 Food index change.
A64: Percentage change | B64: Calculates MoM Food inflation and 12-month Food index percentage change.

Sheet Q3 Pivot
A1: Q3 — Food Inflation Pivot Summary
G2: ← Dashboard
A3: Period | B3: June 2022 – May 2023 | D3: Sector | E3: Rural+Urban
A5: Year | B5: Month | C5: Food Index | D5: MoM Food Inflation % | E5: Components Used | F5: Type
A6: ='Q3 Calculation'!A13 -> 2022 | B6: ='Q3 Calculation'!B13 -> June | C6: ='Q3 Calculation'!O13 -> 173.91667 | D6: ='Q3 Calculation'!Q13 -> 0.010360186 | E6: ='Q3 Calculation'!#REF! -> #REF! | F6: Analysis month
A7: ='Q3 Calculation'!A14 -> 2022 | B7: ='Q3 Calculation'!B14 -> July | C7: ='Q3 Calculation'!O14 -> 174.275 | D7: ='Q3 Calculation'!Q14 -> 0.0020603737 | E7: ='Q3 Calculation'!#REF! -> #REF! | F7: Analysis month
A8: ='Q3 Calculation'!A15 -> 2022 | B8: ='Q3 Calculation'!B15 -> August | C8: ='Q3 Calculation'!O15 -> 174.40833 | D8: ='Q3 Calculation'!Q15 -> 0.00076507436 | E8: ='Q3 Calculation'!#REF! -> #REF! | F8: Analysis month
A9: ='Q3 Calculation'!A16 -> 2022 | B9: ='Q3 Calculation'!B16 -> September | C9: ='Q3 Calculation'!O16 -> 175.25833 | D9: ='Q3 Calculation'!Q16 -> 0.0048736203 | E9: ='Q3 Calculation'!#REF! -> #REF! | F9: Analysis month
A10: ='Q3 Calculation'!A17 -> 2022 | B10: ='Q3 Calculation'!B17 -> October | C10: ='Q3 Calculation'!O17 -> 176.475 | D10: ='Q3 Calculation'!Q17 -> 0.006942133 | E10: ='Q3 Calculation'!#REF! -> #REF! | F10: Analysis month
A11: ='Q3 Calculation'!A18 -> 2022 | B11: ='Q3 Calculation'!B18 -> November | C11: ='Q3 Calculation'!O18 -> 176.54167 | D11: ='Q3 Calculation'!Q18 -> 0.00037776833 | E11: ='Q3 Calculation'!#REF! -> #REF! | F11: Analysis month
A12: ='Q3 Calculation'!A19 -> 2022 | B12: ='Q3 Calculation'!B19 -> December | C12: ='Q3 Calculation'!O19 -> 175.625 | D12: ='Q3 Calculation'!Q19 -> -0.0051923531 | E12: ='Q3 Calculation'!#REF! -> #REF! | F12: Analysis month
A13: ='Q3 Calculation'!A20 -> 2023 | B13: ='Q3 Calculation'!B20 -> January | C13: ='Q3 Calculation'!O20 -> 176.33333 | D13: ='Q3 Calculation'!Q20 -> 0.0040332147 | E13: ='Q3 Calculation'!#REF! -> #REF! | F13: Analysis month
A14: ='Q3 Calculation'!A21 -> 2023 | B14: ='Q3 Calculation'!B21 -> February | C14: ='Q3 Calculation'!O21 -> 175.175 | D14: ='Q3 Calculation'!Q21 -> -0.0065689981 | E14: ='Q3 Calculation'!#REF! -> #REF! | F14: Analysis month
A15: ='Q3 Calculation'!A22 -> 2023 | B15: ='Q3 Calculation'!B22 -> March | C15: ='Q3 Calculation'!O22 -> 175.18333 | D15: ='Q3 Calculation'!Q22 -> 4.7571476e-05 | E15: ='Q3 Calculation'!#REF! -> #REF! | F15: Analysis month
A16: ='Q3 Calculation'!A23 -> 2023 | B16: ='Q3 Calculation'!B23 -> April | C16: ='Q3 Calculation'!O23 -> 175.975 | D16: ='Q3 Calculation'!Q23 -> 0.0045190753 | E16: ='Q3 Calculation'!#REF! -> #REF! | F16: Analysis month
A17: ='Q3 Calculation'!A24 -> 2023 | B17: ='Q3 Calculation'!B24 -> May | C17: ='Q3 Calculation'!O24 -> 177.31667 | D17: ='Q3 Calculation'!Q24 -> 0.007624189 | E17: ='Q3 Calculation'!#REF! -> #REF! | F17: Analysis month
A20: Function / Method Notes
A21: AVERAGE | B21: The Food Index in Q3 Calculation uses AVERAGE across detailed Food categories.
A22: Linked formulas | B22: This pivot-style summary links to Q3 Calculation rather than hard-coding results.

Sheet Q3 Visualization
A1: Q3 — Food Inflation Visualization
I2: ← Dashboard
A3: Analysis Period | B3: June 2022 – May 2023 | D3: Highest MoM Month | E3: ='Q3 Calculation'!B30 -> June | F3: Highest Rate | G3: ='Q3 Calculation'!B29 -> 0.010360186
A5: Month | B5: Food Index | C5: MoM Food Inflation %
A6: ='Q3 Pivot'!B6 -> June | B6: ='Q3 Pivot'!C6 -> 173.91667 | C6: ='Q3 Pivot'!D6 -> 0.010360186
A7: ='Q3 Pivot'!B7 -> July | B7: ='Q3 Pivot'!C7 -> 174.275 | C7: ='Q3 Pivot'!D7 -> 0.0020603737
A8: ='Q3 Pivot'!B8 -> August | B8: ='Q3 Pivot'!C8 -> 174.40833 | C8: ='Q3 Pivot'!D8 -> 0.00076507436
A9: ='Q3 Pivot'!B9 -> September | B9: ='Q3 Pivot'!C9 -> 175.25833 | C9: ='Q3 Pivot'!D9 -> 0.0048736203
A10: ='Q3 Pivot'!B10 -> October | B10: ='Q3 Pivot'!C10 -> 176.475 | C10: ='Q3 Pivot'!D10 -> 0.006942133
A11: ='Q3 Pivot'!B11 -> November | B11: ='Q3 Pivot'!C11 -> 176.54167 | C11: ='Q3 Pivot'!D11 -> 0.00037776833
A12: ='Q3 Pivot'!B12 -> December | B12: ='Q3 Pivot'!C12 -> 175.625 | C12: ='Q3 Pivot'!D12 -> -0.0051923531
A13: ='Q3 Pivot'!B13 -> January | B13: ='Q3 Pivot'!C13 -> 176.33333 | C13: ='Q3 Pivot'!D13 -> 0.0040332147
A14: ='Q3 Pivot'!B14 -> February | B14: ='Q3 Pivot'!C14 -> 175.175 | C14: ='Q3 Pivot'!D14 -> -0.0065689981
A15: ='Q3 Pivot'!B15 -> March | B15: ='Q3 Pivot'!C15 -> 175.18333 | C15: ='Q3 Pivot'!D15 -> 4.7571476e-05
A16: ='Q3 Pivot'!B16 -> April | B16: ='Q3 Pivot'!C16 -> 175.975 | C16: ='Q3 Pivot'!D16 -> 0.0045190753
A17: ='Q3 Pivot'!B17 -> May | B17: ='Q3 Pivot'!C17 -> 177.31667 | C17: ='Q3 Pivot'!D17 -> 0.007624189
A18: lowest | B18: =_xlfn.XLOOKUP(MIN(C6:C17),C6:C17,A6:A17,0) -> February
A21: Individual Food Category Change
A22: Food Category | B22: Absolute Change | C22: % Change | D22: Contribution to Positive Food Change %
A23: ='Q3 Calculation'!A41 -> Cereals and products | B23: ='Q3 Calculation'!D41 -> 19.6 | C23: ='Q3 Calculation'!E41 -> 0.12719014 | D23: ='Q3 Calculation'!F41 -> 0.17625899
A24: ='Q3 Calculation'!A42 -> Meat and fish | B24: ='Q3 Calculation'!D42 -> -2.7 | C24: ='Q3 Calculation'!E42 -> -0.012442396 | D24: ='Q3 Calculation'!F42 -> 0
A25: ='Q3 Calculation'!A43 -> Egg | B25: ='Q3 Calculation'!D43 -> 10.8 | C25: ='Q3 Calculation'!E43 -> 0.066502463 | D25: ='Q3 Calculation'!F43 -> 0.097122302
A26: ='Q3 Calculation'!A44 -> Milk and products | B26: ='Q3 Calculation'!D44 -> 14.6 | C26: ='Q3 Calculation'!E44 -> 0.088538508 | D26: ='Q3 Calculation'!F44 -> 0.13129496
A27: ='Q3 Calculation'!A45 -> Oils and fats | B27: ='Q3 Calculation'!D45 -> -32.4 | C27: ='Q3 Calculation'!E45 -> -0.16007905 | D27: ='Q3 Calculation'!F45 -> 0
A28: ='Q3 Calculation'!A46 -> Fruits | B28: ='Q3 Calculation'!D46 -> 1.2 | C28: ='Q3 Calculation'!E46 -> 0.0070175439 | D28: ='Q3 Calculation'!F46 -> 0.010791367
A29: ='Q3 Calculation'!A47 -> Vegetables | B29: ='Q3 Calculation'!D47 -> -13.9 | C29: ='Q3 Calculation'!E47 -> -0.079473985 | D29: ='Q3 Calculation'!F47 -> 0
A30: ='Q3 Calculation'!A48 -> Pulses and products | B30: ='Q3 Calculation'!D48 -> 10.9 | C30: ='Q3 Calculation'!E48 -> 0.066180935 | D30: ='Q3 Calculation'!F48 -> 0.098021583
A31: ='Q3 Calculation'!A49 -> Sugar and Confectionery | B31: ='Q3 Calculation'!D49 -> 3 | C31: ='Q3 Calculation'!E49 -> 0.025062657 | D31: ='Q3 Calculation'!F49 -> 0.026978417
A32: ='Q3 Calculation'!A50 -> Spices | B32: ='Q3 Calculation'!D50 -> 33.1 | C32: ='Q3 Calculation'!E50 -> 0.17901568 | D32: ='Q3 Calculation'!F50 -> 0.29766187
A33: ='Q3 Calculation'!A51 -> Non-alcoholic beverages | B33: ='Q3 Calculation'!D51 -> 6.3 | C33: ='Q3 Calculation'!E51 -> 0.037701975 | D33: ='Q3 Calculation'!F51 -> 0.056654676
A34: ='Q3 Calculation'!A52 -> Prepared meals, snacks, sweets etc. | B34: ='Q3 Calculation'!D52 -> 11.7 | C34: ='Q3 Calculation'!E52 -> 0.064109589 | D34: ='Q3 Calculation'!F52 -> 0.10521583
A38: Q3 Key Insight
A39: Food inflation was volatile over the 12 months ending May 2023. The highest monthly Food inflation was 1.04% in June 2022, while the lowest was -0.66% in February 2023. The Food Index increased 5.18 points, or 3.01%, from May 2022 to May 2023. Spices recorded the largest individual increase.
A42: 12-Month % Change | B42: ='Q3 Calculation'!B36 -> 0.030112316
A43: Biggest Food Category Contributor | B43: ='Q3 Calculation'!B53 -> Spices | C43: ='Q3 Calculation'!D53 -> 33.1
A45: Function / Method Notes
A46: AVERAGE | B46: Equal-weighted Food Index from detailed Food categories.
A47: COUNT | B47: Counts numeric Food components used in each monthly Food Index.
A48: MAX | B48: Finds highest MoM Food inflation and largest individual Food-category absolute change.
A49: MIN | B49: Finds lowest MoM Food inflation.
A50: INDEX + MATCH | B50: Returns the month/category associated with the MAX or MIN result.
A51: SUMIF | B51: Sums positive individual Food-category changes for contribution-to-positive-change percentages.
A52: Subtraction | B52: Calculates absolute May-23 minus May-22 Food index change.
A53: Percentage change | B53: Calculates MoM Food inflation and 12-month Food index percentage change.

Sheet Q4 Calculation
A1: Q4 — COVID-19 Impact on CPI Inflation in India | P1: Pre vs Post COVID Inflation Summary
A2: Scope | B2: Rural+Urban | D2: Reference milestone | E2: March 2020 | G2: Method | H2: Monthly YoY inflation; 12-month pre vs 12-month post comparison | V2: ← Dashboard
P3: Category | Q3: Category | R3: Pre-COVID Avg YoY | S3: Post-onset Avg YoY | T3: Change (pp) | U3: Interpretation
A4: Methodology | B4: Monthly YoY inflation = Current month CPI ÷ same month previous year CPI − 1. Pre-COVID comparison window: Apr-2019 to Mar-2020. Post-onset window: Apr-2020 to Mar-2021. Essential Services is an equal-weighted AVERAGE of Fuel & Light, Household Goods & Services, and Transport & Communication. Missing source observations needed for comparison are linearly interpolated and flagged. | P4: General CPI | Q4: =AVERAGE(J21:J32) -> 0.047566777 | R4: =AVERAGE(J33:J44) -> 0.058049244 | S4: =R4-Q4 -> 0.010482467 | T4: =IF(S4>0,"Headline inflation increased","Headline inflation decreased") -> Headline inflation increased
P5: Food | Q5: =AVERAGE(K21:K32) -> 0.060680421 | R5: =AVERAGE(K33:K44) -> 0.069071211 | S5: =R5-Q5 -> 0.0083907903 | T5: =IF(S5>0,"Food inflation increased","Food inflation decreased") -> Food inflation increased
P6: Health | Q6: =AVERAGE(L21:L32) -> 0.062565953 | R6: =AVERAGE(L33:L44) -> 0.049649337 | S6: =R6-Q6 -> -0.012916616 | T6: =IF(S6>0,"Health inflation increased","Health inflation decreased") -> Health inflation decreased
A7: Date | B7: Period | C7: General Index | D7: Food & Beverages | E7: Health | F7: Fuel & Light | G7: Household Goods & Services | H7: Transport & Communication | I7: Essential Services Index | J7: General YoY % | K7: Food YoY % | L7: Health YoY % | M7: Essential Services YoY % | N7: Data Status | P7: Essential Services | Q7: =AVERAGE(M21:M32) -> 0.022470986 | R7: =AVERAGE(M33:M44) -> 0.045565035 | S7: =R7-Q7 -> 0.023094049 | T7: =IF(S7>0,"Essential-services inflation increased","Essential-services inflation decreased") -> Essential-services inflation increased
A8: 43160 | B8: Pre-COVID | C8: 136.5 | D8: 137.2 | E8: 134.3 | F8: 136.5 | G8: 135.6 | H8: 121 | I8: =AVERAGE(F8:H8) -> 131.03333 | N8: Observed
A9: 43191 | B9: Pre-COVID | C9: 137.1 | D9: 137.5 | E9: 135.2 | F9: 136.5 | G9: 136.6 | H9: 121.9 | I9: =AVERAGE(F9:H9) -> 131.66667 | N9: Observed
A10: 43221 | B10: Pre-COVID | C10: 137.8 | D10: 138.1 | E10: 136 | F10: 136.9 | G10: 137.4 | H10: 122.9 | I10: =AVERAGE(F10:H10) -> 132.4 | N10: Observed | P10: Key Metric | Q10: Formula / Result
A11: 43252 | B11: Pre-COVID | C11: 138.5 | D11: 139.4 | E11: 136.2 | F11: 138.1 | G11: 137.9 | H11: 123.7 | I11: =AVERAGE(F11:H11) -> 133.23333 | N11: Observed | P11: Highest post-onset headline inflation | Q11: =MAX(J33:J44) -> 0.065948856
A12: 43282 | B12: Pre-COVID | C12: 139.8 | D12: 141.4 | E12: 137 | F12: 139.7 | G12: 138.6 | H12: 123.6 | I12: =AVERAGE(F12:H12) -> 133.96667 | N12: Observed | P12: Month of highest post-onset headline inflation | Q12: =INDEX(A33:A44,MATCH(MAX(J33:J44),J33:J44,0)) -> 44136
A13: 43313 | B13: Pre-COVID | C13: 140.4 | D13: 141.7 | E13: 137.7 | F13: 140.9 | G13: 139.4 | H13: 124.3 | I13: =AVERAGE(F13:H13) -> 134.86667 | N13: Observed
A14: 43344 | B14: Pre-COVID | C14: 140.2 | D14: 140.4 | E14: 138.4 | F14: 142.3 | G14: 139.7 | H14: 126 | I14: =AVERAGE(F14:H14) -> 136 | N14: Observed | P14: Function / Method Notes
A15: 43374 | B15: Pre-COVID | C15: 140.8 | D15: 139.7 | E15: 142.1 | F15: 145.3 | G15: 142.2 | H15: 125.5 | I15: =AVERAGE(F15:H15) -> 137.66667 | N15: Observed | P15: YoY formula | Q15: Current month CPI ÷ same month previous year CPI − 1. This controls for seasonality better than a simple month-to-month comparison.
A16: 43405 | B16: Pre-COVID | C16: 140.8 | D16: 139.7 | E16: 142.1 | F16: 145.1 | G16: 142.2 | H16: 125.5 | I16: =AVERAGE(F16:H16) -> 137.6 | N16: Observed | P16: AVERAGE | Q16: Used for Essential Services composite and for pre/post average inflation.
A17: 43435 | B17: Pre-COVID | C17: 140.1 | D17: 138.2 | E17: 144.9 | F17: 142.7 | G17: 143.2 | H17: 123.6 | I17: =AVERAGE(F17:H17) -> 136.5 | N17: Observed | P17: Linear interpolation | Q17: Used only where a monthly CPI observation required for the comparison is missing; estimated cells are flagged in Data Status.
A18: 43466 | B18: Pre-COVID | C18: 139.6 | D18: 137.4 | E18: 145.1 | F18: 139.5 | G18: 143.6 | H18: 123.3 | I18: =AVERAGE(F18:H18) -> 135.46667 | N18: Observed | P18: MAX | Q18: Finds the highest post-onset inflation rate.
A19: 43497 | B19: Pre-COVID | C19: 139.9 | D19: 137.5 | E19: 145.6 | F19: 138.4 | G19: 143.7 | H19: 123.9 | I19: =AVERAGE(F19:H19) -> 135.33333 | N19: Observed | P19: INDEX + MATCH | Q19: Returns the month corresponding to the MAX inflation rate.
A20: 43525 | B20: Pre-COVID | C20: 140.4 | D20: 138.1 | E20: 146.2 | F20: 139.7 | G20: 143.8 | H20: 124.6 | I20: =AVERAGE(F20:H20) -> 136.03333 | J20: =C20/C8-1 -> 0.028571429 | K20: =D20/D8-1 -> 0.0065597668 | L20: =E20/E8-1 -> 0.088607595 | M20: =I20/I8-1 -> 0.038158229 | N20: Observed | P20: Subtraction | Q20: Post-onset average − Pre-COVID average gives the change in percentage points.
A21: 43556 | B21: Pre-COVID | C21: =C20+(C22-C20)*0.5 -> 141.2 | D21: =D20+(D22-D20)*0.5 -> 139.5 | E21: =E20+(E22-E20)*0.5 -> 146.55 | F21: =F20+(F22-F20)*0.5 -> 140 | G21: =G20+(G22-G20)*0.5 -> 143.75 | H21: =H20+(H22-H20)*0.5 -> 124.75 | I21: =AVERAGE(F21:H21) -> 136.16667 | J21: =C21/C9-1 -> 0.029905179 | K21: =D21/D9-1 -> 0.014545455 | L21: =E21/E9-1 -> 0.083949704 | M21: =I21/I9-1 -> 0.034177215 | N21: General, Food, Health, Fuel, HH, Trans
A22: 43586 | B22: Pre-COVID | C22: 142 | D22: 140.9 | E22: 146.9 | F22: 140.3 | G22: 143.7 | H22: 124.9 | I22: =AVERAGE(F22:H22) -> 136.3 | J22: =C22/C10-1 -> 0.030478955 | K22: =D22/D10-1 -> 0.020275163 | L22: =E22/E10-1 -> 0.080147059 | M22: =I22/I10-1 -> 0.029456193 | N22: Observed
A23: 43617 | B23: Pre-COVID | C23: 142.9 | D23: 142.7 | E23: 147.4 | F23: 141.2 | G23: 143.8 | H23: 124.6 | I23: =AVERAGE(F23:H23) -> 136.53333 | J23: =C23/C11-1 -> 0.031768953 | K23: =D23/D11-1 -> 0.023672884 | L23: =E23/E11-1 -> 0.082232012 | M23: =I23/I11-1 -> 0.024768576 | N23: Observed
A24: 43647 | B24: Pre-COVID | C24: 144.2 | D24: 144.7 | E24: 147.9 | F24: 139.3 | G24: 144.2 | H24: 125.6 | I24: =AVERAGE(F24:H24) -> 136.36667 | J24: =C24/C12-1 -> 0.031473534 | K24: =D24/D12-1 -> 0.023338048 | L24: =E24/E12-1 -> 0.079562044 | M24: =I24/I12-1 -> 0.017914904 | N24: Observed
A25: 43678 | B25: Pre-COVID | C25: 145 | D25: 145.9 | E25: 148.5 | F25: 138.5 | G25: 144.5 | H25: 125.8 | I25: =AVERAGE(F25:H25) -> 136.26667 | J25: =C25/C13-1 -> 0.032763533 | K25: =D25/D13-1 -> 0.029640085 | L25: =E25/E13-1 -> 0.078431373 | M25: =I25/I13-1 -> 0.010380623 | N25: Observed
A26: 43709 | B26: Pre-COVID | C26: 145.8 | D26: 147 | E26: 149 | F26: 139.2 | G26: 144.6 | H26: 126.1 | I26: =AVERAGE(F26:H26) -> 136.63333 | J26: =C26/C14-1 -> 0.039942939 | K26: =D26/D14-1 -> 0.047008547 | L26: =E26/E14-1 -> 0.076589595 | M26: =I26/I14-1 -> 0.0046568627 | N26: Observed
A27: 43739 | B27: Pre-COVID | C27: 147.2 | D27: 149.6 | E27: 149.4 | F27: 140.6 | G27: 145 | H27: 126.3 | I27: =AVERAGE(F27:H27) -> 137.3 | J27: =C27/C15-1 -> 0.045454545 | K27: =D27/D15-1 -> 0.070866142 | L27: =E27/E15-1 -> 0.051372273 | M27: =I27/I15-1 -> -0.0026634383 | N27: Observed
A28: 43770 | B28: Pre-COVID | C28: 148.6 | D28: 151.9 | E28: 149.9 | F28: 142.3 | G28: 145.3 | H28: 126.6 | I28: =AVERAGE(F28:H28) -> 138.06667 | J28: =C28/C16-1 -> 0.055397727 | K28: =D28/D16-1 -> 0.087329993 | L28: =E28/E16-1 -> 0.054890922 | M28: =I28/I16-1 -> 0.0033914729 | N28: Observed
A29: 43800 | B29: Pre-COVID | C29: 150.4 | D29: 155 | E29: 150.4 | F29: 143.7 | G29: 145.8 | H29: 129.8 | I29: =AVERAGE(F29:H29) -> 139.76667 | J29: =C29/C17-1 -> 0.073518915 | K29: =D29/D17-1 -> 0.12156295 | L29: =E29/E17-1 -> 0.037957212 | M29: =I29/I17-1 -> 0.023931624 | N29: Observed
A30: 43831 | B30: Pre-COVID | C30: 150.2 | D30: 153.5 | E30: 151.2 | F30: 144.6 | G30: 146.2 | H30: 130.9 | I30: =AVERAGE(F30:H30) -> 140.56667 | J30: =C30/C18-1 -> 0.075931232 | K30: =D30/D18-1 -> 0.11717613 | L30: =E30/E18-1 -> 0.042039972 | M30: =I30/I18-1 -> 0.037647638 | N30: Observed
A31: 43862 | B31: Pre-COVID | C31: 149.1 | D31: 150.5 | E31: 151.7 | F31: 147.2 | G31: 146.4 | H31: 130.3 | I31: =AVERAGE(F31:H31) -> 141.3 | J31: =C31/C19-1 -> 0.065761258 | K31: =D31/D19-1 -> 0.094545455 | L31: =E31/E19-1 -> 0.041895604 | M31: =I31/I19-1 -> 0.04408867 | N31: Observed
A32: 43891 | B32: COVID onset | C32: 148.6 | D32: 148.9 | E32: 152.3 | F32: 148.9 | G32: 146.4 | H32: 129.9 | I32: =AVERAGE(F32:H32) -> 141.73333 | J32: =C32/C20-1 -> 0.058404558 | K32: =D32/D20-1 -> 0.0782042 | L32: =E32/E20-1 -> 0.041723666 | M32: =I32/I20-1 -> 0.041901495 | N32: Observed
A33: 43922 | B33: Post-onset | C33: =C32+(C35-C32)*(1/3) -> 149.66667 | D33: =D32+(D35-D32)*(1/3) -> 150.6 | E33: =E32+(E35-E32)*(1/3) -> 153 | F33: =F32+(F35-F32)*(1/3) -> 146.56667 | G33: =G32+(G35-G32)*(1/3) -> 146.4 | H33: =H32+(H35-H32)*(1/3) -> 131.6 | I33: =AVERAGE(F33:H33) -> 141.52222 | J33: =C33/C21-1 -> 0.059962229 | K33: =D33/D21-1 -> 0.079569892 | L33: =E33/E21-1 -> 0.044012282 | M33: =I33/I21-1 -> 0.039330885 | N33: Interpolated Apr-20: 1/3 between Mar-20 and Jun-20
A34: 43952 | B34: Post-onset | C34: =C32+(C35-C32)*(2/3) -> 150.73333 | D34: =D32+(D35-D32)*(2/3) -> 152.3 | E34: =E32+(E35-E32)*(2/3) -> 153.7 | F34: =F32+(F35-F32)*(2/3) -> 144.23333 | G34: =G32+(G35-G32)*(2/3) -> 146.4 | H34: =H32+(H35-H32)*(2/3) -> 133.3 | I34: =AVERAGE(F34:H34) -> 141.31111 | J34: =C34/C22-1 -> 0.061502347 | K34: =D34/D22-1 -> 0.080908446 | L34: =E34/E22-1 -> 0.046289993 | M34: =I34/I22-1 -> 0.036765305 | N34: Interpolated May-20: 2/3 between Mar-20 and Jun-20
A35: 43983 | B35: Post-onset | C35: 151.8 | D35: 154 | E35: 154.4 | F35: 141.9 | G35: 146.4 | H35: 135 | I35: =AVERAGE(F35:H35) -> 141.1 | J35: =C35/C23-1 -> 0.062281316 | K35: =D35/D23-1 -> 0.079187106 | L35: =E35/E23-1 -> 0.047489824 | M35: =I35/I23-1 -> 0.033447266 | N35: Observed
A36: 44013 | B36: Post-onset | C36: 151.8 | D36: 154 | E36: 154.4 | F36: 141.9 | G36: 146.4 | H36: 135 | I36: =AVERAGE(F36:H36) -> 141.1 | J36: =C36/C24-1 -> 0.052704577 | K36: =D36/D24-1 -> 0.064270905 | L36: =E36/E24-1 -> 0.043948614 | M36: =I36/I24-1 -> 0.03471034 | N36: Observed
A37: 44044 | B37: Post-onset | C37: 153.9 | D37: 157 | E37: 155 | F37: 143 | G37: 148.4 | H37: 138.5 | I37: =AVERAGE(F37:H37) -> 143.3 | J37: =C37/C25-1 -> 0.06137931 | K37: =D37/D25-1 -> 0.076079507 | L37: =E37/E25-1 -> 0.043771044 | M37: =I37/I25-1 -> 0.051614481 | N37: Observed
A38: 44075 | B38: Post-onset | C38: 154.7 | D38: 158 | E38: 155.6 | F38: 142.9 | G38: 148.7 | H38: 139.6 | I38: =AVERAGE(F38:H38) -> 143.73333 | J38: =C38/C26-1 -> 0.061042524 | K38: =D38/D26-1 -> 0.074829932 | L38: =E38/E26-1 -> 0.044295302 | M38: =I38/I26-1 -> 0.051963894 | N38: Observed
A39: 44105 | B39: Post-onset | C39: 156.4 | D39: 161.4 | E39: 156.3 | F39: 143.1 | G39: 148.7 | H39: 140.6 | I39: =AVERAGE(F39:H39) -> 144.13333 | J39: =C39/C27-1 -> 0.0625 | K39: =D39/D27-1 -> 0.078877005 | L39: =E39/E27-1 -> 0.046184739 | M39: =I39/I27-1 -> 0.049769361 | N39: Observed
A40: 44136 | B40: Post-onset | C40: 158.4 | D40: 164.7 | E40: 157.2 | F40: 143.6 | G40: 149.2 | H40: 140.4 | I40: =AVERAGE(F40:H40) -> 144.4 | J40: =C40/C28-1 -> 0.065948856 | K40: =D40/D28-1 -> 0.084265964 | L40: =E40/E28-1 -> 0.048699133 | M40: =I40/I28-1 -> 0.04587156 | N40: Observed
A41: 44166 | B41: Post-onset | C41: 158.9 | D41: 165.4 | E41: 158.3 | F41: 144.6 | G41: 149.7 | H41: 140.7 | I41: =AVERAGE(F41:H41) -> 145 | J41: =C41/C29-1 -> 0.056515957 | K41: =D41/D29-1 -> 0.067096774 | L41: =E41/E29-1 -> 0.052526596 | M41: =I41/I29-1 -> 0.037443358 | N41: Observed
A42: 44197 | B42: Post-onset | C42: =SUMIFS('Clean Data'!$AD:$AD,'Clean Data'!$A:$A,"Rural+Urban",'Clean Data'!$B:$B,2021,'Clean Data'!$C:$C,"January") -> 157.3 | D42: =SUMIFS('Clean Data'!$P:$P,'Clean Data'!$A:$A,"Rural+Urban",'Clean Data'!$B:$B,2021,'Clean Data'!$C:$C,"January") -> 161 | E42: =SUMIFS('Clean Data'!$X:$X,'Clean Data'!$A:$A,"Rural+Urban",'Clean Data'!$B:$B,2021,'Clean Data'!$C:$C,"January") -> 159.3 | F42: =SUMIFS('Clean Data'!$V:$V,'Clean Data'!$A:$A,"Rural+Urban",'Clean Data'!$B:$B,2021,'Clean Data'!$C:$C,"January") -> 147.9 | G42: =SUMIFS('Clean Data'!$W:$W,'Clean Data'!$A:$A,"Rural+Urban",'Clean Data'!$B:$B,2021,'Clean Data'!$C:$C,"January") -> 150 | H42: =SUMIFS('Clean Data'!$Y:$Y,'Clean Data'!$A:$A,"Rural+Urban",'Clean Data'!$B:$B,2021,'Clean Data'!$C:$C,"January") -> 141.9 | I42: =AVERAGE(F42:H42) -> 146.6 | J42: =C42/C30-1 -> 0.047270306 | K42: =D42/D30-1 -> 0.048859935 | L42: =E42/E30-1 -> 0.053571429 | M42: =I42/I30-1 -> 0.042921508 | N42: Observed — retrieved from Clean Data
A43: 44228 | B43: Post-onset | C43: 156.6 | D43: 156.9 | E43: 161.3 | F43: 152.4 | G43: 150.9 | H43: 145.1 | I43: =AVERAGE(F43:H43) -> 149.46667 | J43: =C43/C31-1 -> 0.050301811 | K43: =D43/D31-1 -> 0.042524917 | L43: =E43/E31-1 -> 0.063282795 | M43: =I43/I31-1 -> 0.05779665 | N43: Observed
A44: 44256 | B44: Post-onset | C44: 156.8 | D44: 156.7 | E44: 161.7 | F44: 155.5 | G44: 151.2 | H44: 146.2 | I44: =AVERAGE(F44:H44) -> 150.96667 | J44: =C44/C32-1 -> 0.055181696 | K44: =D44/D32-1 -> 0.05238415 | L44: =E44/E32-1 -> 0.061720289 | M44: =I44/I32-1 -> 0.065145814 | N44: Observed
A46: Q4 Data / Method Note
A47: April and May 2020 source observations were unavailable in the Rural+Urban series, so the analysis uses transparent linear interpolation between March and June 2020. January 2021 is observed and retrieved directly from Clean Data. These assumptions are flagged in the Data Status column.

Sheet Q4 Pivot
A1: Q4 — COVID Inflation Pre/Post Summary
G2: ← Dashboard
A3: Category | B3: Pre-COVID Avg YoY | C3: Post-onset Avg YoY | D3: Change (pp) | E3: Direction | F3: Method
A4: ='Q4 Calculation'!P4 -> General CPI | B4: ='Q4 Calculation'!Q4 -> 0.047566777 | C4: ='Q4 Calculation'!R4 -> 0.058049244 | D4: ='Q4 Calculation'!S4 -> 0.010482467 | E4: =IF(D4>0,"Higher after onset","Lower after onset") -> Higher after onset | F4: 12-month average YoY comparison
A5: ='Q4 Calculation'!P5 -> Food | B5: ='Q4 Calculation'!Q5 -> 0.060680421 | C5: ='Q4 Calculation'!R5 -> 0.069071211 | D5: ='Q4 Calculation'!S5 -> 0.0083907903 | E5: =IF(D5>0,"Higher after onset","Lower after onset") -> Higher after onset | F5: 12-month average YoY comparison
A6: ='Q4 Calculation'!P6 -> Health | B6: ='Q4 Calculation'!Q6 -> 0.062565953 | C6: ='Q4 Calculation'!R6 -> 0.049649337 | D6: ='Q4 Calculation'!S6 -> -0.012916616 | E6: =IF(D6>0,"Higher after onset","Lower after onset") -> Lower after onset | F6: 12-month average YoY comparison
A7: ='Q4 Calculation'!P7 -> Essential Services | B7: ='Q4 Calculation'!Q7 -> 0.022470986 | C7: ='Q4 Calculation'!R7 -> 0.045565035 | D7: ='Q4 Calculation'!S7 -> 0.023094049 | E7: =IF(D7>0,"Higher after onset","Lower after onset") -> Higher after onset | F7: 12-month average YoY comparison
A10: Milestone
A11: COVID onset / first lockdown reference | B11: ='Q4 Calculation'!A32 -> 43891 | C11: ='Q4 Calculation'!J32 -> 0.058404558 | D11: ='Q4 Calculation'!K32 -> 0.0782042 | E11: ='Q4 Calculation'!L32 -> 0.041723666 | F11: ='Q4 Calculation'!M32 -> 0.041901495
A14: Function / Method Notes
A15: Linked formulas | B15: Summary values link directly to Q4 Calculation; no hard-coded analytical results.
A16: IF | B16: Classifies whether post-onset average inflation is higher or lower than pre-COVID.
A17: 12-month comparison | B17: Apr-2019–Mar-2020 vs Apr-2020–Mar-2021 keeps equal-length windows around the March 2020 milestone.

Sheet Q4 Visualization
A1: Q4 — COVID-19 Inflation Impact Dashboard
Q2: ← Dashboard
A3: Month | B3: General CPI YoY | C3: Food YoY | D3: Health YoY | E3: Essential Services YoY | G3: Category | H3: Pre-COVID Avg | I3: Post-onset Avg | J3: Change (pp)
A4: ='Q4 Calculation'!A20 -> 43525 | B4: ='Q4 Calculation'!J20 -> 0.028571429 | C4: ='Q4 Calculation'!K20 -> 0.0065597668 | D4: ='Q4 Calculation'!L20 -> 0.088607595 | E4: ='Q4 Calculation'!M20 -> 0.038158229 | G4: ='Q4 Calculation'!P4 -> General CPI | H4: ='Q4 Calculation'!Q4 -> 0.047566777 | I4: ='Q4 Calculation'!R4 -> 0.058049244 | J4: ='Q4 Calculation'!S4 -> 0.010482467
A5: ='Q4 Calculation'!A21 -> 43556 | B5: ='Q4 Calculation'!J21 -> 0.029905179 | C5: ='Q4 Calculation'!K21 -> 0.014545455 | D5: ='Q4 Calculation'!L21 -> 0.083949704 | E5: ='Q4 Calculation'!M21 -> 0.034177215 | G5: ='Q4 Calculation'!P5 -> Food | H5: ='Q4 Calculation'!Q5 -> 0.060680421 | I5: ='Q4 Calculation'!R5 -> 0.069071211 | J5: ='Q4 Calculation'!S5 -> 0.0083907903
A6: ='Q4 Calculation'!A22 -> 43586 | B6: ='Q4 Calculation'!J22 -> 0.030478955 | C6: ='Q4 Calculation'!K22 -> 0.020275163 | D6: ='Q4 Calculation'!L22 -> 0.080147059 | E6: ='Q4 Calculation'!M22 -> 0.029456193 | G6: ='Q4 Calculation'!P6 -> Health | H6: ='Q4 Calculation'!Q6 -> 0.062565953 | I6: ='Q4 Calculation'!R6 -> 0.049649337 | J6: ='Q4 Calculation'!S6 -> -0.012916616
A7: ='Q4 Calculation'!A23 -> 43617 | B7: ='Q4 Calculation'!J23 -> 0.031768953 | C7: ='Q4 Calculation'!K23 -> 0.023672884 | D7: ='Q4 Calculation'!L23 -> 0.082232012 | E7: ='Q4 Calculation'!M23 -> 0.024768576 | G7: ='Q4 Calculation'!P7 -> Essential Services | H7: ='Q4 Calculation'!Q7 -> 0.022470986 | I7: ='Q4 Calculation'!R7 -> 0.045565035 | J7: ='Q4 Calculation'!S7 -> 0.023094049
A8: ='Q4 Calculation'!A24 -> 43647 | B8: ='Q4 Calculation'!J24 -> 0.031473534 | C8: ='Q4 Calculation'!K24 -> 0.023338048 | D8: ='Q4 Calculation'!L24 -> 0.079562044 | E8: ='Q4 Calculation'!M24 -> 0.017914904
A9: ='Q4 Calculation'!A25 -> 43678 | B9: ='Q4 Calculation'!J25 -> 0.032763533 | C9: ='Q4 Calculation'!K25 -> 0.029640085 | D9: ='Q4 Calculation'!L25 -> 0.078431373 | E9: ='Q4 Calculation'!M25 -> 0.010380623
A10: Q4 Key Insight
A11: general index CPI inflation increased from about 4.76% before the COVID-19 onset to 5.80% after onset, a rise of about 1.05 percentage points. Food and essential services also increased, while health inflation was lower on average in the first post-onset year. The pattern suggests supply disruption and changing demand conditions rather than a uniform effect across categories.
A14: ='Q4 Calculation'!A30 -> 43831 | B14: ='Q4 Calculation'!J30 -> 0.075931232 | C14: ='Q4 Calculation'!K30 -> 0.11717613 | D14: ='Q4 Calculation'!L30 -> 0.042039972 | E14: ='Q4 Calculation'!M30 -> 0.037647638 | G14: Essential Services | H14: The composite rose materially after onset, reflecting higher inflation in fuel/light, household services and transport/communication.
A15: ='Q4 Calculation'!A31 -> 43862 | B15: ='Q4 Calculation'!J31 -> 0.065761258 | C15: ='Q4 Calculation'!K31 -> 0.094545455 | D15: ='Q4 Calculation'!L31 -> 0.041895604 | E15: ='Q4 Calculation'!M31 -> 0.04408867
A16: ='Q4 Calculation'!A32 -> 43891 | B16: ='Q4 Calculation'!J32 -> 0.058404558 | C16: ='Q4 Calculation'!K32 -> 0.0782042 | D16: ='Q4 Calculation'!L32 -> 0.041723666 | E16: ='Q4 Calculation'!M32 -> 0.041901495
A17: ='Q4 Calculation'!A33 -> 43922 | B17: ='Q4 Calculation'!J33 -> 0.059962229 | C17: ='Q4 Calculation'!K33 -> 0.079569892 | D17: ='Q4 Calculation'!L33 -> 0.044012282 | E17: ='Q4 Calculation'!M33 -> 0.039330885 | G17: Function / Method Notes
A18: ='Q4 Calculation'!A34 -> 43952 | B18: ='Q4 Calculation'!J34 -> 0.061502347 | C18: ='Q4 Calculation'!K34 -> 0.080908446 | D18: ='Q4 Calculation'!L34 -> 0.046289993 | E18: ='Q4 Calculation'!M34 -> 0.036765305 | G18: Linked formulas | H18: Chart data and summary metrics are linked to Q4 Calculation.
A19: ='Q4 Calculation'!A35 -> 43983 | B19: ='Q4 Calculation'!J35 -> 0.062281316 | C19: ='Q4 Calculation'!K35 -> 0.079187106 | D19: ='Q4 Calculation'!L35 -> 0.047489824 | E19: ='Q4 Calculation'!M35 -> 0.033447266 | G19: Line chart | H19: Shows the progression of monthly YoY inflation around the March 2020 milestone.
A20: ='Q4 Calculation'!A36 -> 44013 | B20: ='Q4 Calculation'!J36 -> 0.052704577 | C20: ='Q4 Calculation'!K36 -> 0.064270905 | D20: ='Q4 Calculation'!L36 -> 0.043948614 | E20: ='Q4 Calculation'!M36 -> 0.03471034 | G20: Clustered column chart | H20: Compares average inflation before and after the onset across categories.
A21: ='Q4 Calculation'!A37 -> 44044 | B21: ='Q4 Calculation'!J37 -> 0.06137931 | C21: ='Q4 Calculation'!K37 -> 0.076079507 | D21: ='Q4 Calculation'!L37 -> 0.043771044 | E21: ='Q4 Calculation'!M37 -> 0.051614481
A22: ='Q4 Calculation'!A38 -> 44075 | B22: ='Q4 Calculation'!J38 -> 0.061042524 | C22: ='Q4 Calculation'!K38 -> 0.074829932 | D22: ='Q4 Calculation'!L38 -> 0.044295302 | E22: ='Q4 Calculation'!M38 -> 0.051963894
A23: ='Q4 Calculation'!A39 -> 44105 | B23: ='Q4 Calculation'!J39 -> 0.0625 | C23: ='Q4 Calculation'!K39 -> 0.078877005 | D23: ='Q4 Calculation'!L39 -> 0.046184739 | E23: ='Q4 Calculation'!M39 -> 0.049769361
A24: ='Q4 Calculation'!A40 -> 44136 | B24: ='Q4 Calculation'!J40 -> 0.065948856 | C24: ='Q4 Calculation'!K40 -> 0.084265964 | D24: ='Q4 Calculation'!L40 -> 0.048699133 | E24: ='Q4 Calculation'!M40 -> 0.04587156
A25: ='Q4 Calculation'!A41 -> 44166 | B25: ='Q4 Calculation'!J41 -> 0.056515957 | C25: ='Q4 Calculation'!K41 -> 0.067096774 | D25: ='Q4 Calculation'!L41 -> 0.052526596 | E25: ='Q4 Calculation'!M41 -> 0.037443358
A26: ='Q4 Calculation'!A42 -> 44197 | B26: ='Q4 Calculation'!J42 -> 0.047270306 | C26: ='Q4 Calculation'!K42 -> 0.048859935 | D26: ='Q4 Calculation'!L42 -> 0.053571429 | E26: ='Q4 Calculation'!M42 -> 0.042921508
A27: ='Q4 Calculation'!A43 -> 44228 | B27: ='Q4 Calculation'!J43 -> 0.050301811 | C27: ='Q4 Calculation'!K43 -> 0.042524917 | D27: ='Q4 Calculation'!L43 -> 0.063282795 | E27: ='Q4 Calculation'!M43 -> 0.05779665
A28: ='Q4 Calculation'!A44 -> 44256 | B28: ='Q4 Calculation'!J44 -> 0.055181696 | C28: ='Q4 Calculation'!K44 -> 0.05238415 | D28: ='Q4 Calculation'!L44 -> 0.061720289 | E28: ='Q4 Calculation'!M44 -> 0.065145814

Sheet Q4 Research
A1: Q4 — Research: Why COVID-19 Changed Inflation Dynamics
G2: ← Dashboard
A3: Driver | B3: Evidence / Interpretation | C3: Source | D3: Source Link | E3: Connection to our CPI analysis
A4: Lockdown supply disruptions | B4: The Economic Survey reports that headline CPI inflation stayed high during the COVID-induced lockdown and afterward because supply-side disruptions persisted; food inflation was a major driver. | C4: Economic Survey 2020-21 / Ministry of Finance | D4: https://www.indiabudget.gov.in/economicsurvey/ebook_es2021/files/basic-html/page534.html | E4: Supports the rise in headline and food inflation after March 2020.
A5: Food-price pressure | B5: The Economic Survey states food inflation increased to 9.1% during Apr-Dec 2020-21 and that COVID disruptions increased price momentum from April 2020. | C5: Economic Survey 2020-21 / Ministry of Finance | D5: https://www.pib.gov.in/Pressreleaseshare.aspx?PRID=1693196&lang=2&reg=48 | E5: Consistent with elevated Food YoY inflation in the post-onset period.
A6: Supply factors dominated during COVID | B6: RBI analysis finds supply-side factors became predominant during different phases of COVID-19; demand-side contribution to inflation fell in 2020. | C6: RBI Annual Report 2022-23 | D6: https://www.rbi.org.in/scripts/AnnualReportPublications.aspx?Id=1373 | E6: Explains why inflation could rise despite weak economic activity.
A7: Pre-COVID food pressure already existed | B7: RBI notes inflation exceeded the upper tolerance band in Dec 2019-Feb 2020 because of rising food-price pressures. | C7: RBI Annual Report 2019-20 | D7: https://www.rbi.org.in/scripts/AnnualReportPublications.aspx?Id=1287 | E7: Important context: food inflation was already high before the lockdown.
A8: Easing as supply constraints normalized | B8: The Economic Survey notes that softer inflation toward the end of 2020 reflected easing supply-side constraints, particularly in food. | C8: Economic Survey 2020-21 | D8: https://www.indiabudget.gov.in/economicsurvey/ebook_es2021/files/basic-html/page422.html | E8: Explains why food inflation later moderated from its 2020 peaks.
A11: Overall conclusion
A12: COVID-19 and the nationwide lockdown materially changed India’s inflation dynamics. Our before/after analysis shows headline CPI and essential-service inflation increased after the March 2020 milestone, while food inflation remained elevated. Healthcare moved differently and did not rise on average in the same way. The evidence indicates that supply-chain disruptions and food-supply pressures were important drivers, but the analysis should be interpreted as an association around the COVID milestone rather than proof of causation.
A16: Method / Source Notes
A17: Official sources | B17: Research uses Government of India Economic Survey and Reserve Bank of India publications.
A18: Causality caution | B18: The workbook describes association around the March 2020 milestone; it does not claim the spreadsheet alone proves causal impact.
A19: Essential Services definition | B19: Equal-weighted average of Fuel & Light, Household Goods & Services, and Transport & Communication for this project.
A20: March 2020 milestone | B20: Used because the case-study hint specifies Mar-20 as the onset/reference point.

Sheet Q5 Oil Data
A1: Q5 — Imported Crude Oil Price Data (Indian Basket)
A2: Source: Petroleum Planning & Analysis Cell (PPAC), Government of India. Price is Indian Basket crude oil, USD per barrel. | G2: ← Dashboard
A3: 2020-12 is included only as the base month required to calculate Jan-2021 MoM oil change. Q5 analysis itself is 2021–2023.
A5: Date | B5: Year | C5: Month | D5: Indian Basket Crude Oil ($/bbl) | E5: MoM Oil Price Change % | F5: Use
A6: 44166 | B6: 2020 | C6: December | D6: 49.84 | F6: Base month only
A7: 44197 | B7: 2021 | C7: January | D7: 54.79 | E7: =IFERROR(D7/D6-1,"") -> 0.099317817 | F7: Q5 analysis
A8: 44228 | B8: 2021 | C8: February | D8: 61.22 | E8: =IFERROR(D8/D7-1,"") -> 0.11735718 | F8: Q5 analysis
A9: 44256 | B9: 2021 | C9: March | D9: 64.73 | E9: =IFERROR(D9/D8-1,"") -> 0.057334205 | F9: Q5 analysis
A10: 44287 | B10: 2021 | C10: April | D10: 63.4 | E10: =IFERROR(D10/D9-1,"") -> -0.020546887 | F10: Q5 analysis
A11: 44317 | B11: 2021 | C11: May | D11: 66.95 | E11: =IFERROR(D11/D10-1,"") -> 0.055993691 | F11: Q5 analysis
A12: 44348 | B12: 2021 | C12: June | D12: 71.98 | E12: =IFERROR(D12/D11-1,"") -> 0.075130695 | F12: Q5 analysis
A13: 44378 | B13: 2021 | C13: July | D13: 73.54 | E13: =IFERROR(D13/D12-1,"") -> 0.021672687 | F13: Q5 analysis
A14: 44409 | B14: 2021 | C14: August | D14: 69.8 | E14: =IFERROR(D14/D13-1,"") -> -0.050856677 | F14: Q5 analysis
A15: 44440 | B15: 2021 | C15: September | D15: 73.13 | E15: =IFERROR(D15/D14-1,"") -> 0.047707736 | F15: Q5 analysis
A16: 44470 | B16: 2021 | C16: October | D16: 82.11 | E16: =IFERROR(D16/D15-1,"") -> 0.12279502 | F16: Q5 analysis
A17: 44501 | B17: 2021 | C17: November | D17: 80.64 | E17: =IFERROR(D17/D16-1,"") -> -0.017902813 | F17: Q5 analysis
A18: 44531 | B18: 2021 | C18: December | D18: 73.3 | E18: =IFERROR(D18/D17-1,"") -> -0.091021825 | F18: Q5 analysis
... A42: 45261 | B42: 2023 | C42: December | D42: 77.42 | E42: =IFERROR(D42/D41-1,"") -> -0.072369998 | F42: Q5 analysis
A45: Function / Method Notes
A46: MoM percentage change | B46: (Current month oil price ÷ previous month oil price) − 1. This measures the month-on-month fluctuation requested in Q5.
A47: Indian Basket | B47: PPAC defines the Indian Basket as a derived basket of Oman & Dubai sour grades and Brent Dated sweet grade; the applicable composition is documented in PPAC reports.
A48: Source limitation | B48: The CPI file ends in May 2023. Therefore, the oil series is collected through Dec-2023, but CPI correlation analysis can only use the overlapping Jan-2021 to May-2023 period.
A50: Source links | B50: https://ppac.gov.in/prices/international-prices-of-crude-oil
A51: PPAC historical supporting data | B51: https://www.data.gov.in/resource/month-wise-details-average-international-crude-oil-prices-indian-basket-2017-18-2022-23

Sheet Q5 Calculation
A1: Q5 — Imported Oil vs CPI Category Inflation (MoM)
A2: Scope: Rural+Urban CPI, overlapping period Jan-2021 to May-2023. Oil series is Indian Basket crude oil ($/bbl). | AG2: ← Dashboard
A3: Method: calculate MoM oil-price change and MoM CPI-index change for every CPI category, then use CORREL to test contemporaneous linear association.
A5: Date | B5: Year | C5: Month | D5: Oil Price ($/bbl) | E5: Oil MoM % | F5: Cereals and products MoM % | G5: Meat and fish MoM % | H5: Egg MoM % | I5: Milk and products MoM % | J5: Oils and fats MoM % | K5: Fruits MoM % | L5: Vegetables MoM % | M5: Pulses and products MoM % | N5: Sugar and Confectionery MoM % | O5: Spices MoM % | P5: Non-alcoholic beverages MoM % | Q5: Prepared meals, snacks, sweets etc. MoM % | R5: Food and beverages MoM % | S5: Pan, tobacco and intoxicants MoM % | T5: Clothing MoM % | U5: Footwear MoM % | V5: Clothing and footwear MoM % | W5: Housing MoM % | X5: Fuel and light MoM % | Y5: Household goods and services MoM % | Z5: Health MoM % | AA5: Transport and communication MoM % | AB5: Recreation and amusement MoM % | AC5: Education MoM % | AD5: Personal care and effects MoM % | AE5: Miscellaneous MoM % | AF5: General index MoM %
A6: 44166 | B6: 2020 | C6: December | D6: 49.84
A7: 44197 | B7: 2021 | C7: January | D7: 54.79 | E7: =IFERROR(D7/D6-1,"") -> 0.099317817 | F7: =IFERROR(SUMIFS('Clean Data'!$D:$D,'Clean Data'!$A:$A,"Rural+Urban",'Clean Data'!$B:$B,B7,'Clean Data'!$C:$C,C7)/SUMIFS('Clean Data'!$D:$D,'Clean Data'!$A:$A,"Rural+Urban",'Clean Data'!$B:$B,YEAR(EDATE(A7,-1)),'Clean Data'!$C:$C,TEXT(EDATE(A7,-1),"mmmm"))-1,"") -> -0.0075342466 | G7: =IFERROR(SUMIFS('Clean Data'!$E:$E,'Clean Data'!$A:$A,"Rural+Urban",'Clean Data'!$B:$B,B7,'Clean Data'!$C:$C,C7)/SUMIFS('Clean Data'!$E:$E,'Clean Data'!$A:$A,"Rural+Urban",'Clean Data'!$B:$B,YEAR(EDATE(A7,-1)),'Clean Data'!$C:$C,TEXT(EDATE(A7,-1),"mmmm"))-1,"") -> -0.0047120419 | H7: =IFERROR(SUMIFS('Clean Data'!$F:$F,'Clean Data'!$A:$A,"Rural+Urban",'Clean Data'!$B:$B,B7,'Clean Data'!$C:$C,C7)/SUMIFS('Clean Data'!$F:$F,'Clean Data'!$A:$A,"Rural+Urban",'Clean Data'!$B:$B,YEAR(EDATE(A7,-1)),'Clean Data'!$C:$C,TEXT(EDATE(A7,-1),"mmmm"))-1,"") -> 0 | I7: =IFERROR(SUMIFS('Clean Data'!$G:$G,'Clean Data'!$A:$A,"Rural+Urban",'Clean Data'!$B:$B,B7,'Clean Data'!$C:$C,C7)/SUMIFS('Clean Data'!$G:$G,'Clean Data'!$A:$A,"Rural+Urban",'Clean Data'!$B:$B,YEAR(EDATE(A7,-1)),'Clean Data'!$C:$C,TEXT(EDATE(A7,-1),"mmmm"))-1,"") -> 0 | J7: =IFERROR(SUMIFS('Clean Data'!$H:$H,'Clean Data'!$A:$A,"Rural+Urban",'Clean Data'!$B:$B,B7,'Clean Data'!$C:$C,C7)/SUMIFS('Clean Data'!$H:$H,'Clean Data'!$A:$A,"Rural+Urban",'Clean Data'!$B:$B,YEAR(EDATE(A7,-1)),'Clean Data'!$C:$C,TEXT(EDATE(A7,-1),"mmmm"))-1,"") -> 0.029331514 | K7: =IFERROR(SUMIFS('Clean Data'!$I:$I,'Clean Data'!$A:$A,"Rural+Urban",'Clean Data'!$B:$B,B7,'Clean Data'!$C:$C,C7)/SUMIFS('Clean Data'!$I:$I,'Clean Data'!$A:$A,"Rural+Urban",'Clean Data'!$B:$B,YEAR(EDATE(A7,-1)),'Clean Data'!$C:$C,TEXT(EDATE(A7,-1),"mmmm"))-1,"") -> 0.012863913 | L7: =IFERROR(SUMIFS('Clean Data'!$J:$J,'Clean Data'!$A:$A,"Rural+Urban",'Clean Data'!$B:$B,B7,'Clean Data'!$C:$C,C7)/SUMIFS('Clean Data'!$J:$J,'Clean Data'!$A:$A,"Rural+Urban",'Clean Data'!$B:$B,YEAR(EDATE(A7,-1)),'Clean Data'!$C:$C,TEXT(EDATE(A7,-1),"mmmm"))-1,"") -> -0.15748373 | M7: =IFERROR(SUMIFS('Clean Data'!$K:$K,'Clean Data'!$A:$A,"Rural+Urban",'Clean Data'!$B:$B,B7,'Clean Data'!$C:$C,C7)/SUMIFS('Clean Data'!$K:$K,'Clean Data'!$A:$A,"Rural+Urban",'Clean Data'!$B:$B,YEAR(EDATE(A7,-1)),'Clean Data'!$C:$C,TEXT(EDATE(A7,-1),"mmmm"))-1,"") -> 0.0012484395 | N7: =IFERROR(SUMIFS('Clean Data'!$L:$L,'Clean Data'!$A:$A,"Rural+Urban",'Clean Data'!$B:$B,B7,'Clean Data'!$C:$C,C7)/SUMIFS('Clean Data'!$L:$L,'Clean Data'!$A:$A,"Rural+Urban",'Clean Data'!$B:$B,YEAR(EDATE(A7,-1)),'Clean Data'!$C:$C,TEXT(EDATE(A7,-1),"mmmm"))-1,"") -> -0.0060711188 | O7: =IFERROR(SUMIFS('Clean Data'!$M:$M,'Clean Data'!$A:$A,"Rural+Urban",'Clean Data'!$B:$B,B7,'Clean Data'!$C:$C,C7)/SUMIFS('Clean Data'!$M:$M,'Clean Data'!$A:$A,"Rural+Urban",'Clean Data'!$B:$B,YEAR(EDATE(A7,-1)),'Clean Data'!$C:$C,TEXT(EDATE(A7,-1),"mmmm"))-1,"") -> 0.0061349693 | P7: =IFERROR(SUMIFS('Clean Data'!$N:$N,'Clean Data'!$A:$A,"Rural+Urban",'Clean Data'!$B:$B,B7,'Clean Data'!$C:$C,C7)/SUMIFS('Clean Data'!$N:$N,'Clean Data'!$A:$A,"Rural+Urban",'Clean Data'!$B:$B,YEAR(EDATE(A7,-1)),'Clean Data'!$C:$C,TEXT(EDATE(A7,-1),"mmmm"))-1,"") -> 0.017426273 | Q7: =IFERROR(SUMIFS('Clean Data'!$O:$O,'Clean Data'!$A:$A,"Rural+Urban",'Clean Data'!$B:$B,B7,'Clean Data'!$C:$C,C7)/SUMIFS('Clean Data'!$O:$O,'Clean Data'!$A:$A,"Rural+Urban",'Clean Data'!$B:$B,YEAR(EDATE(A7,-1)),'Clean Data'!$C:$C,TEXT(EDATE(A7,-1),"mmmm"))-1,"") -> 0.0048543689 | R7: =IFERROR(SUMIFS('Clean Data'!$P:$P,'Clean Data'!$A:$A,"Rural+Urban",'Clean Data'!$B:$B,B7,'Clean Data'!$C:$C,C7)/SUMIFS('Clean Data'!$P:$P,'Clean Data'!$A:$A,"Rural+Urban",'Clean Data'!$B:$B,YEAR(EDATE(A7,-1)),'Clean Data'!$C:$C,TEXT(EDATE(A7,-1),"mmmm"))-1,"") -> -0.026602177 | S7: =IFERROR(SUMIFS('Clean Data'!$Q:$Q,'Clean Data'!$A:$A,"Rural+Urban",'Clean Data'!$B:$B,B7,'Clean Data'!$C:$C,C7)/SUMIFS('Clean Data'!$Q:$Q,'Clean Data'!$A:$A,"Rural+Urban",'Clean Data'!$B:$B,YEAR(EDATE(A7,-1)),'Clean Data'!$C:$C,TEXT(EDATE(A7,-1),"mmmm"))-1,"") -> 0.0059331176 | T7: =IFERROR(SUMIFS('Clean Data'!$R:$R,'Clean Data'!$A:$A,"Rural+Urban",'Clean Data'!$B:$B,B7,'Clean Data'!$C:$C,C7)/SUMIFS('Clean Data'!$R:$R,'Clean Data'!$A:$A,"Rural+Urban",'Clean Data'!$B:$B,YEAR(EDATE(A7,-1)),'Clean Data'!$C:$C,TEXT(EDATE(A7,-1),"mmmm"))-1,"") -> 0.0032258065 | U7: =IFERROR(SUMIFS('Clean Data'!$S:$S,'Clean Data'!$A:$A,"Rural+Urban",'Clean Data'!$B:$B,B7,'Clean Data'!$C:$C,C7)/SUMIFS('Clean Data'!$S:$S,'Clean Data'!$A:$A,"Rural+Urban",'Clean Data'!$B:$B,YEAR(EDATE(A7,-1)),'Clean Data'!$C:$C,TEXT(EDATE(A7,-1),"mmmm"))-1,"") -> 0.0048143054 | V7: =IFERROR(SUMIFS('Clean Data'!$T:$T,'Clean Data'!$A:$A,"Rural+Urban",'Clean Data'!$B:$B,B7,'Clean Data'!$C:$C,C7)/SUMIFS('Clean Data'!$T:$T,'Clean Data'!$A:$A,"Rural+Urban",'Clean Data'!$B:$B,YEAR(EDATE(A7,-1)),'Clean Data'!$C:$C,TEXT(EDATE(A7,-1),"mmmm"))-1,"") -> 0.00390625 | W7: =IFERROR(SUMIFS('Clean Data'!$U:$U,'Clean Data'!$A:$A,"Rural+Urban",'Clean Data'!$B:$B,B7,'Clean Data'!$C:$C,C7)/SUMIFS('Clean Data'!$U:$U,'Clean Data'!$A:$A,"Rural+Urban",'Clean Data'!$B:$B,YEAR(EDATE(A7,-1)),'Clean Data'!$C:$C,TEXT(EDATE(A7,-1),"mmmm"))-1,"") -> -0.0044191919 | X7: =IFERROR(SUMIFS('Clean Data'!$V:$V,'Clean Data'!$A:$A,"Rural+Urban",'Clean Data'!$B:$B,B7,'Clean Data'!$C:$C,C7)/SUMIFS('Clean Data'!$V:$V,'Clean Data'!$A:$A,"Rural+Urban",'Clean Data'!$B:$B,YEAR(EDATE(A7,-1)),'Clean Data'!$C:$C,TEXT(EDATE(A7,-1),"mmmm"))-1,"") -> 0.022821577 | Y7: =IFERROR(SUMIFS('Clean Data'!$W:$W,'Clean Data'!$A:$A,"Rural+Urban",'Clean Data'!$B:$B,B7,'Clean Data'!$C:$C,C7)/SUMIFS('Clean Data'!$W:$W,'Clean Data'!$A:$A,"Rural+Urban",'Clean Data'!$B:$B,YEAR(EDATE(A7,-1)),'Clean Data'!$C:$C,TEXT(EDATE(A7,-1),"mmmm"))-1,"") -> 0.002004008 | Z7: =IFERROR(SUMIFS('Clean Data'!$X:$X,'Clean Data'!$A:$A,"Rural+Urban",'Clean Data'!$B:$B,B7,'Clean Data'!$C:$C,C7)/SUMIFS('Clean Data'!$X:$X,'Clean Data'!$A:$A,"Rural+Urban",'Clean Data'!$B:$B,YEAR(EDATE(A7,-1)),'Clean Data'!$C:$C,TEXT(EDATE(A7,-1),"mmmm"))-1,"") -> 0.0063171194 | AA7: =IFERROR(SUMIFS('Clean Data'!$Y:$Y,'Clean Data'!$A:$A,"Rural+Urban",'Clean Data'!$B:$B,B7,'Clean Data'!$C:$C,C7)/SUMIFS('Clean Data'!$Y:$Y,'Clean Data'!$A:$A,"Rural+Urban",'Clean Data'!$B:$B,YEAR(EDATE(A7,-1)),'Clean Data'!$C:$C,TEXT(EDATE(A7,-1),"mmmm"))-1,"") -> 0.0085287846 | AB7: =IFERROR(SUMIFS('Clean Data'!$Z:$Z,'Clean Data'!$A:$A,"Rural+Urban",'Clean Data'!$B:$B,B7,'Clean Data'!$C:$C,C7)/SUMIFS('Clean Data'!$Z:$Z,'Clean Data'!$A:$A,"Rural+Urban",'Clean Data'!$B:$B,YEAR(EDATE(A7,-1)),'Clean Data'!$C:$C,TEXT(EDATE(A7,-1),"mmmm"))-1,"") -> 0.0074074074 | AC7: =IFERROR(SUMIFS('Clean Data'!$AA:$AA,'Clean Data'!$A:$A,"Rural+Urban",'Clean Data'!$B:$B,B7,'Clean Data'!$C:$C,C7)/SUMIFS('Clean Data'!$AA:$AA,'Clean Data'!$A:$A,"Rural+Urban",'Clean Data'!$B:$B,YEAR(EDATE(A7,-1)),'Clean Data'!$C:$C,TEXT(EDATE(A7,-1),"mmmm"))-1,"") -> -0.0012547051 | AD7: =IFERROR(SUMIFS('Clean Data'!$AB:$AB,'Clean Data'!$A:$A,"Rural+Urban",'Clean Data'!$B:$B,B7,'Clean Data'!$C:$C,C7)/SUMIFS('Clean Data'!$AB:$AB,'Clean Data'!$A:$A,"Rural+Urban",'Clean Data'!$B:$B,YEAR(EDATE(A7,-1)),'Clean Data'!$C:$C,TEXT(EDATE(A7,-1),"mmmm"))-1,"") -> -0.0019096117 | AE7: =IFERROR(SUMIFS('Clean Data'!$AC:$AC,'Clean Data'!$A:$A,"Rural+Urban",'Clean Data'!$B:$B,B7,'Clean Data'!$C:$C,C7)/SUMIFS('Clean Data'!$AC:$AC,'Clean Data'!$A:$A,"Rural+Urban",'Clean Data'!$B:$B,YEAR(EDATE(A7,-1)),'Clean Data'!$C:$C,TEXT(EDATE(A7,-1),"mmmm"))-1,"") -> 0.0046296296 | AF7: =IFERROR(SUMIFS('Clean Data'!$AD:$AD,'Clean Data'!$A:$A,"Rural+Urban",'Clean Data'!$B:$B,B7,'Clean Data'!$C:$C,C7)/SUMIFS('Clean Data'!$AD:$AD,'Clean Data'!$A:$A,"Rural+Urban",'Clean Data'!$B:$B,YEAR(EDATE(A7,-1)),'Clean Data'!$C:$C,TEXT(EDATE(A7,-1),"mmmm"))-1,"") -> -0.010069226
A8: 44228 | B8: 2021 | C8: February | D8: 61.22 | E8: =IFERROR(D8/D7-1,"") -> 0.11735718 | F8: =IFERROR(SUMIFS('Clean Data'!$D:$D,'Clean Data'!$A:$A,"Rural+Urban",'Clean Data'!$B:$B,B8,'Clean Data'!$C:$C,C8)/SUMIFS('Clean Data'!$D:$D,'Clean Data'!$A:$A,"Rural+Urban",'Clean Data'!$B:$B,YEAR(EDATE(A8,-1)),'Clean Data'!$C:$C,TEXT(EDATE(A8,-1),"mmmm"))-1,"") -> -0.0041407867 | G8: =IFERROR(SUMIFS('Clean Data'!$E:$E,'Clean Data'!$A:$A,"Rural+Urban",'Clean Data'!$B:$B,B8,'Clean Data'!$C:$C,C8)/SUMIFS('Clean Data'!$E:$E,'Clean Data'!$A:$A,"Rural+Urban",'Clean Data'!$B:$B,YEAR(EDATE(A8,-1)),'Clean Data'!$C:$C,TEXT(EDATE(A8,-1),"mmmm"))-1,"") -> -0.018937401 | H8: =IFERROR(SUMIFS('Clean Data'!$F:$F,'Clean Data'!$A:$A,"Rural+Urban",'Clean Data'!$B:$B,B8,'Clean Data'!$C:$C,C8)/SUMIFS('Clean Data'!$F:$F,'Clean Data'!$A:$A,"Rural+Urban",'Clean Data'!$B:$B,YEAR(EDATE(A8,-1)),'Clean Data'!$C:$C,TEXT(EDATE(A8,-1),"mmmm"))-1,"") -> -0.037649743 | I8: =IFERROR(SUMIFS('Clean Data'!$G:$G,'Clean Data'!$A:$A,"Rural+Urban",'Clean Data'!$B:$B,B8,'Clean Data'!$C:$C,C8)/SUMIFS('Clean Data'!$G:$G,'Clean Data'!$A:$A,"Rural+Urban",'Clean Data'!$B:$B,YEAR(EDATE(A8,-1)),'Clean Data'!$C:$C,TEXT(EDATE(A8,-1),"mmmm"))-1,"") -> 0.0038935756 | J8: =IFERROR(SUMIFS('Clean Data'!$H:$H,'Clean Data'!$A:$A,"Rural+Urban",'Clean Data'!$B:$B,B8,'Clean Data'!$C:$C,C8)/SUMIFS('Clean Data'!$H:$H,'Clean Data'!$A:$A,"Rural+Urban",'Clean Data'!$B:$B,YEAR(EDATE(A8,-1)),'Clean Data'!$C:$C,TEXT(EDATE(A8,-1),"mmmm"))-1,"") -> 0.051689861 | K8: =IFERROR(SUMIFS('Clean Data'!$I:$I,'Clean Data'!$A:$A,"Rural+Urban",'Clean Data'!$B:$B,B8,'Clean Data'!$C:$C,C8)/SUMIFS('Clean Data'!$I:$I,'Clean Data'!$A:$A,"Rural+Urban",'Clean Data'!$B:$B,YEAR(EDATE(A8,-1)),'Clean Data'!$C:$C,TEXT(EDATE(A8,-1),"mmmm"))-1,"") -> 0.0073529412 | L8: =IFERROR(SUMIFS('Clean Data'!$J:$J,'Clean Data'!$A:$A,"Rural+Urban",'Clean Data'!$B:$B,B8,'Clean Data'!$C:$C,C8)/SUMIFS('Clean Data'!$J:$J,'Clean Data'!$A:$A,"Rural+Urban",'Clean Data'!$B:$B,YEAR(EDATE(A8,-1)),'Clean Data'!$C:$C,TEXT(EDATE(A8,-1),"mmmm"))-1,"") -> -0.17610711 | M8: =IFERROR(SUMIFS('Clean Data'!$K:$K,'Clean Data'!$A:$A,"Rural+Urban",'Clean Data'!$B:$B,B8,'Clean Data'!$C:$C,C8)/SUMIFS('Clean Data'!$K:$K,'Clean Data'!$A:$A,"Rural+Urban",'Clean Data'!$B:$B,YEAR(EDATE(A8,-1)),'Clean Data'!$C:$C,TEXT(EDATE(A8,-1),"mmmm"))-1,"") -> -0.0099750623 | N8: =IFERROR(SUMIFS('Clean Data'!$L:$L,'Clean Data'!$A:$A,"Rural+Urban",'Clean Data'!$B:$B,B8,'Clean Data'!$C:$C,C8)/SUMIFS('Clean Data'!$L:$L,'Clean Data'!$A:$A,"Rural+Urban",'Clean Data'!$B:$B,YEAR(EDATE(A8,-1)),'Clean Data'!$C:$C,TEXT(EDATE(A8,-1),"mmmm"))-1,"") -> -0.015706806 | O8: =IFERROR(SUMIFS('Clean Data'!$M:$M,'Clean Data'!$A:$A,"Rural+Urban",'Clean Data'!$B:$B,B8,'Clean Data'!$C:$C,C8)/SUMIFS('Clean Data'!$M:$M,'Clean Data'!$A:$A,"Rural+Urban",'Clean Data'!$B:$B,YEAR(EDATE(A8,-1)),'Clean Data'!$C:$C,TEXT(EDATE(A8,-1),"mmmm"))-1,"") -> 0.0012195122 | P8: =IFERROR(SUMIFS('Clean Data'!$N:$N,'Clean Data'!$A:$A,"Rural+Urban",'Clean Data'!$B:$B,B8,'Clean Data'!$C:$C,C8)/SUMIFS('Clean Data'!$N:$N,'Clean Data'!$A:$A,"Rural+Urban",'Clean Data'!$B:$B,YEAR(EDATE(A8,-1)),'Clean Data'!$C:$C,TEXT(EDATE(A8,-1),"mmmm"))-1,"") -> 0.024374177 | Q8: =IFERROR(SUMIFS('Clean Data'!$O:$O,'Clean Data'!$A:$A,"Rural+Urban",'Clean Data'!$B:$B,B8,'Clean Data'!$C:$C,C8)/SUMIFS('Clean Data'!$O:$O,'Clean Data'!$A:$A,"Rural+Urban",'Clean Data'!$B:$B,YEAR(EDATE(A8,-1)),'Clean Data'!$C:$C,TEXT(EDATE(A8,-1),"mmmm"))-1,"") -> 0.01147343 | R8: =IFERROR(SUMIFS('Clean Data'!$P:$P,'Clean Data'!$A:$A,"Rural+Urban",'Clean Data'!$B:$B,B8,'Clean Data'!$C:$C,C8)/SUMIFS('Clean Data'!$P:$P,'Clean Data'!$A:$A,"Rural+Urban",'Clean Data'!$B:$B,YEAR(EDATE(A8,-1)),'Clean Data'!$C:$C,TEXT(EDATE(A8,-1),"mmmm"))-1,"") -> -0.025465839 | S8: =IFERROR(SUMIFS('Clean Data'!$Q:$Q,'Clean Data'!$A:$A,"Rural+Urban",'Clean Data'!$B:$B,B8,'Clean Data'!$C:$C,C8)/SUMIFS('Clean Data'!$Q:$Q,'Clean Data'!$A:$A,"Rural+Urban",'Clean Data'!$B:$B,YEAR(EDATE(A8,-1)),'Clean Data'!$C:$C,TEXT(EDATE(A8,-1),"mmmm"))-1,"") -> 0.0096514745 | T8: =IFERROR(SUMIFS('Clean Data'!$R:$R,'Clean Data'!$A:$A,"Rural+Urban",'Clean Data'!$B:$B,B8,'Clean Data'!$C:$C,C8)/SUMIFS('Clean Data'!$R:$R,'Clean Data'!$A:$A,"Rural+Urban",'Clean Data'!$B:$B,YEAR(EDATE(A8,-1)),'Clean Data'!$C:$C,TEXT(EDATE(A8,-1),"mmmm"))-1,"") -> 0.010932476 | U8: =IFERROR(SUMIFS('Clean Data'!$S:$S,'Clean Data'!$A:$A,"Rural+Urban",'Clean Data'!$B:$B,B8,'Clean Data'!$C:$C,C8)/SUMIFS('Clean Data'!$S:$S,'Clean Data'!$A:$A,"Rural+Urban",'Clean Data'!$B:$B,YEAR(EDATE(A8,-1)),'Clean Data'!$C:$C,TEXT(EDATE(A8,-1),"mmmm"))-1,"") -> 0.0088980151 | V8: =IFERROR(SUMIFS('Clean Data'!$T:$T,'Clean Data'!$A:$A,"Rural+Urban",'Clean Data'!$B:$B,B8,'Clean Data'!$C:$C,C8)/SUMIFS('Clean Data'!$T:$T,'Clean Data'!$A:$A,"Rural+Urban",'Clean Data'!$B:$B,YEAR(EDATE(A8,-1)),'Clean Data'!$C:$C,TEXT(EDATE(A8,-1),"mmmm"))-1,"") -> 0.010376135 | W8: =IFERROR(SUMIFS('Clean Data'!$U:$U,'Clean Data'!$A:$A,"Rural+Urban",'Clean Data'!$B:$B,B8,'Clean Data'!$C:$C,C8)/SUMIFS('Clean Data'!$U:$U,'Clean Data'!$A:$A,"Rural+Urban",'Clean Data'!$B:$B,YEAR(EDATE(A8,-1)),'Clean Data'!$C:$C,TEXT(EDATE(A8,-1),"mmmm"))-1,"") -> 0.013316424 | X8: =IFERROR(SUMIFS('Clean Data'!$V:$V,'Clean Data'!$A:$A,"Rural+Urban",'Clean Data'!$B:$B,B8,'Clean Data'!$C:$C,C8)/SUMIFS('Clean Data'!$V:$V,'Clean Data'!$A:$A,"Rural+Urban",'Clean Data'!$B:$B,YEAR(EDATE(A8,-1)),'Clean Data'!$C:$C,TEXT(EDATE(A8,-1),"mmmm"))-1,"") -> 0.030425963 | Y8: =IFERROR(SUMIFS('Clean Data'!$W:$W,'Clean Data'!$A:$A,"Rural+Urban",'Clean Data'!$B:$B,B8,'Clean Data'!$C:$C,C8)/SUMIFS('Clean Data'!$W:$W,'Clean Data'!$A:$A,"Rural+Urban",'Clean Data'!$B:$B,YEAR(EDATE(A8,-1)),'Clean Data'!$C:$C,TEXT(EDATE(A8,-1),"mmmm"))-1,"") -> 0.006 | Z8: =IFERROR(SUMIFS('Clean Data'!$X:$X,'Clean Data'!$A:$A,"Rural+Urban",'Clean Data'!$B:$B,B8,'Clean Data'!$C:$C,C8)/SUMIFS('Clean Data'!$X:$X,'Clean Data'!$A:$A,"Rural+Urban",'Clean Data'!$B:$B,YEAR(EDATE(A8,-1)),'Clean Data'!$C:$C,TEXT(EDATE(A8,-1),"mmmm"))-1,"") -> 0.012554928 | AA8: =IFERROR(SUMIFS('Clean Data'!$Y:$Y,'Clean Data'!$A:$A,"Rural+Urban",'Clean Data'!$B:$B,B8,'Clean Data'!$C:$C,C8)/SUMIFS('Clean Data'!$Y:$Y,'Clean Data'!$A:$A,"Rural+Urban",'Clean Data'!$B:$B,YEAR(EDATE(A8,-1)),'Clean Data'!$C:$C,TEXT(EDATE(A8,-1),"mmmm"))-1,"") -> 0.022551092 | AB8: =IFERROR(SUMIFS('Clean Data'!$Z:$Z,'Clean Data'!$A:$A,"Rural+Urban",'Clean Data'!$B:$B,B8,'Clean Data'!$C:$C,C8)/SUMIFS('Clean Data'!$Z:$Z,'Clean Data'!$A:$A,"Rural+Urban",'Clean Data'!$B:$B,YEAR(EDATE(A8,-1)),'Clean Data'!$C:$C,TEXT(EDATE(A8,-1),"mmmm"))-1,"") -> 0.012700535 | AC8: =IFERROR(SUMIFS('Clean Data'!$AA:$AA,'Clean Data'!$A:$A,"Rural+Urban",'Clean Data'!$B:$B,B8,'Clean Data'!$C:$C,C8)/SUMIFS('Clean Data'!$AA:$AA,'Clean Data'!$A:$A,"Rural+Urban",'Clean Data'!$B:$B,YEAR(EDATE(A8,-1)),'Clean Data'!$C:$C,TEXT(EDATE(A8,-1),"mmmm"))-1,"") -> 0.0018844221 | AD8: =IFERROR(SUMIFS('Clean Data'!$AB:$AB,'Clean Data'!$A:$A,"Rural+Urban",'Clean Data'!$B:$B,B8,'Clean Data'!$C:$C,C8)/SUMIFS('Clean Data'!$AB:$AB,'Clean Data'!$A:$A,"Rural+Urban",'Clean Data'!$B:$B,YEAR(EDATE(A8,-1)),'Clean Data'!$C:$C,TEXT(EDATE(A8,-1),"mmmm"))-1,"") -> -0.006377551 | AE8: =IFERROR(SUMIFS('Clean Data'!$AC:$AC,'Clean Data'!$A:$A,"Rural+Urban",'Clean Data'!$B:$B,B8,'Clean Data'!$C:$C,C8)/SUMIFS('Clean Data'!$AC:$AC,'Clean Data'!$A:$A,"Rural+Urban",'Clean Data'!$B:$B,YEAR(EDATE(A8,-1)),'Clean Data'!$C:$C,TEXT(EDATE(A8,-1),"mmmm"))-1,"") -> 0.0098749177 | AF8: =IFERROR(SUMIFS('Clean Data'!$AD:$AD,'Clean Data'!$A:$A,"Rural+Urban",'Clean Data'!$B:$B,B8,'Clean Data'!$C:$C,C8)/SUMIFS('Clean Data'!$AD:$AD,'Clean Data'!$A:$A,"Rural+Urban",'Clean Data'!$B:$B,YEAR(EDATE(A8,-1)),'Clean Data'!$C:$C,TEXT(EDATE(A8,-1),"mmmm"))-1,"") -> -0.0044500954
A9: 44256 | B9: 2021 | C9: March | D9: 64.73 | E9: =IFERROR(D9/D8-1,"") -> 0.057334205 | F9: =IFERROR(SUMIFS('Clean Data'!$D:$D,'Clean Data'!$A:$A,"Rural+Urban",'Clean Data'!$B:$B,B9,'Clean Data'!$C:$C,C9)/SUMIFS('Clean Data'!$D:$D,'Clean Data'!$A:$A,"Rural+Urban",'Clean Data'!$B:$B,YEAR(EDATE(A9,-1)),'Clean Data'!$C:$C,TEXT(EDATE(A9,-1),"mmmm"))-1,"") -> -0.0013860014 | G9: =IFERROR(SUMIFS('Clean Data'!$E:$E,'Clean Data'!$A:$A,"Rural+Urban",'Clean Data'!$B:$B,B9,'Clean Data'!$C:$C,C9)/SUMIFS('Clean Data'!$E:$E,'Clean Data'!$A:$A,"Rural+Urban",'Clean Data'!$B:$B,YEAR(EDATE(A9,-1)),'Clean Data'!$C:$C,TEXT(EDATE(A9,-1),"mmmm"))-1,"") -> 0.030563003 | H9: =IFERROR(SUMIFS('Clean Data'!$F:$F,'Clean Data'!$A:$A,"Rural+Urban",'Clean Data'!$B:$B,B9,'Clean Data'!$C:$C,C9)/SUMIFS('Clean Data'!$F:$F,'Clean Data'!$A:$A,"Rural+Urban",'Clean Data'!$B:$B,YEAR(EDATE(A9,-1)),'Clean Data'!$C:$C,TEXT(EDATE(A9,-1),"mmmm"))-1,"") -> -0.029045643 | I9: =IFERROR(SUMIFS('Clean Data'!$G:$G,'Clean Data'!$A:$A,"Rural+Urban",'Clean Data'!$B:$B,B9,'Clean Data'!$C:$C,C9)/SUMIFS('Clean Data'!$G:$G,'Clean Data'!$A:$A,"Rural+Urban",'Clean Data'!$B:$B,YEAR(EDATE(A9,-1)),'Clean Data'!$C:$C,TEXT(EDATE(A9,-1),"mmmm"))-1,"") -> 0.0012928248 | J9: =IFERROR(SUMIFS('Clean Data'!$H:$H,'Clean Data'!$A:$A,"Rural+Urban",'Clean Data'!$B:$B,B9,'Clean Data'!$C:$C,C9)/SUMIFS('Clean Data'!$H:$H,'Clean Data'!$A:$A,"Rural+Urban",'Clean Data'!$B:$B,YEAR(EDATE(A9,-1)),'Clean Data'!$C:$C,TEXT(EDATE(A9,-1),"mmmm"))-1,"") -> 0.032766226 | K9: =IFERROR(SUMIFS('Clean Data'!$I:$I,'Clean Data'!$A:$A,"Rural+Urban",'Clean Data'!$B:$B,B9,'Clean Data'!$C:$C,C9)/SUMIFS('Clean Data'!$I:$I,'Clean Data'!$A:$A,"Rural+Urban",'Clean Data'!$B:$B,YEAR(EDATE(A9,-1)),'Clean Data'!$C:$C,TEXT(EDATE(A9,-1),"mmmm"))-1,"") -> 0.0199071 | L9: =IFERROR(SUMIFS('Clean Data'!$J:$J,'Clean Data'!$A:$A,"Rural+Urban",'Clean Data'!$B:$B,B9,'Clean Data'!$C:$C,C9)/SUMIFS('Clean Data'!$J:$J,'Clean Data'!$A:$A,"Rural+Urban",'Clean Data'!$B:$B,YEAR(EDATE(A9,-1)),'Clean Data'!$C:$C,TEXT(EDATE(A9,-1),"mmmm"))-1,"") -> -0.065625 | M9: =IFERROR(SUMIFS('Clean Data'!$K:$K,'Clean Data'!$A:$A,"Rural+Urban",'Clean Data'!$B:$B,B9,'Clean Data'!$C:$C,C9)/SUMIFS('Clean Data'!$K:$K,'Clean Data'!$A:$A,"Rural+Urban",'Clean Data'!$B:$B,YEAR(EDATE(A9,-1)),'Clean Data'!$C:$C,TEXT(EDATE(A9,-1),"mmmm"))-1,"") -> 0.0062972292 | N9: =IFERROR(SUMIFS('Clean Data'!$L:$L,'Clean Data'!$A:$A,"Rural+Urban",'Clean Data'!$B:$B,B9,'Clean Data'!$C:$C,C9)/SUMIFS('Clean Data'!$L:$L,'Clean Data'!$A:$A,"Rural+Urban",'Clean Data'!$B:$B,YEAR(EDATE(A9,-1)),'Clean Data'!$C:$C,TEXT(EDATE(A9,-1),"mmmm"))-1,"") -> -0.0017730496 | O9: =IFERROR(SUMIFS('Clean Data'!$M:$M,'Clean Data'!$A:$A,"Rural+Urban",'Clean Data'!$B:$B,B9,'Clean Data'!$C:$C,C9)/SUMIFS('Clean Data'!$M:$M,'Clean Data'!$A:$A,"Rural+Urban",'Clean Data'!$B:$B,YEAR(EDATE(A9,-1)),'Clean Data'!$C:$C,TEXT(EDATE(A9,-1),"mmmm"))-1,"") -> -0.0042630938 | P9: =IFERROR(SUMIFS('Clean Data'!$N:$N,'Clean Data'!$A:$A,"Rural+Urban",'Clean Data'!$B:$B,B9,'Clean Data'!$C:$C,C9)/SUMIFS('Clean Data'!$N:$N,'Clean Data'!$A:$A,"Rural+Urban",'Clean Data'!$B:$B,YEAR(EDATE(A9,-1)),'Clean Data'!$C:$C,TEXT(EDATE(A9,-1),"mmmm"))-1,"") -> 0.0064308682 | Q9: =IFERROR(SUMIFS('Clean Data'!$O:$O,'Clean Data'!$A:$A,"Rural+Urban",'Clean Data'!$B:$B,B9,'Clean Data'!$C:$C,C9)/SUMIFS('Clean Data'!$O:$O,'Clean Data'!$A:$A,"Rural+Urban",'Clean Data'!$B:$B,YEAR(EDATE(A9,-1)),'Clean Data'!$C:$C,TEXT(EDATE(A9,-1),"mmmm"))-1,"") -> 0.0041791045 | R9: =IFERROR(SUMIFS('Clean Data'!$P:$P,'Clean Data'!$A:$A,"Rural+Urban",'Clean Data'!$B:$B,B9,'Clean Data'!$C:$C,C9)/SUMIFS('Clean Data'!$P:$P,'Clean Data'!$A:$A,"Rural+Urban",'Clean Data'!$B:$B,YEAR(EDATE(A9,-1)),'Clean Data'!$C:$C,TEXT(EDATE(A9,-1),"mmmm"))-1,"") -> -0.0012746973 | S9: =IFERROR(SUMIFS('Clean Data'!$Q:$Q,'Clean Data'!$A:$A,"Rural+Urban",'Clean Data'!$B:$B,B9,'Clean Data'!$C:$C,C9)/SUMIFS('Clean Data'!$Q:$Q,'Clean Data'!$A:$A,"Rural+Urban",'Clean Data'!$B:$B,YEAR(EDATE(A9,-1)),'Clean Data'!$C:$C,TEXT(EDATE(A9,-1),"mmmm"))-1,"") -> -0.0010621349 | T9: =IFERROR(SUMIFS('Clean Data'!$R:$R,'Clean Data'!$A:$A,"Rural+Urban",'Clean Data'!$B:$B,B9,'Clean Data'!$C:$C,C9)/SUMIFS('Clean Data'!$R:$R,'Clean Data'!$A:$A,"Rural+Urban",'Clean Data'!$B:$B,YEAR(EDATE(A9,-1)),'Clean Data'!$C:$C,TEXT(EDATE(A9,-1),"mmmm"))-1,"") -> 0.0038167939 | U9: =IFERROR(SUMIFS('Clean Data'!$S:$S,'Clean Data'!$A:$A,"Rural+Urban",'Clean Data'!$B:$B,B9,'Clean Data'!$C:$C,C9)/SUMIFS('Clean Data'!$S:$S,'Clean Data'!$A:$A,"Rural+Urban",'Clean Data'!$B:$B,YEAR(EDATE(A9,-1)),'Clean Data'!$C:$C,TEXT(EDATE(A9,-1),"mmmm"))-1,"") -> 0.0033921303 | V9: =IFERROR(SUMIFS('Clean Data'!$T:$T,'Clean Data'!$A:$A,"Rural+Urban",'Clean Data'!$B:$B,B9,'Clean Data'!$C:$C,C9)/SUMIFS('Clean Data'!$T:$T,'Clean Data'!$A:$A,"Rural+Urban",'Clean Data'!$B:$B,YEAR(EDATE(A9,-1)),'Clean Data'!$C:$C,TEXT(EDATE(A9,-1),"mmmm"))-1,"") -> 0.0038510911 | W9: =IFERROR(SUMIFS('Clean Data'!$U:$U,'Clean Data'!$A:$A,"Rural+Urban",'Clean Data'!$B:$B,B9,'Clean Data'!$C:$C,C9)/SUMIFS('Clean Data'!$U:$U,'Clean Data'!$A:$A,"Rural+Urban",'Clean Data'!$B:$B,YEAR(EDATE(A9,-1)),'Clean Data'!$C:$C,TEXT(EDATE(A9,-1),"mmmm"))-1,"") -> 0.00062578223 | X9: =IFERROR(SUMIFS('Clean Data'!$V:$V,'Clean Data'!$A:$A,"Rural+Urban",'Clean Data'!$B:$B,B9,'Clean Data'!$C:$C,C9)/SUMIFS('Clean Data'!$V:$V,'Clean Data'!$A:$A,"Rural+Urban",'Clean Data'!$B:$B,YEAR(EDATE(A9,-1)),'Clean Data'!$C:$C,TEXT(EDATE(A9,-1),"mmmm"))-1,"") -> 0.020341207 | Y9: =IFERROR(SUMIFS('Clean Data'!$W:$W,'Clean Data'!$A:$A,"Rural+Urban",'Clean Data'!$B:$B,B9,'Clean Data'!$C:$C,C9)/SUMIFS('Clean Data'!$W:$W,'Clean Data'!$A:$A,"Rural+Urban",'Clean Data'!$B:$B,YEAR(EDATE(A9,-1)),'Clean Data'!$C:$C,TEXT(EDATE(A9,-1),"mmmm"))-1,"") -> 0.0019880716 | Z9: =IFERROR(SUMIFS('Clean Data'!$X:$X,'Clean Data'!$A:$A,"Rural+Urban",'Clean Data'!$B:$B,B9,'Clean Data'!$C:$C,C9)/SUMIFS('Clean Data'!$X:$X,'Clean Data'!$A:$A,"Rural+Urban",'Clean Data'!$B:$B,YEAR(EDATE(A9,-1)),'Clean Data'!$C:$C,TEXT(EDATE(A9,-1),"mmmm"))-1,"") -> 0.0024798512 | AA9: =IFERROR(SUMIFS('Clean Data'!$Y:$Y,'Clean Data'!$A:$A,"Rural+Urban",'Clean Data'!$B:$B,B9,'Clean Data'!$C:$C,C9)/SUMIFS('Clean Data'!$Y:$Y,'Clean Data'!$A:$A,"Rural+Urban",'Clean Data'!$B:$B,YEAR(EDATE(A9,-1)),'Clean Data'!$C:$C,TEXT(EDATE(A9,-1),"mmmm"))-1,"") -> 0.0075809786 | AB9: =IFERROR(SUMIFS('Clean Data'!$Z:$Z,'Clean Data'!$A:$A,"Rural+Urban",'Clean Data'!$B:$B,B9,'Clean Data'!$C:$C,C9)/SUMIFS('Clean Data'!$Z:$Z,'Clean Data'!$A:$A,"Rural+Urban",'Clean Data'!$B:$B,YEAR(EDATE(A9,-1)),'Clean Data'!$C:$C,TEXT(EDATE(A9,-1),"mmmm"))-1,"") -> 0.0072607261 | AC9: =IFERROR(SUMIFS('Clean Data'!$AA:$AA,'Clean Data'!$A:$A,"Rural+Urban",'Clean Data'!$B:$B,B9,'Clean Data'!$C:$C,C9)/SUMIFS('Clean Data'!$AA:$AA,'Clean Data'!$A:$A,"Rural+Urban",'Clean Data'!$B:$B,YEAR(EDATE(A9,-1)),'Clean Data'!$C:$C,TEXT(EDATE(A9,-1),"mmmm"))-1,"") -> 0.0043887147 | AD9: =IFERROR(SUMIFS('Clean Data'!$AB:$AB,'Clean Data'!$A:$A,"Rural+Urban",'Clean Data'!$B:$B,B9,'Clean Data'!$C:$C,C9)/SUMIFS('Clean Data'!$AB:$AB,'Clean Data'!$A:$A,"Rural+Urban",'Clean Data'!$B:$B,YEAR(EDATE(A9,-1)),'Clean Data'!$C:$C,TEXT(EDATE(A9,-1),"mmmm"))-1,"") -> -0.01283697 | AE9: =IFERROR(SUMIFS('Clean Data'!$AC:$AC,'Clean Data'!$A:$A,"Rural+Urban",'Clean Data'!$B:$B,B9,'Clean Data'!$C:$C,C9)/SUMIFS('Clean Data'!$AC:$AC,'Clean Data'!$A:$A,"Rural+Urban",'Clean Data'!$B:$B,YEAR(EDATE(A9,-1)),'Clean Data'!$C:$C,TEXT(EDATE(A9,-1),"mmmm"))-1,"") -> 0.0026075619 | AF9: =IFERROR(SUMIFS('Clean Data'!$AD:$AD,'Clean Data'!$A:$A,"Rural+Urban",'Clean Data'!$B:$B,B9,'Clean Data'!$C:$C,C9)/SUMIFS('Clean Data'!$AD:$AD,'Clean Data'!$A:$A,"Rural+Urban",'Clean Data'!$B:$B,YEAR(EDATE(A9,-1)),'Clean Data'!$C:$C,TEXT(EDATE(A9,-1),"mmmm"))-1,"") -> 0.0012771392
A10: 44287 | B10: 2021 | C10: April | D10: 63.4 | E10: =IFERROR(D10/D9-1,"") -> -0.020546887 | F10: =IFERROR(SUMIFS('Clean Data'!$D:$D,'Clean Data'!$A:$A,"Rural+Urban",'Clean Data'!$B:$B,B10,'Clean Data'!$C:$C,C10)/SUMIFS('Clean Data'!$D:$D,'Clean Data'!$A:$A,"Rural+Urban",'Clean Data'!$B:$B,YEAR(EDATE(A10,-1)),'Clean Data'!$C:$C,TEXT(EDATE(A10,-1),"mmmm"))-1,"") -> 0.0013879251 | G10: =IFERROR(SUMIFS('Clean Data'!$E:$E,'Clean Data'!$A:$A,"Rural+Urban",'Clean Data'!$B:$B,B10,'Clean Data'!$C:$C,C10)/SUMIFS('Clean Data'!$E:$E,'Clean Data'!$A:$A,"Rural+Urban",'Clean Data'!$B:$B,YEAR(EDATE(A10,-1)),'Clean Data'!$C:$C,TEXT(EDATE(A10,-1),"mmmm"))-1,"") -> 0.030176899 | H10: =IFERROR(SUMIFS('Clean Data'!$F:$F,'Clean Data'!$A:$A,"Rural+Urban",'Clean Data'!$B:$B,B10,'Clean Data'!$C:$C,C10)/SUMIFS('Clean Data'!$F:$F,'Clean Data'!$A:$A,"Rural+Urban",'Clean Data'!$B:$B,YEAR(EDATE(A10,-1)),'Clean Data'!$C:$C,TEXT(EDATE(A10,-1),"mmmm"))-1,"") -> 0.0048840049 | I10: =IFERROR(SUMIFS('Clean Data'!$G:$G,'Clean Data'!$A:$A,"Rural+Urban",'Clean Data'!$B:$B,B10,'Clean Data'!$C:$C,C10)/SUMIFS('Clean Data'!$G:$G,'Clean Data'!$A:$A,"Rural+Urban",'Clean Data'!$B:$B,YEAR(EDATE(A10,-1)),'Clean Data'!$C:$C,TEXT(EDATE(A10,-1),"mmmm"))-1,"") -> 0.003227889 | J10: =IFERROR(SUMIFS('Clean Data'!$H:$H,'Clean Data'!$A:$A,"Rural+Urban",'Clean Data'!$B:$B,B10,'Clean Data'!$C:$C,C10)/SUMIFS('Clean Data'!$H:$H,'Clean Data'!$A:$A,"Rural+Urban",'Clean Data'!$B:$B,YEAR(EDATE(A10,-1)),'Clean Data'!$C:$C,TEXT(EDATE(A10,-1),"mmmm"))-1,"") -> 0.037827944 | K10: =IFERROR(SUMIFS('Clean Data'!$I:$I,'Clean Data'!$A:$A,"Rural+Urban",'Clean Data'!$B:$B,B10,'Clean Data'!$C:$C,C10)/SUMIFS('Clean Data'!$I:$I,'Clean Data'!$A:$A,"Rural+Urban",'Clean Data'!$B:$B,YEAR(EDATE(A10,-1)),'Clean Data'!$C:$C,TEXT(EDATE(A10,-1),"mmmm"))-1,"") -> 0.069616135 | L10: =IFERROR(SUMIFS('Clean Data'!$J:$J,'Clean Data'!$A:$A,"Rural+Urban",'Clean Data'!$B:$B,B10,'Clean Data'!$C:$C,C10)/SUMIFS('Clean Data'!$J:$J,'Clean Data'!$A:$A,"Rural+Urban",'Clean Data'!$B:$B,YEAR(EDATE(A10,-1)),'Clean Data'!$C:$C,TEXT(EDATE(A10,-1),"mmmm"))-1,"") -> -0.036120401 | M10: =IFERROR(SUMIFS('Clean Data'!$K:$K,'Clean Data'!$A:$A,"Rural+Urban",'Clean Data'!$B:$B,B10,'Clean Data'!$C:$C,C10)/SUMIFS('Clean Data'!$K:$K,'Clean Data'!$A:$A,"Rural+Urban",'Clean Data'!$B:$B,YEAR(EDATE(A10,-1)),'Clean Data'!$C:$C,TEXT(EDATE(A10,-1),"mmmm"))-1,"") -> 0.011889862 | N10: =IFERROR(SUMIFS('Clean Data'!$L:$L,'Clean Data'!$A:$A,"Rural+Urban",'Clean Data'!$B:$B,B10,'Clean Data'!$C:$C,C10)/SUMIFS('Clean Data'!$L:$L,'Clean Data'!$A:$A,"Rural+Urban",'Clean Data'!$B:$B,YEAR(EDATE(A10,-1)),'Clean Data'!$C:$C,TEXT(EDATE(A10,-1),"mmmm"))-1,"") -> 0.0044404973 | O10: =IFERROR(SUMIFS('Clean Data'!$M:$M,'Clean Data'!$A:$A,"Rural+Urban",'Clean Data'!$B:$B,B10,'Clean Data'!$C:$C,C10)/SUMIFS('Clean Data'!$M:$M,'Clean Data'!$A:$A,"Rural+Urban",'Clean Data'!$B:$B,YEAR(EDATE(A10,-1)),'Clean Data'!$C:$C,TEXT(EDATE(A10,-1),"mmmm"))-1,"") -> 0.0024464832 | P10: =IFERROR(SUMIFS('Clean Data'!$N:$N,'Clean Data'!$A:$A,"Rural+Urban",'Clean Data'!$B:$B,B10,'Clean Data'!$C:$C,C10)/SUMIFS('Clean Data'!$N:$N,'Clean Data'!$A:$A,"Rural+Urban",'Clean Data'!$B:$B,YEAR(EDATE(A10,-1)),'Clean Data'!$C:$C,TEXT(EDATE(A10,-1),"mmmm"))-1,"") -> 0.007028754 | Q10: =IFERROR(SUMIFS('Clean Data'!$O:$O,'Clean Data'!$A:$A,"Rural+Urban",'Clean Data'!$B:$B,B10,'Clean Data'!$C:$C,C10)/SUMIFS('Clean Data'!$O:$O,'Clean Data'!$A:$A,"Rural+Urban",'Clean Data'!$B:$B,YEAR(EDATE(A10,-1)),'Clean Data'!$C:$C,TEXT(EDATE(A10,-1),"mmmm"))-1,"") -> 0.0041617122 | R10: =IFERROR(SUMIFS('Clean Data'!$P:$P,'Clean Data'!$A:$A,"Rural+Urban",'Clean Data'!$B:$B,B10,'Clean Data'!$C:$C,C10)/SUMIFS('Clean Data'!$P:$P,'Clean Data'!$A:$A,"Rural+Urban",'Clean Data'!$B:$B,YEAR(EDATE(A10,-1)),'Clean Data'!$C:$C,TEXT(EDATE(A10,-1),"mmmm"))-1,"") -> 0.0082961072 | S10: =IFERROR(SUMIFS('Clean Data'!$Q:$Q,'Clean Data'!$A:$A,"Rural+Urban",'Clean Data'!$B:$B,B10,'Clean Data'!$C:$C,C10)/SUMIFS('Clean Data'!$Q:$Q,'Clean Data'!$A:$A,"Rural+Urban",'Clean Data'!$B:$B,YEAR(EDATE(A10,-1)),'Clean Data'!$C:$C,TEXT(EDATE(A10,-1),"mmmm"))-1,"") -> 0.0037214248 | T10: =IFERROR(SUMIFS('Clean Data'!$R:$R,'Clean Data'!$A:$A,"Rural+Urban",'Clean Data'!$B:$B,B10,'Clean Data'!$C:$C,C10)/SUMIFS('Clean Data'!$R:$R,'Clean Data'!$A:$A,"Rural+Urban",'Clean Data'!$B:$B,YEAR(EDATE(A10,-1)),'Clean Data'!$C:$C,TEXT(EDATE(A10,-1),"mmmm"))-1,"") -> 0.0063371356 | U10: =IFERROR(SUMIFS('Clean Data'!$S:$S,'Clean Data'!$A:$A,"Rural+Urban",'Clean Data'!$B:$B,B10,'Clean Data'!$C:$C,C10)/SUMIFS('Clean Data'!$S:$S,'Clean Data'!$A:$A,"Rural+Urban",'Clean Data'!$B:$B,YEAR(EDATE(A10,-1)),'Clean Data'!$C:$C,TEXT(EDATE(A10,-1),"mmmm"))-1,"") -> 0.0040567951 | V10: =IFERROR(SUMIFS('Clean Data'!$T:$T,'Clean Data'!$A:$A,"Rural+Urban",'Clean Data'!$B:$B,B10,'Clean Data'!$C:$C,C10)/SUMIFS('Clean Data'!$T:$T,'Clean Data'!$A:$A,"Rural+Urban",'Clean Data'!$B:$B,YEAR(EDATE(A10,-1)),'Clean Data'!$C:$C,TEXT(EDATE(A10,-1),"mmmm"))-1,"") -> 0.0057544757 | W10: =IFERROR(SUMIFS('Clean Data'!$U:$U,'Clean Data'!$A:$A,"Rural+Urban",'Clean Data'!$B:$B,B10,'Clean Data'!$C:$C,C10)/SUMIFS('Clean Data'!$U:$U,'Clean Data'!$A:$A,"Rural+Urban",'Clean Data'!$B:$B,YEAR(EDATE(A10,-1)),'Clean Data'!$C:$C,TEXT(EDATE(A10,-1),"mmmm"))-1,"") -> 0.009380863 | X10: =IFERROR(SUMIFS('Clean Data'!$V:$V,'Clean Data'!$A:$A,"Rural+Urban",'Clean Data'!$B:$B,B10,'Clean Data'!$C:$C,C10)/SUMIFS('Clean Data'!$V:$V,'Clean Data'!$A:$A,"Rural+Urban",'Clean Data'!$B:$B,YEAR(EDATE(A10,-1)),'Clean Data'!$C:$C,TEXT(EDATE(A10,-1),"mmmm"))-1,"") -> 0.00064308682 | Y10: =IFERROR(SUMIFS('Clean Data'!$W:$W,'Clean Data'!$A:$A,"Rural+Urban",'Clean Data'!$B:$B,B10,'Clean Data'!$C:$C,C10)/SUMIFS('Clean Data'!$W:$W,'Clean Data'!$A:$A,"Rural+Urban",'Clean Data'!$B:$B,YEAR(EDATE(A10,-1)),'Clean Data'!$C:$C,TEXT(EDATE(A10,-1),"mmmm"))-1,"") -> 0.003968254 | Z10: =IFERROR(SUMIFS('Clean Data'!$X:$X,'Clean Data'!$A:$A,"Rural+Urban",'Clean Data'!$B:$B,B10,'Clean Data'!$C:$C,C10)/SUMIFS('Clean Data'!$X:$X,'Clean Data'!$A:$A,"Rural+Urban",'Clean Data'!$B:$B,YEAR(EDATE(A10,-1)),'Clean Data'!$C:$C,TEXT(EDATE(A10,-1),"mmmm"))-1,"") -> 0.0037105751 | AA10: =IFERROR(SUMIFS('Clean Data'!$Y:$Y,'Clean Data'!$A:$A,"Rural+Urban",'Clean Data'!$B:$B,B10,'Clean Data'!$C:$C,C10)/SUMIFS('Clean Data'!$Y:$Y,'Clean Data'!$A:$A,"Rural+Urban",'Clean Data'!$B:$B,YEAR(EDATE(A10,-1)),'Clean Data'!$C:$C,TEXT(EDATE(A10,-1),"mmmm"))-1,"") -> 0.0027359781 | AB10: =IFERROR(SUMIFS('Clean Data'!$Z:$Z,'Clean Data'!$A:$A,"Rural+Urban",'Clean Data'!$B:$B,B10,'Clean Data'!$C:$C,C10)/SUMIFS('Clean Data'!$Z:$Z,'Clean Data'!$A:$A,"Rural+Urban",'Clean Data'!$B:$B,YEAR(EDATE(A10,-1)),'Clean Data'!$C:$C,TEXT(EDATE(A10,-1),"mmmm"))-1,"") -> 0.003931848 | AC10: =IFERROR(SUMIFS('Clean Data'!$AA:$AA,'Clean Data'!$A:$A,"Rural+Urban",'Clean Data'!$B:$B,B10,'Clean Data'!$C:$C,C10)/SUMIFS('Clean Data'!$AA:$AA,'Clean Data'!$A:$A,"Rural+Urban",'Clean Data'!$B:$B,YEAR(EDATE(A10,-1)),'Clean Data'!$C:$C,TEXT(EDATE(A10,-1),"mmmm"))-1,"") -> 0.00062421973 | AD10: =IFERROR(SUMIFS('Clean Data'!$AB:$AB,'Clean Data'!$A:$A,"Rural+Urban",'Clean Data'!$B:$B,B10,'Clean Data'!$C:$C,C10)/SUMIFS('Clean Data'!$AB:$AB,'Clean Data'!$A:$A,"Rural+Urban",'Clean Data'!$B:$B,YEAR(EDATE(A10,-1)),'Clean Data'!$C:$C,TEXT(EDATE(A10,-1),"mmmm"))-1,"") -> 0.010403121 | AE10: =IFERROR(SUMIFS('Clean Data'!$AC:$AC,'Clean Data'!$A:$A,"Rural+Urban",'Clean Data'!$B:$B,B10,'Clean Data'!$C:$C,C10)/SUMIFS('Clean Data'!$AC:$AC,'Clean Data'!$A:$A,"Rural+Urban",'Clean Data'!$B:$B,YEAR(EDATE(A10,-1)),'Clean Data'!$C:$C,TEXT(EDATE(A10,-1),"mmmm"))-1,"") -> 0.0039011704 | AF10: =IFERROR(SUMIFS('Clean Data'!$AD:$AD,'Clean Data'!$A:$A,"Rural+Urban",'Clean Data'!$B:$B,B10,'Clean Data'!$C:$C,C10)/SUMIFS('Clean Data'!$AD:$AD,'Clean Data'!$A:$A,"Rural+Urban",'Clean Data'!$B:$B,YEAR(EDATE(A10,-1)),'Clean Data'!$C:$C,TEXT(EDATE(A10,-1),"mmmm"))-1,"") -> 0.006377551
